Workbook

Sheet Draft Board
A1: 2026 TD/FG-Only Draft Board — ranked by Adjusted VOR
A2: Rank | B2: Pos | C2: Player | D2: Tm | E2: P | F2: PassTD | G2: RushTD | H2: RecTD | I2: FG | J2: PAT | K2: DefTD | L2: Saf | M2: Points | N2: VOR | O2: Adj VOR | P2: Conf | Q2: Notes
A3: 1 | B3: QB1 | C3: Josh Allen | D3: BUF | E3: QB | F3: 27 | G3: 12 | M3: =F3*Settings!$B$4+G3*Settings!$B$5+H3*Settings!$B$6+I3*Settings!$B$7+J3*Settings!$B$8+K3*Settings!$B$9+L3*Settings!$B$10 | N3: =M3-INDEX(Settings!$G$4:$G$9,MATCH($E3,Settings!$F$4:$F$9,0)) | O3: =N3*INDEX(Settings!$H$4:$H$9,MATCH($E3,Settings!$F$4:$F$9,0)) | P3: HIGH | Q3: TIER OF ONE. 12 rush TDs alone outscore 20 of 40 QBs in total
A4: 2 | B4: RB1 | C4: Jahmyr Gibbs | D4: DET | E4: RB | G4: 13.4 | H4: 3.8 | M4: =F4*Settings!$B$4+G4*Settings!$B$5+H4*Settings!$B$6+I4*Settings!$B$7+J4*Settings!$B$8+K4*Settings!$B$9+L4*Settings!$B$10 | N4: =M4-INDEX(Settings!$G$4:$G$9,MATCH($E4,Settings!$F$4:$F$9,0)) | O4: =N4*INDEX(Settings!$H$4:$H$9,MATCH($E4,Settings!$F$4:$F$9,0)) | P4: HIGH | Q4: Overall RB1
A5: 3 | B5: RB2 | C5: Jonathan Taylor | D5: IND | E5: RB | G5: 12.2 | H5: 1.3 | M5: =F5*Settings!$B$4+G5*Settings!$B$5+H5*Settings!$B$6+I5*Settings!$B$7+J5*Settings!$B$8+K5*Settings!$B$9+L5*Settings!$B$10 | N5: =M5-INDEX(Settings!$G$4:$G$9,MATCH($E5,Settings!$F$4:$F$9,0)) | O5: =N5*INDEX(Settings!$H$4:$H$9,MATCH($E5,Settings!$F$4:$F$9,0)) | P5: HIGH | Q5: True goal-line back
A6: 4 | B6: RB3 | C6: Christian McCaffrey | D6: SF | E6: RB | G6: 9 | H6: 4.4 | M6: =F6*Settings!$B$4+G6*Settings!$B$5+H6*Settings!$B$6+I6*Settings!$B$7+J6*Settings!$B$8+K6*Settings!$B$9+L6*Settings!$B$10 | N6: =M6-INDEX(Settings!$G$4:$G$9,MATCH($E6,Settings!$F$4:$F$9,0)) | O6: =N6*INDEX(Settings!$H$4:$H$9,MATCH($E6,Settings!$F$4:$F$9,0)) | P6: HIGH | Q6: Goal-line yes
A7: 5 | B7: RB4 | C7: Derrick Henry | D7: BAL | E7: RB | G7: 12.8 | H7: 0.6 | M7: =F7*Settings!$B$4+G7*Settings!$B$5+H7*Settings!$B$6+I7*Settings!$B$7+J7*Settings!$B$8+K7*Settings!$B$9+L7*Settings!$B$10 | N7: =M7-INDEX(Settings!$G$4:$G$9,MATCH($E7,Settings!$F$4:$F$9,0)) | O7: =N7*INDEX(Settings!$H$4:$H$9,MATCH($E7,Settings!$F$4:$F$9,0)) | P7: HIGH | Q7: Vegas HIGHER than consensus here
A8: 6 | B8: QB2 | C8: Jalen Hurts | D8: PHI | E8: QB | F8: 24 | G8: 8.5 | M8: =F8*Settings!$B$4+G8*Settings!$B$5+H8*Settings!$B$6+I8*Settings!$B$7+J8*Settings!$B$8+K8*Settings!$B$9+L8*Settings!$B$10 | N8: =M8-INDEX(Settings!$G$4:$G$9,MATCH($E8,Settings!$F$4:$F$9,0)) | O8: =N8*INDEX(Settings!$H$4:$H$9,MATCH($E8,Settings!$F$4:$F$9,0)) | P8: HIGH | Q8: Tush push survived 2026 rules vote; goal-line sneak intact
A9: 7 | B9: RB5 | C9: James Cook III | D9: BUF | E9: RB | G9: 10.8 | H9: 1.8 | M9: =F9*Settings!$B$4+G9*Settings!$B$5+H9*Settings!$B$6+I9*Settings!$B$7+J9*Settings!$B$8+K9*Settings!$B$9+L9*Settings!$B$10 | N9: =M9-INDEX(Settings!$G$4:$G$9,MATCH($E9,Settings!$F$4:$F$9,0)) | O9: =N9*INDEX(Settings!$H$4:$H$9,MATCH($E9,Settings!$F$4:$F$9,0)) | P9: HIGH | Q9: Allen vulture tax already priced into line
A10: 8 | B10: RB6 | C10: Josh Jacobs | D10: GB | E10: RB | G10: 11.3 | H10: 1.3 | M10: =F10*Settings!$B$4+G10*Settings!$B$5+H10*Settings!$B$6+I10*Settings!$B$7+J10*Settings!$B$8+K10*Settings!$B$9+L10*Settings!$B$10 | N10: =M10-INDEX(Settings!$G$4:$G$9,MATCH($E10,Settings!$F$4:$F$9,0)) | O10: =N10*INDEX(Settings!$H$4:$H$9,MATCH($E10,Settings!$F$4:$F$9,0)) | P10: HIGH | Q10: Goal-line yes
A11: 9 | B11: WR1 | C11: Ja'Marr Chase | D11: CIN | E11: WR | G11: 0.1 | H11: 10.9 | M11: =F11*Settings!$B$4+G11*Settings!$B$5+H11*Settings!$B$6+I11*Settings!$B$7+J11*Settings!$B$8+K11*Settings!$B$9+L11*Settings!$B$10 | N11: =M11-INDEX(Settings!$G$4:$G$9,MATCH($E11,Settings!$F$4:$F$9,0)) | O11: =N11*INDEX(Settings!$H$4:$H$9,MATCH($E11,Settings!$F$4:$F$9,0)) | P11: HIGH
A12: 10 | B12: RB7 | C12: Bijan Robinson | D12: ATL | E12: RB | G12: 8.7 | H12: 3.3 | M12: =F12*Settings!$B$4+G12*Settings!$B$5+H12*Settings!$B$6+I12*Settings!$B$7+J12*Settings!$B$8+K12*Settings!$B$9+L12*Settings!$B$10 | N12: =M12-INDEX(Settings!$G$4:$G$9,MATCH($E12,Settings!$F$4:$F$9,0)) | O12: =N12*INDEX(Settings!$H$4:$H$9,MATCH($E12,Settings!$F$4:$F$9,0)) | P12: HIGH | Q12: CAUTION only 48 pct of inside-5 carries in 2025
A13: 11 | B13: RB8 | C13: Kyren Williams | D13: LAR | E13: RB | G13: 10.1 | H13: 1.8 | M13: =F13*Settings!$B$4+G13*Settings!$B$5+H13*Settings!$B$6+I13*Settings!$B$7+J13*Settings!$B$8+K13*Settings!$B$9+L13*Settings!$B$10 | N13: =M13-INDEX(Settings!$G$4:$G$9,MATCH($E13,Settings!$F$4:$F$9,0)) | O13: =N13*INDEX(Settings!$H$4:$H$9,MATCH($E13,Settings!$F$4:$F$9,0)) | P13: HIGH | Q13: Alternates drives with Corum
A14: 12 | B14: RB9 | C14: Javonte Williams | D14: DAL | E14: RB | G14: 10.6 | H14: 1.2 | M14: =F14*Settings!$B$4+G14*Settings!$B$5+H14*Settings!$B$6+I14*Settings!$B$7+J14*Settings!$B$8+K14*Settings!$B$9+L14*Settings!$B$10 | N14: =M14-INDEX(Settings!$G$4:$G$9,MATCH($E14,Settings!$F$4:$F$9,0)) | O14: =N14*INDEX(Settings!$H$4:$H$9,MATCH($E14,Settings!$F$4:$F$9,0)) | P14: HIGH | Q14: Goal-line yes
A15: 13 | B15: WR2 | C15: Davante Adams | D15: LAR | E15: WR | H15: 10.3 | M15: =F15*Settings!$B$4+G15*Settings!$B$5+H15*Settings!$B$6+I15*Settings!$B$7+J15*Settings!$B$8+K15*Settings!$B$9+L15*Settings!$B$10 | N15: =M15-INDEX(Settings!$G$4:$G$9,MATCH($E15,Settings!$F$4:$F$9,0)) | O15: =N15*INDEX(Settings!$H$4:$H$9,MATCH($E15,Settings!$F$4:$F$9,0)) | P15: HIGH
A16: 14 | B16: WR3 | C16: Amon-Ra St. Brown | D16: DET | E16: WR | G16: 0.1 | H16: 10.2 | M16: =F16*Settings!$B$4+G16*Settings!$B$5+H16*Settings!$B$6+I16*Settings!$B$7+J16*Settings!$B$8+K16*Settings!$B$9+L16*Settings!$B$10 | N16: =M16-INDEX(Settings!$G$4:$G$9,MATCH($E16,Settings!$F$4:$F$9,0)) | O16: =N16*INDEX(Settings!$H$4:$H$9,MATCH($E16,Settings!$F$4:$F$9,0)) | P16: HIGH
A17: 15 | B17: WR4 | C17: Puka Nacua | D17: LAR | E17: WR | G17: 0.6 | H17: 9.3 | M17: =F17*Settings!$B$4+G17*Settings!$B$5+H17*Settings!$B$6+I17*Settings!$B$7+J17*Settings!$B$8+K17*Settings!$B$9+L17*Settings!$B$10 | N17: =M17-INDEX(Settings!$G$4:$G$9,MATCH($E17,Settings!$F$4:$F$9,0)) | O17: =N17*INDEX(Settings!$H$4:$H$9,MATCH($E17,Settings!$F$4:$F$9,0)) | P17: HIGH
A18: 16 | B18: RB10 | C18: Omarion Hampton | D18: LAC | E18: RB | G18: 9.2 | H18: 1.9 | M18: =F18*Settings!$B$4+G18*Settings!$B$5+H18*Settings!$B$6+I18*Settings!$B$7+J18*Settings!$B$8+K18*Settings!$B$9+L18*Settings!$B$10 | N18: =M18-INDEX(Settings!$G$4:$G$9,MATCH($E18,Settings!$F$4:$F$9,0)) | O18: =N18*INDEX(Settings!$H$4:$H$9,MATCH($E18,Settings!$F$4:$F$9,0)) | P18: HIGH | Q18: Goal-line yes
A19: 17 | B19: K1 | C19: Jason Myers | D19: SEA | E19: K | I19: 39 | J19: 50 | M19: =F19*Settings!$B$4+G19*Settings!$B$5+H19*Settings!$B$6+I19*Settings!$B$7+J19*Settings!$B$8+K19*Settings!$B$9+L19*Settings!$B$10 | N19: =M19-INDEX(Settings!$G$4:$G$9,MATCH($E19,Settings!$F$4:$F$9,0)) | O19: =N19*INDEX(Settings!$H$4:$H$9,MATCH($E19,Settings!$F$4:$F$9,0)) | P19: HIGH | Q19: Led NFL 43 FGM 2025 on 48 FGA
A20: 18 | B20: RB11 | C20: Chase Brown | D20: CIN | E20: RB | G20: 7.4 | H20: 3.6 | M20: =F20*Settings!$B$4+G20*Settings!$B$5+H20*Settings!$B$6+I20*Settings!$B$7+J20*Settings!$B$8+K20*Settings!$B$9+L20*Settings!$B$10 | N20: =M20-INDEX(Settings!$G$4:$G$9,MATCH($E20,Settings!$F$4:$F$9,0)) | O20: =N20*INDEX(Settings!$H$4:$H$9,MATCH($E20,Settings!$F$4:$F$9,0)) | P20: HIGH | Q20: Vegas LOWER than consensus
A21: 19 | B21: RB12 | C21: Saquon Barkley | D21: PHI | E21: RB | G21: 8.6 | H21: 2.1 | M21: =F21*Settings!$B$4+G21*Settings!$B$5+H21*Settings!$B$6+I21*Settings!$B$7+J21*Settings!$B$8+K21*Settings!$B$9+L21*Settings!$B$10 | N21: =M21-INDEX(Settings!$G$4:$G$9,MATCH($E21,Settings!$F$4:$F$9,0)) | O21: =N21*INDEX(Settings!$H$4:$H$9,MATCH($E21,Settings!$F$4:$F$9,0)) | P21: HIGH | Q21: TRAP: Hurts vultures 8.5 rush TDs; not priced in
A22: 20 | B22: RB13 | C22: Kenneth Walker III | D22: KC | E22: RB | G22: 8.9 | H22: 1.6 | M22: =F22*Settings!$B$4+G22*Settings!$B$5+H22*Settings!$B$6+I22*Settings!$B$7+J22*Settings!$B$8+K22*Settings!$B$9+L22*Settings!$B$10 | N22: =M22-INDEX(Settings!$G$4:$G$9,MATCH($E22,Settings!$F$4:$F$9,0)) | O22: =N22*INDEX(Settings!$H$4:$H$9,MATCH($E22,Settings!$F$4:$F$9,0)) | P22: HIGH | Q22: New to KC; no established GL hierarchy
A23: 21 | B23: TE1 | C23: Brock Bowers | D23: LV | E23: TE | G23: 0.1 | H23: 6.8 | M23: =F23*Settings!$B$4+G23*Settings!$B$5+H23*Settings!$B$6+I23*Settings!$B$7+J23*Settings!$B$8+K23*Settings!$B$9+L23*Settings!$B$10 | N23: =M23-INDEX(Settings!$G$4:$G$9,MATCH($E23,Settings!$F$4:$F$9,0)) | O23: =N23*INDEX(Settings!$H$4:$H$9,MATCH($E23,Settings!$F$4:$F$9,0)) | P23: HIGH
A24: 22 | B24: TE2 | C24: Mark Andrews | D24: BAL | E24: TE | G24: 0.3 | H24: 6.5 | M24: =F24*Settings!$B$4+G24*Settings!$B$5+H24*Settings!$B$6+I24*Settings!$B$7+J24*Settings!$B$8+K24*Settings!$B$9+L24*Settings!$B$10 | N24: =M24-INDEX(Settings!$G$4:$G$9,MATCH($E24,Settings!$F$4:$F$9,0)) | O24: =N24*INDEX(Settings!$H$4:$H$9,MATCH($E24,Settings!$F$4:$F$9,0)) | P24: HIGH
A25: 23 | B25: K2 | C25: Ka'imi Fairbairn | D25: HOU | E25: K | I25: 39 | J25: 39 | M25: =F25*Settings!$B$4+G25*Settings!$B$5+H25*Settings!$B$6+I25*Settings!$B$7+J25*Settings!$B$8+K25*Settings!$B$9+L25*Settings!$B$10 | N25: =M25-INDEX(Settings!$G$4:$G$9,MATCH($E25,Settings!$F$4:$F$9,0)) | O25: =N25*INDEX(Settings!$H$4:$H$9,MATCH($E25,Settings!$F$4:$F$9,0)) | P25: HIGH | Q25: Best FG-lean in league; HOU led NFL 52 FGA
A26: 24 | B26: QB3 | C26: Joe Burrow | D26: CIN | E26: QB | F26: 33 | G26: 1.5 | M26: =F26*Settings!$B$4+G26*Settings!$B$5+H26*Settings!$B$6+I26*Settings!$B$7+J26*Settings!$B$8+K26*Settings!$B$9+L26*Settings!$B$10 | N26: =M26-INDEX(Settings!$G$4:$G$9,MATCH($E26,Settings!$F$4:$F$9,0)) | O26: =N26*INDEX(Settings!$H$4:$H$9,MATCH($E26,Settings!$F$4:$F$9,0)) | P26: HIGH | Q26: Volume passer; CIN 26.0 implied pts
A27: 25 | B27: QB4 | C27: Drake Maye | D27: NE | E27: QB | F27: 28 | G27: 4 | M27: =F27*Settings!$B$4+G27*Settings!$B$5+H27*Settings!$B$6+I27*Settings!$B$7+J27*Settings!$B$8+K27*Settings!$B$9+L27*Settings!$B$10 | N27: =M27-INDEX(Settings!$G$4:$G$9,MATCH($E27,Settings!$F$4:$F$9,0)) | O27: =N27*INDEX(Settings!$H$4:$H$9,MATCH($E27,Settings!$F$4:$F$9,0)) | P27: HIGH | Q27: NE 10.5 win total
A28: 26 | B28: WR5 | C28: CeeDee Lamb | D28: DAL | E28: WR | G28: 0.1 | H28: 8.3 | M28: =F28*Settings!$B$4+G28*Settings!$B$5+H28*Settings!$B$6+I28*Settings!$B$7+J28*Settings!$B$8+K28*Settings!$B$9+L28*Settings!$B$10 | N28: =M28-INDEX(Settings!$G$4:$G$9,MATCH($E28,Settings!$F$4:$F$9,0)) | O28: =N28*INDEX(Settings!$H$4:$H$9,MATCH($E28,Settings!$F$4:$F$9,0)) | P28: HIGH
A29: 27 | B29: K3 | C29: Brandon Aubrey | D29: DAL | E29: K | I29: 35 | J29: 49 | M29: =F29*Settings!$B$4+G29*Settings!$B$5+H29*Settings!$B$6+I29*Settings!$B$7+J29*Settings!$B$8+K29*Settings!$B$9+L29*Settings!$B$10 | N29: =M29-INDEX(Settings!$G$4:$G$9,MATCH($E29,Settings!$F$4:$F$9,0)) | O29: =N29*INDEX(Settings!$H$4:$H$9,MATCH($E29,Settings!$F$4:$F$9,0)) | P29: HIGH
A30: 28 | B30: WR6 | C30: Jaxon Smith-Njigba | D30: SEA | E30: WR | G30: 0.1 | H30: 8.2 | M30: =F30*Settings!$B$4+G30*Settings!$B$5+H30*Settings!$B$6+I30*Settings!$B$7+J30*Settings!$B$8+K30*Settings!$B$9+L30*Settings!$B$10 | N30: =M30-INDEX(Settings!$G$4:$G$9,MATCH($E30,Settings!$F$4:$F$9,0)) | O30: =N30*INDEX(Settings!$H$4:$H$9,MATCH($E30,Settings!$F$4:$F$9,0)) | P30: HIGH
A31: 29 | B31: K4 | C31: Blake Grupe | D31: IND | E31: K | I31: 34 | J31: 51 | M31: =F31*Settings!$B$4+G31*Settings!$B$5+H31*Settings!$B$6+I31*Settings!$B$7+J31*Settings!$B$8+K31*Settings!$B$9+L31*Settings!$B$10 | N31: =M31-INDEX(Settings!$G$4:$G$9,MATCH($E31,Settings!$F$4:$F$9,0)) | O31: =N31*INDEX(Settings!$H$4:$H$9,MATCH($E31,Settings!$F$4:$F$9,0)) | P31: MEDIUM | Q31: Shrader listed as backup
A32: 30 | B32: WR7 | C32: Rashee Rice | D32: KC | E32: WR | G32: 0.3 | H32: 7.9 | M32: =F32*Settings!$B$4+G32*Settings!$B$5+H32*Settings!$B$6+I32*Settings!$B$7+J32*Settings!$B$8+K32*Settings!$B$9+L32*Settings!$B$10 | N32: =M32-INDEX(Settings!$G$4:$G$9,MATCH($E32,Settings!$F$4:$F$9,0)) | O32: =N32*INDEX(Settings!$H$4:$H$9,MATCH($E32,Settings!$F$4:$F$9,0)) | P32: HIGH
A33: 31 | B33: WR8 | C33: Tee Higgins | D33: CIN | E33: WR | H33: 8.2 | M33: =F33*Settings!$B$4+G33*Settings!$B$5+H33*Settings!$B$6+I33*Settings!$B$7+J33*Settings!$B$8+K33*Settings!$B$9+L33*Settings!$B$10 | N33: =M33-INDEX(Settings!$G$4:$G$9,MATCH($E33,Settings!$F$4:$F$9,0)) | O33: =N33*INDEX(Settings!$H$4:$H$9,MATCH($E33,Settings!$F$4:$F$9,0)) | P33: HIGH
A34: 32 | B34: TE3 | C34: Trey McBride | D34: ARI | E34: TE | H34: 6.2 | M34: =F34*Settings!$B$4+G34*Settings!$B$5+H34*Settings!$B$6+I34*Settings!$B$7+J34*Settings!$B$8+K34*Settings!$B$9+L34*Settings!$B$10 | N34: =M34-INDEX(Settings!$G$4:$G$9,MATCH($E34,Settings!$F$4:$F$9,0)) | O34: =N34*INDEX(Settings!$H$4:$H$9,MATCH($E34,Settings!$F$4:$F$9,0)) | P34: HIGH
A35: 33 | B35: QB5 | C35: Trevor Lawrence | D35: JAX | E35: QB | F35: 26 | G35: 4.5 | M35: =F35*Settings!$B$4+G35*Settings!$B$5+H35*Settings!$B$6+I35*Settings!$B$7+J35*Settings!$B$8+K35*Settings!$B$9+L35*Settings!$B$10 | N35: =M35-INDEX(Settings!$G$4:$G$9,MATCH($E35,Settings!$F$4:$F$9,0)) | O35: =N35*INDEX(Settings!$H$4:$H$9,MATCH($E35,Settings!$F$4:$F$9,0)) | P35: HIGH
A36: 34 | B36: QB6 | C36: Matthew Stafford | D36: LAR | E36: QB | F36: 34 | G36: 0.5 | M36: =F36*Settings!$B$4+G36*Settings!$B$5+H36*Settings!$B$6+I36*Settings!$B$7+J36*Settings!$B$8+K36*Settings!$B$9+L36*Settings!$B$10 | N36: =M36-INDEX(Settings!$G$4:$G$9,MATCH($E36,Settings!$F$4:$F$9,0)) | O36: =N36*INDEX(Settings!$H$4:$H$9,MATCH($E36,Settings!$F$4:$F$9,0)) | P36: HIGH | Q36: LAR highest implied pts 26.6 but zero rush value
A37: 35 | B37: TE4 | C37: Colston Loveland | D37: CHI | E37: TE | H37: 6 | M37: =F37*Settings!$B$4+G37*Settings!$B$5+H37*Settings!$B$6+I37*Settings!$B$7+J37*Settings!$B$8+K37*Settings!$B$9+L37*Settings!$B$10 | N37: =M37-INDEX(Settings!$G$4:$G$9,MATCH($E37,Settings!$F$4:$F$9,0)) | O37: =N37*INDEX(Settings!$H$4:$H$9,MATCH($E37,Settings!$F$4:$F$9,0)) | P37: HIGH
A38: 36 | B38: WR9 | C38: Rome Odunze | D38: CHI | E38: WR | H38: 7.7 | M38: =F38*Settings!$B$4+G38*Settings!$B$5+H38*Settings!$B$6+I38*Settings!$B$7+J38*Settings!$B$8+K38*Settings!$B$9+L38*Settings!$B$10 | N38: =M38-INDEX(Settings!$G$4:$G$9,MATCH($E38,Settings!$F$4:$F$9,0)) | O38: =N38*INDEX(Settings!$H$4:$H$9,MATCH($E38,Settings!$F$4:$F$9,0)) | P38: HIGH
A39: 37 | B39: QB7 | C39: Dak Prescott | D39: DAL | E39: QB | F39: 30.5 | G39: 2 | M39: =F39*Settings!$B$4+G39*Settings!$B$5+H39*Settings!$B$6+I39*Settings!$B$7+J39*Settings!$B$8+K39*Settings!$B$9+L39*Settings!$B$10 | N39: =M39-INDEX(Settings!$G$4:$G$9,MATCH($E39,Settings!$F$4:$F$9,0)) | O39: =N39*INDEX(Settings!$H$4:$H$9,MATCH($E39,Settings!$F$4:$F$9,0)) | P39: HIGH
A40: 38 | B40: TE5 | C40: Dallas Goedert | D40: PHI | E40: TE | H40: 5.8 | M40: =F40*Settings!$B$4+G40*Settings!$B$5+H40*Settings!$B$6+I40*Settings!$B$7+J40*Settings!$B$8+K40*Settings!$B$9+L40*Settings!$B$10 | N40: =M40-INDEX(Settings!$G$4:$G$9,MATCH($E40,Settings!$F$4:$F$9,0)) | O40: =N40*INDEX(Settings!$H$4:$H$9,MATCH($E40,Settings!$F$4:$F$9,0)) | P40: HIGH
A41: 39 | B41: WR10 | C41: George Pickens | D41: DAL | E41: WR | H41: 7.6 | M41: =F41*Settings!$B$4+G41*Settings!$B$5+H41*Settings!$B$6+I41*Settings!$B$7+J41*Settings!$B$8+K41*Settings!$B$9+L41*Settings!$B$10 | N41: =M41-INDEX(Settings!$G$4:$G$9,MATCH($E41,Settings!$F$4:$F$9,0)) | O41: =N41*INDEX(Settings!$H$4:$H$9,MATCH($E41,Settings!$F$4:$F$9,0)) | P41: HIGH
A42: 40 | B42: RB14 | C42: Ashton Jeanty | D42: LV | E42: RB | G42: 7 | H42: 2 | M42: =F42*Settings!$B$4+G42*Settings!$B$5+H42*Settings!$B$6+I42*Settings!$B$7+J42*Settings!$B$8+K42*Settings!$B$9+L42*Settings!$B$10 | N42: =M42-INDEX(Settings!$G$4:$G$9,MATCH($E42,Settings!$F$4:$F$9,0)) | O42: =N42*INDEX(Settings!$H$4:$H$9,MATCH($E42,Settings!$F$4:$F$9,0)) | P42: HIGH | Q42: Goal-line yes
A43: 41 | B43: RB15 | C43: De'Von Achane | D43: MIA | E43: RB | G43: 5.7 | H43: 3.3 | M43: =F43*Settings!$B$4+G43*Settings!$B$5+H43*Settings!$B$6+I43*Settings!$B$7+J43*Settings!$B$8+K43*Settings!$B$9+L43*Settings!$B$10 | N43: =M43-INDEX(Settings!$G$4:$G$9,MATCH($E43,Settings!$F$4:$F$9,0)) | O43: =N43*INDEX(Settings!$H$4:$H$9,MATCH($E43,Settings!$F$4:$F$9,0)) | P43: HIGH | Q43: Not the goal-line back
A44: 42 | B44: K5 | C44: Jake Bates | D44: DET | E44: K | I44: 31 | J44: 53 | M44: =F44*Settings!$B$4+G44*Settings!$B$5+H44*Settings!$B$6+I44*Settings!$B$7+J44*Settings!$B$8+K44*Settings!$B$9+L44*Settings!$B$10 | N44: =M44-INDEX(Settings!$G$4:$G$9,MATCH($E44,Settings!$F$4:$F$9,0)) | O44: =N44*INDEX(Settings!$H$4:$H$9,MATCH($E44,Settings!$F$4:$F$9,0)) | P44: HIGH | Q44: XP-heavy; TD offense caps him
A45: 43 | B45: RB16 | C45: Jeremiyah Love | D45: ARI | E45: RB | G45: 6.8 | H45: 2.1 | M45: =F45*Settings!$B$4+G45*Settings!$B$5+H45*Settings!$B$6+I45*Settings!$B$7+J45*Settings!$B$8+K45*Settings!$B$9+L45*Settings!$B$10 | N45: =M45-INDEX(Settings!$G$4:$G$9,MATCH($E45,Settings!$F$4:$F$9,0)) | O45: =N45*INDEX(Settings!$H$4:$H$9,MATCH($E45,Settings!$F$4:$F$9,0)) | P45: HIGH | Q45: Rookie; opened camp as RB2 behind Allgeier
A46: 44 | B46: QB8 | C46: Jaxson Dart | D46: NYG | E46: QB | F46: 22 | G46: 6 | M46: =F46*Settings!$B$4+G46*Settings!$B$5+H46*Settings!$B$6+I46*Settings!$B$7+J46*Settings!$B$8+K46*Settings!$B$9+L46*Settings!$B$10 | N46: =M46-INDEX(Settings!$G$4:$G$9,MATCH($E46,Settings!$F$4:$F$9,0)) | O46: =N46*INDEX(Settings!$H$4:$H$9,MATCH($E46,Settings!$F$4:$F$9,0)) | P46: HIGH | Q46: BIGGEST ADP ARBITRAGE. But new HC Harbaugh may curb rushing
A47: 45 | B47: QB9 | C47: Brock Purdy | D47: SF | E47: QB | F47: 27 | G47: 3.5 | M47: =F47*Settings!$B$4+G47*Settings!$B$5+H47*Settings!$B$6+I47*Settings!$B$7+J47*Settings!$B$8+K47*Settings!$B$9+L47*Settings!$B$10 | N47: =M47-INDEX(Settings!$G$4:$G$9,MATCH($E47,Settings!$F$4:$F$9,0)) | O47: =N47*INDEX(Settings!$H$4:$H$9,MATCH($E47,Settings!$F$4:$F$9,0)) | P47: HIGH
A48: 46 | B48: TE6 | C48: Jake Ferguson | D48: DAL | E48: TE | H48: 5.5 | M48: =F48*Settings!$B$4+G48*Settings!$B$5+H48*Settings!$B$6+I48*Settings!$B$7+J48*Settings!$B$8+K48*Settings!$B$9+L48*Settings!$B$10 | N48: =M48-INDEX(Settings!$G$4:$G$9,MATCH($E48,Settings!$F$4:$F$9,0)) | O48: =N48*INDEX(Settings!$H$4:$H$9,MATCH($E48,Settings!$F$4:$F$9,0)) | P48: HIGH
A49: 47 | B49: WR11 | C49: Malik Nabers | D49: NYG | E49: WR | G49: 0.1 | H49: 7.2 | M49: =F49*Settings!$B$4+G49*Settings!$B$5+H49*Settings!$B$6+I49*Settings!$B$7+J49*Settings!$B$8+K49*Settings!$B$9+L49*Settings!$B$10 | N49: =M49-INDEX(Settings!$G$4:$G$9,MATCH($E49,Settings!$F$4:$F$9,0)) | O49: =N49*INDEX(Settings!$H$4:$H$9,MATCH($E49,Settings!$F$4:$F$9,0)) | P49: HIGH
A50: 48 | B50: WR12 | C50: Emeka Egbuka | D50: TB | E50: WR | G50: 0.1 | H50: 7.2 | M50: =F50*Settings!$B$4+G50*Settings!$B$5+H50*Settings!$B$6+I50*Settings!$B$7+J50*Settings!$B$8+K50*Settings!$B$9+L50*Settings!$B$10 | N50: =M50-INDEX(Settings!$G$4:$G$9,MATCH($E50,Settings!$F$4:$F$9,0)) | O50: =N50*INDEX(Settings!$H$4:$H$9,MATCH($E50,Settings!$F$4:$F$9,0)) | P50: HIGH
A51: 49 | B51: WR13 | C51: Courtland Sutton | D51: DEN | E51: WR | H51: 7.3 | M51: =F51*Settings!$B$4+G51*Settings!$B$5+H51*Settings!$B$6+I51*Settings!$B$7+J51*Settings!$B$8+K51*Settings!$B$9+L51*Settings!$B$10 | N51: =M51-INDEX(Settings!$G$4:$G$9,MATCH($E51,Settings!$F$4:$F$9,0)) | O51: =N51*INDEX(Settings!$H$4:$H$9,MATCH($E51,Settings!$F$4:$F$9,0)) | P51: HIGH
A52: 50 | B52: WR14 | C52: Justin Jefferson | D52: MIN | E52: WR | G52: 0.1 | H52: 7.2 | M52: =F52*Settings!$B$4+G52*Settings!$B$5+H52*Settings!$B$6+I52*Settings!$B$7+J52*Settings!$B$8+K52*Settings!$B$9+L52*Settings!$B$10 | N52: =M52-INDEX(Settings!$G$4:$G$9,MATCH($E52,Settings!$F$4:$F$9,0)) | O52: =N52*INDEX(Settings!$H$4:$H$9,MATCH($E52,Settings!$F$4:$F$9,0)) | P52: HIGH
A53: 51 | B53: TE7 | C53: Tyler Warren | D53: IND | E53: TE | G53: 0.2 | H53: 5.2 | M53: =F53*Settings!$B$4+G53*Settings!$B$5+H53*Settings!$B$6+I53*Settings!$B$7+J53*Settings!$B$8+K53*Settings!$B$9+L53*Settings!$B$10 | N53: =M53-INDEX(Settings!$G$4:$G$9,MATCH($E53,Settings!$F$4:$F$9,0)) | O53: =N53*INDEX(Settings!$H$4:$H$9,MATCH($E53,Settings!$F$4:$F$9,0)) | P53: HIGH
A54: 52 | B54: K6 | C54: Cameron Dicker | D54: LAC | E54: K | I54: 35 | J54: 38 | M54: =F54*Settings!$B$4+G54*Settings!$B$5+H54*Settings!$B$6+I54*Settings!$B$7+J54*Settings!$B$8+K54*Settings!$B$9+L54*Settings!$B$10 | N54: =M54-INDEX(Settings!$G$4:$G$9,MATCH($E54,Settings!$F$4:$F$9,0)) | O54: =N54*INDEX(Settings!$H$4:$H$9,MATCH($E54,Settings!$F$4:$F$9,0)) | P54: HIGH | Q54: 92.7 pct in 2025; strong FG lean
A55: 53 | B55: K7 | C55: Cairo Santos | D55: CHI | E55: K | I55: 32 | J55: 47 | M55: =F55*Settings!$B$4+G55*Settings!$B$5+H55*Settings!$B$6+I55*Settings!$B$7+J55*Settings!$B$8+K55*Settings!$B$9+L55*Settings!$B$10 | N55: =M55-INDEX(Settings!$G$4:$G$9,MATCH($E55,Settings!$F$4:$F$9,0)) | O55: =N55*INDEX(Settings!$H$4:$H$9,MATCH($E55,Settings!$F$4:$F$9,0)) | P55: HIGH | Q55: 39 FGA in 2025
A56: 54 | B56: RB17 | C56: Breece Hall | D56: NYJ | E56: RB | G56: 6.3 | H56: 2.4 | M56: =F56*Settings!$B$4+G56*Settings!$B$5+H56*Settings!$B$6+I56*Settings!$B$7+J56*Settings!$B$8+K56*Settings!$B$9+L56*Settings!$B$10 | N56: =M56-INDEX(Settings!$G$4:$G$9,MATCH($E56,Settings!$F$4:$F$9,0)) | O56: =N56*INDEX(Settings!$H$4:$H$9,MATCH($E56,Settings!$F$4:$F$9,0)) | P56: MEDIUM | Q56: Groin strain Aug 17; expected Week 1
A57: 55 | B57: WR15 | C57: Drake London | D57: ATL | E57: WR | H57: 7.2 | M57: =F57*Settings!$B$4+G57*Settings!$B$5+H57*Settings!$B$6+I57*Settings!$B$7+J57*Settings!$B$8+K57*Settings!$B$9+L57*Settings!$B$10 | N57: =M57-INDEX(Settings!$G$4:$G$9,MATCH($E57,Settings!$F$4:$F$9,0)) | O57: =N57*INDEX(Settings!$H$4:$H$9,MATCH($E57,Settings!$F$4:$F$9,0)) | P57: HIGH
A58: 56 | B58: TE8 | C58: George Kittle | D58: SF | E58: TE | H58: 5.3 | M58: =F58*Settings!$B$4+G58*Settings!$B$5+H58*Settings!$B$6+I58*Settings!$B$7+J58*Settings!$B$8+K58*Settings!$B$9+L58*Settings!$B$10 | N58: =M58-INDEX(Settings!$G$4:$G$9,MATCH($E58,Settings!$F$4:$F$9,0)) | O58: =N58*INDEX(Settings!$H$4:$H$9,MATCH($E58,Settings!$F$4:$F$9,0)) | P58: HIGH
A59: 57 | B59: WR16 | C59: Christian Watson | D59: GB | E59: WR | G59: 0.1 | H59: 7 | M59: =F59*Settings!$B$4+G59*Settings!$B$5+H59*Settings!$B$6+I59*Settings!$B$7+J59*Settings!$B$8+K59*Settings!$B$9+L59*Settings!$B$10 | N59: =M59-INDEX(Settings!$G$4:$G$9,MATCH($E59,Settings!$F$4:$F$9,0)) | O59: =N59*INDEX(Settings!$H$4:$H$9,MATCH($E59,Settings!$F$4:$F$9,0)) | P59: HIGH
A60: 58 | B60: K8 | C60: Harrison Mevis | D60: LAR | E60: K | I60: 29 | J60: 55 | M60: =F60*Settings!$B$4+G60*Settings!$B$5+H60*Settings!$B$6+I60*Settings!$B$7+J60*Settings!$B$8+K60*Settings!$B$9+L60*Settings!$B$10 | N60: =M60-INDEX(Settings!$G$4:$G$9,MATCH($E60,Settings!$F$4:$F$9,0)) | O60: =N60*INDEX(Settings!$H$4:$H$9,MATCH($E60,Settings!$F$4:$F$9,0)) | P60: MEDIUM | Q60: Most TD-heavy K; LAR led NFL RZ trips
A61: 59 | B61: RB18 | C61: Jadarian Price | D61: SEA | E61: RB | G61: 7.5 | H61: 1.1 | M61: =F61*Settings!$B$4+G61*Settings!$B$5+H61*Settings!$B$6+I61*Settings!$B$7+J61*Settings!$B$8+K61*Settings!$B$9+L61*Settings!$B$10 | N61: =M61-INDEX(Settings!$G$4:$G$9,MATCH($E61,Settings!$F$4:$F$9,0)) | O61: =N61*INDEX(Settings!$H$4:$H$9,MATCH($E61,Settings!$F$4:$F$9,0)) | P61: HIGH | Q61: Rookie; leads while Charbonnet rehabs
A62: 60 | B62: RB19 | C62: Cam Skattebo | D62: NYG | E62: RB | G62: 7.4 | H62: 1.2 | M62: =F62*Settings!$B$4+G62*Settings!$B$5+H62*Settings!$B$6+I62*Settings!$B$7+J62*Settings!$B$8+K62*Settings!$B$9+L62*Settings!$B$10 | N62: =M62-INDEX(Settings!$G$4:$G$9,MATCH($E62,Settings!$F$4:$F$9,0)) | O62: =N62*INDEX(Settings!$H$4:$H$9,MATCH($E62,Settings!$F$4:$F$9,0)) | P62: HIGH | Q62: Goal-line yes
A63: 61 | B63: RB20 | C63: D'Andre Swift | D63: CHI | E63: RB | G63: 7.5 | H63: 1.1 | M63: =F63*Settings!$B$4+G63*Settings!$B$5+H63*Settings!$B$6+I63*Settings!$B$7+J63*Settings!$B$8+K63*Settings!$B$9+L63*Settings!$B$10 | N63: =M63-INDEX(Settings!$G$4:$G$9,MATCH($E63,Settings!$F$4:$F$9,0)) | O63: =N63*INDEX(Settings!$H$4:$H$9,MATCH($E63,Settings!$F$4:$F$9,0)) | P63: HIGH
A64: 62 | B64: QB10 | C64: Lamar Jackson | D64: BAL | E64: QB | F64: 26.5 | G64: 3.5 | M64: =F64*Settings!$B$4+G64*Settings!$B$5+H64*Settings!$B$6+I64*Settings!$B$7+J64*Settings!$B$8+K64*Settings!$B$9+L64*Settings!$B$10 | N64: =M64-INDEX(Settings!$G$4:$G$9,MATCH($E64,Settings!$F$4:$F$9,0)) | O64: =N64*INDEX(Settings!$H$4:$H$9,MATCH($E64,Settings!$F$4:$F$9,0)) | P64: HIGH | Q64: BAL 11.5 win total
A65: 63 | B65: QB11 | C65: Jayden Daniels | D65: WAS | E65: QB | F65: 23.5 | G65: 5 | M65: =F65*Settings!$B$4+G65*Settings!$B$5+H65*Settings!$B$6+I65*Settings!$B$7+J65*Settings!$B$8+K65*Settings!$B$9+L65*Settings!$B$10 | N65: =M65-INDEX(Settings!$G$4:$G$9,MATCH($E65,Settings!$F$4:$F$9,0)) | O65: =N65*INDEX(Settings!$H$4:$H$9,MATCH($E65,Settings!$F$4:$F$9,0)) | P65: HIGH
A66: 64 | B66: QB12 | C66: Bo Nix | D66: DEN | E66: QB | F66: 26.5 | G66: 3.5 | M66: =F66*Settings!$B$4+G66*Settings!$B$5+H66*Settings!$B$6+I66*Settings!$B$7+J66*Settings!$B$8+K66*Settings!$B$9+L66*Settings!$B$10 | N66: =M66-INDEX(Settings!$G$4:$G$9,MATCH($E66,Settings!$F$4:$F$9,0)) | O66: =N66*INDEX(Settings!$H$4:$H$9,MATCH($E66,Settings!$F$4:$F$9,0)) | P66: HIGH
A67: 65 | B67: TE9 | C67: Hunter Henry | D67: NE | E67: TE | H67: 5.2 | M67: =F67*Settings!$B$4+G67*Settings!$B$5+H67*Settings!$B$6+I67*Settings!$B$7+J67*Settings!$B$8+K67*Settings!$B$9+L67*Settings!$B$10 | N67: =M67-INDEX(Settings!$G$4:$G$9,MATCH($E67,Settings!$F$4:$F$9,0)) | O67: =N67*INDEX(Settings!$H$4:$H$9,MATCH($E67,Settings!$F$4:$F$9,0)) | P67: HIGH
A68: 66 | B68: TE10 | C68: Terrance Ferguson | D68: LAR | E68: TE | H68: 5.2 | M68: =F68*Settings!$B$4+G68*Settings!$B$5+H68*Settings!$B$6+I68*Settings!$B$7+J68*Settings!$B$8+K68*Settings!$B$9+L68*Settings!$B$10 | N68: =M68-INDEX(Settings!$G$4:$G$9,MATCH($E68,Settings!$F$4:$F$9,0)) | O68: =N68*INDEX(Settings!$H$4:$H$9,MATCH($E68,Settings!$F$4:$F$9,0)) | P68: HIGH
A69: 67 | B69: TE11 | C69: Sam LaPorta | D69: DET | E69: TE | H69: 5.2 | M69: =F69*Settings!$B$4+G69*Settings!$B$5+H69*Settings!$B$6+I69*Settings!$B$7+J69*Settings!$B$8+K69*Settings!$B$9+L69*Settings!$B$10 | N69: =M69-INDEX(Settings!$G$4:$G$9,MATCH($E69,Settings!$F$4:$F$9,0)) | O69: =N69*INDEX(Settings!$H$4:$H$9,MATCH($E69,Settings!$F$4:$F$9,0)) | P69: HIGH
A70: 68 | B70: WR17 | C70: A.J. Brown | D70: NE | E70: WR | H70: 7 | M70: =F70*Settings!$B$4+G70*Settings!$B$5+H70*Settings!$B$6+I70*Settings!$B$7+J70*Settings!$B$8+K70*Settings!$B$9+L70*Settings!$B$10 | N70: =M70-INDEX(Settings!$G$4:$G$9,MATCH($E70,Settings!$F$4:$F$9,0)) | O70: =N70*INDEX(Settings!$H$4:$H$9,MATCH($E70,Settings!$F$4:$F$9,0)) | P70: HIGH
A71: 69 | B71: K9 | C71: Will Reichard | D71: MIN | E71: K | I71: 33 | J71: 42 | M71: =F71*Settings!$B$4+G71*Settings!$B$5+H71*Settings!$B$6+I71*Settings!$B$7+J71*Settings!$B$8+K71*Settings!$B$9+L71*Settings!$B$10 | N71: =M71-INDEX(Settings!$G$4:$G$9,MATCH($E71,Settings!$F$4:$F$9,0)) | O71: =N71*INDEX(Settings!$H$4:$H$9,MATCH($E71,Settings!$F$4:$F$9,0)) | P71: HIGH | Q71: 94.3 pct in 2025
A72: 70 | B72: K10 | C72: Chase McLaughlin | D72: TB | E72: K | I72: 33 | J72: 42 | M72: =F72*Settings!$B$4+G72*Settings!$B$5+H72*Settings!$B$6+I72*Settings!$B$7+J72*Settings!$B$8+K72*Settings!$B$9+L72*Settings!$B$10 | N72: =M72-INDEX(Settings!$G$4:$G$9,MATCH($E72,Settings!$F$4:$F$9,0)) | O72: =N72*INDEX(Settings!$H$4:$H$9,MATCH($E72,Settings!$F$4:$F$9,0)) | P72: HIGH
A73: 71 | B73: RB21 | C73: Rhamondre Stevenson | D73: NE | E73: RB | G73: 6.9 | H73: 1.6 | M73: =F73*Settings!$B$4+G73*Settings!$B$5+H73*Settings!$B$6+I73*Settings!$B$7+J73*Settings!$B$8+K73*Settings!$B$9+L73*Settings!$B$10 | N73: =M73-INDEX(Settings!$G$4:$G$9,MATCH($E73,Settings!$F$4:$F$9,0)) | O73: =N73*INDEX(Settings!$H$4:$H$9,MATCH($E73,Settings!$F$4:$F$9,0)) | P73: HIGH | Q73: Goal-line yes
A74: 72 | B74: RB22 | C74: Bhayshul Tuten | D74: JAX | E74: RB | G74: 6.8 | H74: 1.7 | M74: =F74*Settings!$B$4+G74*Settings!$B$5+H74*Settings!$B$6+I74*Settings!$B$7+J74*Settings!$B$8+K74*Settings!$B$9+L74*Settings!$B$10 | N74: =M74-INDEX(Settings!$G$4:$G$9,MATCH($E74,Settings!$F$4:$F$9,0)) | O74: =N74*INDEX(Settings!$H$4:$H$9,MATCH($E74,Settings!$F$4:$F$9,0)) | P74: HIGH | Q74: But Rodriguez owns goal line
A75: 73 | B75: WR18 | C75: Nico Collins | D75: HOU | E75: WR | G75: 0.1 | H75: 6.8 | M75: =F75*Settings!$B$4+G75*Settings!$B$5+H75*Settings!$B$6+I75*Settings!$B$7+J75*Settings!$B$8+K75*Settings!$B$9+L75*Settings!$B$10 | N75: =M75-INDEX(Settings!$G$4:$G$9,MATCH($E75,Settings!$F$4:$F$9,0)) | O75: =N75*INDEX(Settings!$H$4:$H$9,MATCH($E75,Settings!$F$4:$F$9,0)) | P75: HIGH
A76: 74 | B76: WR19 | C76: Chris Olave | D76: NO | E76: WR | H76: 6.8 | M76: =F76*Settings!$B$4+G76*Settings!$B$5+H76*Settings!$B$6+I76*Settings!$B$7+J76*Settings!$B$8+K76*Settings!$B$9+L76*Settings!$B$10 | N76: =M76-INDEX(Settings!$G$4:$G$9,MATCH($E76,Settings!$F$4:$F$9,0)) | O76: =N76*INDEX(Settings!$H$4:$H$9,MATCH($E76,Settings!$F$4:$F$9,0)) | P76: HIGH
A77: 75 | B77: QB13 | C77: Caleb Williams | D77: CHI | E77: QB | F77: 27 | G77: 3 | M77: =F77*Settings!$B$4+G77*Settings!$B$5+H77*Settings!$B$6+I77*Settings!$B$7+J77*Settings!$B$8+K77*Settings!$B$9+L77*Settings!$B$10 | N77: =M77-INDEX(Settings!$G$4:$G$9,MATCH($E77,Settings!$F$4:$F$9,0)) | O77: =N77*INDEX(Settings!$H$4:$H$9,MATCH($E77,Settings!$F$4:$F$9,0)) | P77: HIGH
A78: 76 | B78: WR20 | C78: D.J. Moore | D78: BUF | E78: WR | G78: 0.2 | H78: 6.5 | M78: =F78*Settings!$B$4+G78*Settings!$B$5+H78*Settings!$B$6+I78*Settings!$B$7+J78*Settings!$B$8+K78*Settings!$B$9+L78*Settings!$B$10 | N78: =M78-INDEX(Settings!$G$4:$G$9,MATCH($E78,Settings!$F$4:$F$9,0)) | O78: =N78*INDEX(Settings!$H$4:$H$9,MATCH($E78,Settings!$F$4:$F$9,0)) | P78: HIGH
A79: 77 | B79: TE12 | C79: Tucker Kraft | D79: GB | E79: TE | G79: 0.1 | H79: 4.7 | M79: =F79*Settings!$B$4+G79*Settings!$B$5+H79*Settings!$B$6+I79*Settings!$B$7+J79*Settings!$B$8+K79*Settings!$B$9+L79*Settings!$B$10 | N79: =M79-INDEX(Settings!$G$4:$G$9,MATCH($E79,Settings!$F$4:$F$9,0)) | O79: =N79*INDEX(Settings!$H$4:$H$9,MATCH($E79,Settings!$F$4:$F$9,0)) | P79: HIGH
A80: 78 | B80: WR21 | C80: Jameson Williams | D80: DET | E80: WR | G80: 0.3 | H80: 6.3 | M80: =F80*Settings!$B$4+G80*Settings!$B$5+H80*Settings!$B$6+I80*Settings!$B$7+J80*Settings!$B$8+K80*Settings!$B$9+L80*Settings!$B$10 | N80: =M80-INDEX(Settings!$G$4:$G$9,MATCH($E80,Settings!$F$4:$F$9,0)) | O80: =N80*INDEX(Settings!$H$4:$H$9,MATCH($E80,Settings!$F$4:$F$9,0)) | P80: HIGH
A81: 79 | B81: RB23 | C81: Bucky Irving | D81: TB | E81: RB | G81: 6.2 | H81: 1.9 | M81: =F81*Settings!$B$4+G81*Settings!$B$5+H81*Settings!$B$6+I81*Settings!$B$7+J81*Settings!$B$8+K81*Settings!$B$9+L81*Settings!$B$10 | N81: =M81-INDEX(Settings!$G$4:$G$9,MATCH($E81,Settings!$F$4:$F$9,0)) | O81: =N81*INDEX(Settings!$H$4:$H$9,MATCH($E81,Settings!$F$4:$F$9,0)) | P81: HIGH | Q81: TRAP: ZERO carries inside the 5 in 2025
A82: 80 | B82: TE13 | C82: Dalton Kincaid | D82: BUF | E82: TE | H82: 4.7 | M82: =F82*Settings!$B$4+G82*Settings!$B$5+H82*Settings!$B$6+I82*Settings!$B$7+J82*Settings!$B$8+K82*Settings!$B$9+L82*Settings!$B$10 | N82: =M82-INDEX(Settings!$G$4:$G$9,MATCH($E82,Settings!$F$4:$F$9,0)) | O82: =N82*INDEX(Settings!$H$4:$H$9,MATCH($E82,Settings!$F$4:$F$9,0)) | P82: HIGH
A83: 81 | B83: QB14 | C83: Justin Herbert | D83: LAC | E83: QB | F83: 27.5 | G83: 2.5 | M83: =F83*Settings!$B$4+G83*Settings!$B$5+H83*Settings!$B$6+I83*Settings!$B$7+J83*Settings!$B$8+K83*Settings!$B$9+L83*Settings!$B$10 | N83: =M83-INDEX(Settings!$G$4:$G$9,MATCH($E83,Settings!$F$4:$F$9,0)) | O83: =N83*INDEX(Settings!$H$4:$H$9,MATCH($E83,Settings!$F$4:$F$9,0)) | P83: HIGH
A84: 82 | B84: K11 | C84: Tyler Loop | D84: BAL | E84: K | I84: 29 | J84: 49 | M84: =F84*Settings!$B$4+G84*Settings!$B$5+H84*Settings!$B$6+I84*Settings!$B$7+J84*Settings!$B$8+K84*Settings!$B$9+L84*Settings!$B$10 | N84: =M84-INDEX(Settings!$G$4:$G$9,MATCH($E84,Settings!$F$4:$F$9,0)) | O84: =N84*INDEX(Settings!$H$4:$H$9,MATCH($E84,Settings!$F$4:$F$9,0)) | P84: MEDIUM | Q84: Year 2; BAL 11.5 win total
A85: 83 | B85: RB24 | C85: Quinshon Judkins | D85: CLE | E85: RB | G85: 7.2 | H85: 0.8 | M85: =F85*Settings!$B$4+G85*Settings!$B$5+H85*Settings!$B$6+I85*Settings!$B$7+J85*Settings!$B$8+K85*Settings!$B$9+L85*Settings!$B$10 | N85: =M85-INDEX(Settings!$G$4:$G$9,MATCH($E85,Settings!$F$4:$F$9,0)) | O85: =N85*INDEX(Settings!$H$4:$H$9,MATCH($E85,Settings!$F$4:$F$9,0)) | P85: HIGH | Q85: Goal-line yes
A86: 84 | B86: RB25 | C86: TreVeyon Henderson | D86: NE | E86: RB | G86: 6.8 | H86: 1.2 | M86: =F86*Settings!$B$4+G86*Settings!$B$5+H86*Settings!$B$6+I86*Settings!$B$7+J86*Settings!$B$8+K86*Settings!$B$9+L86*Settings!$B$10 | N86: =M86-INDEX(Settings!$G$4:$G$9,MATCH($E86,Settings!$F$4:$F$9,0)) | O86: =N86*INDEX(Settings!$H$4:$H$9,MATCH($E86,Settings!$F$4:$F$9,0)) | P86: HIGH | Q86: Not the goal-line back
A87: 85 | B87: DST1 | C87: Seahawks D/ST | D87: SEA | E87: DST | K87: 3.47 | L87: 0.5 | M87: =F87*Settings!$B$4+G87*Settings!$B$5+H87*Settings!$B$6+I87*Settings!$B$7+J87*Settings!$B$8+K87*Settings!$B$9+L87*Settings!$B$10 | N87: =M87-INDEX(Settings!$G$4:$G$9,MATCH($E87,Settings!$F$4:$F$9,0)) | O87: =N87*INDEX(Settings!$H$4:$H$9,MATCH($E87,Settings!$F$4:$F$9,0)) | P87: MEDIUM | Q87: Only team with 3+ def TD all 3 yrs; Tory Horton PR
A88: 86 | B88: WR22 | C88: Mike Evans | D88: SF | E88: WR | H88: 6.4 | M88: =F88*Settings!$B$4+G88*Settings!$B$5+H88*Settings!$B$6+I88*Settings!$B$7+J88*Settings!$B$8+K88*Settings!$B$9+L88*Settings!$B$10 | N88: =M88-INDEX(Settings!$G$4:$G$9,MATCH($E88,Settings!$F$4:$F$9,0)) | O88: =N88*INDEX(Settings!$H$4:$H$9,MATCH($E88,Settings!$F$4:$F$9,0)) | P88: HIGH
A89: 87 | B89: K12 | C89: Cam Little | D89: JAX | E89: K | I89: 29 | J89: 48 | M89: =F89*Settings!$B$4+G89*Settings!$B$5+H89*Settings!$B$6+I89*Settings!$B$7+J89*Settings!$B$8+K89*Settings!$B$9+L89*Settings!$B$10 | N89: =M89-INDEX(Settings!$G$4:$G$9,MATCH($E89,Settings!$F$4:$F$9,0)) | O89: =N89*INDEX(Settings!$H$4:$H$9,MATCH($E89,Settings!$F$4:$F$9,0)) | P89: HIGH
A90: 88 | B90: DST2 | C90: Cowboys D/ST | D90: DAL | E90: DST | K90: 3.14 | L90: 0.45 | M90: =F90*Settings!$B$4+G90*Settings!$B$5+H90*Settings!$B$6+I90*Settings!$B$7+J90*Settings!$B$8+K90*Settings!$B$9+L90*Settings!$B$10 | N90: =M90-INDEX(Settings!$G$4:$G$9,MATCH($E90,Settings!$F$4:$F$9,0)) | O90: =N90*INDEX(Settings!$H$4:$H$9,MATCH($E90,Settings!$F$4:$F$9,0)) | P90: MEDIUM | Q90: KaVontae Turpin led NFL KR yds 2025
A91: 89 | B91: K13 | C91: Harrison Butker | D91: KC | E91: K | I91: 33 | J91: 35 | M91: =F91*Settings!$B$4+G91*Settings!$B$5+H91*Settings!$B$6+I91*Settings!$B$7+J91*Settings!$B$8+K91*Settings!$B$9+L91*Settings!$B$10 | N91: =M91-INDEX(Settings!$G$4:$G$9,MATCH($E91,Settings!$F$4:$F$9,0)) | O91: =N91*INDEX(Settings!$H$4:$H$9,MATCH($E91,Settings!$F$4:$F$9,0)) | P91: HIGH | Q91: Strong FG lean
A92: 90 | B92: K14 | C92: Wil Lutz | D92: DEN | E92: K | I92: 30 | J92: 44 | M92: =F92*Settings!$B$4+G92*Settings!$B$5+H92*Settings!$B$6+I92*Settings!$B$7+J92*Settings!$B$8+K92*Settings!$B$9+L92*Settings!$B$10 | N92: =M92-INDEX(Settings!$G$4:$G$9,MATCH($E92,Settings!$F$4:$F$9,0)) | O92: =N92*INDEX(Settings!$H$4:$H$9,MATCH($E92,Settings!$F$4:$F$9,0)) | P92: HIGH
A93: 91 | B93: K15 | C93: Evan McPherson | D93: CIN | E93: K | I93: 29 | J93: 47 | M93: =F93*Settings!$B$4+G93*Settings!$B$5+H93*Settings!$B$6+I93*Settings!$B$7+J93*Settings!$B$8+K93*Settings!$B$9+L93*Settings!$B$10 | N93: =M93-INDEX(Settings!$G$4:$G$9,MATCH($E93,Settings!$F$4:$F$9,0)) | O93: =N93*INDEX(Settings!$H$4:$H$9,MATCH($E93,Settings!$F$4:$F$9,0)) | P93: HIGH | Q93: Only 28 FGA in 2025
A94: 92 | B94: RB26 | C94: David Montgomery | D94: HOU | E94: RB | G94: 7 | H94: 0.8 | M94: =F94*Settings!$B$4+G94*Settings!$B$5+H94*Settings!$B$6+I94*Settings!$B$7+J94*Settings!$B$8+K94*Settings!$B$9+L94*Settings!$B$10 | N94: =M94-INDEX(Settings!$G$4:$G$9,MATCH($E94,Settings!$F$4:$F$9,0)) | O94: =N94*INDEX(Settings!$H$4:$H$9,MATCH($E94,Settings!$F$4:$F$9,0)) | P94: HIGH | Q94: Traded DET to HOU
A95: 93 | B95: WR23 | C95: Ladd McConkey | D95: LAC | E95: WR | H95: 6.2 | M95: =F95*Settings!$B$4+G95*Settings!$B$5+H95*Settings!$B$6+I95*Settings!$B$7+J95*Settings!$B$8+K95*Settings!$B$9+L95*Settings!$B$10 | N95: =M95-INDEX(Settings!$G$4:$G$9,MATCH($E95,Settings!$F$4:$F$9,0)) | O95: =N95*INDEX(Settings!$H$4:$H$9,MATCH($E95,Settings!$F$4:$F$9,0)) | P95: HIGH
A96: 94 | B96: QB15 | C96: Patrick Mahomes | D96: KC | E96: QB | F96: 26 | G96: 3 | M96: =F96*Settings!$B$4+G96*Settings!$B$5+H96*Settings!$B$6+I96*Settings!$B$7+J96*Settings!$B$8+K96*Settings!$B$9+L96*Settings!$B$10 | N96: =M96-INDEX(Settings!$G$4:$G$9,MATCH($E96,Settings!$F$4:$F$9,0)) | O96: =N96*INDEX(Settings!$H$4:$H$9,MATCH($E96,Settings!$F$4:$F$9,0)) | P96: MEDIUM | Q96: INJURY RISK: torn ACL+LCL 2025; no preseason snaps
A97: 95 | B97: DST3 | C97: Texans D/ST | D97: HOU | E97: DST | K97: 2.79 | L97: 0.65 | M97: =F97*Settings!$B$4+G97*Settings!$B$5+H97*Settings!$B$6+I97*Settings!$B$7+J97*Settings!$B$8+K97*Settings!$B$9+L97*Settings!$B$10 | N97: =M97-INDEX(Settings!$G$4:$G$9,MATCH($E97,Settings!$F$4:$F$9,0)) | O97: =N97*INDEX(Settings!$H$4:$H$9,MATCH($E97,Settings!$F$4:$F$9,0)) | P97: MEDIUM | Q97: 3 FR TD in 2025; elite pass rush; weak returns
A98: 96 | B98: DST4 | C98: Browns D/ST | D98: CLE | E98: DST | K98: 2.79 | L98: 0.6 | M98: =F98*Settings!$B$4+G98*Settings!$B$5+H98*Settings!$B$6+I98*Settings!$B$7+J98*Settings!$B$8+K98*Settings!$B$9+L98*Settings!$B$10 | N98: =M98-INDEX(Settings!$G$4:$G$9,MATCH($E98,Settings!$F$4:$F$9,0)) | O98: =N98*INDEX(Settings!$H$4:$H$9,MATCH($E98,Settings!$F$4:$F$9,0)) | P98: MEDIUM | Q98: 3 INT TD on only 11 INTs; bad offense = more snaps
A99: 97 | B99: DST5 | C99: Broncos D/ST | D99: DEN | E99: DST | K99: 2.77 | L99: 0.65 | M99: =F99*Settings!$B$4+G99*Settings!$B$5+H99*Settings!$B$6+I99*Settings!$B$7+J99*Settings!$B$8+K99*Settings!$B$9+L99*Settings!$B$10 | N99: =M99-INDEX(Settings!$G$4:$G$9,MATCH($E99,Settings!$F$4:$F$9,0)) | O99: =N99*INDEX(Settings!$H$4:$H$9,MATCH($E99,Settings!$F$4:$F$9,0)) | P99: MEDIUM | Q99: Marvin Mims led PR yds 2025
A100: 98 | B100: DST6 | C100: Vikings D/ST | D100: MIN | E100: DST | K100: 2.77 | L100: 0.6 | M100: =F100*Settings!$B$4+G100*Settings!$B$5+H100*Settings!$B$6+I100*Settings!$B$7+J100*Settings!$B$8+K100*Settings!$B$9+L100*Settings!$B$10 | N100: =M100-INDEX(Settings!$G$4:$G$9,MATCH($E100,Settings!$F$4:$F$9,0)) | O100: =N100*INDEX(Settings!$H$4:$H$9,MATCH($E100,Settings!$F$4:$F$9,0)) | P100: MEDIUM | Q100: Led NFL forced fumbles 2025
...

Sheet QB
A1: QB — ranked by projected points
A2: Rank | B2: Pos | C2: Player | D2: Tm | E2: P | F2: PassTD | G2: RushTD | H2: RecTD | I2: FG | J2: PAT | K2: DefTD | L2: Saf | M2: Points | N2: VOR | O2: Adj VOR | P2: Conf | Q2: Notes
A3: 1 | B3: QB1 | C3: Josh Allen | D3: BUF | E3: QB | F3: 27 | G3: 12 | M3: =F3*Settings!$B$4+G3*Settings!$B$5+H3*Settings!$B$6+I3*Settings!$B$7+J3*Settings!$B$8+K3*Settings!$B$9+L3*Settings!$B$10 | N3: =M3-INDEX(Settings!$G$4:$G$9,MATCH($E3,Settings!$F$4:$F$9,0)) | O3: =N3*INDEX(Settings!$H$4:$H$9,MATCH($E3,Settings!$F$4:$F$9,0)) | P3: HIGH | Q3: TIER OF ONE. 12 rush TDs alone outscore 20 of 40 QBs in total
A4: 6 | B4: QB2 | C4: Jalen Hurts | D4: PHI | E4: QB | F4: 24 | G4: 8.5 | M4: =F4*Settings!$B$4+G4*Settings!$B$5+H4*Settings!$B$6+I4*Settings!$B$7+J4*Settings!$B$8+K4*Settings!$B$9+L4*Settings!$B$10 | N4: =M4-INDEX(Settings!$G$4:$G$9,MATCH($E4,Settings!$F$4:$F$9,0)) | O4: =N4*INDEX(Settings!$H$4:$H$9,MATCH($E4,Settings!$F$4:$F$9,0)) | P4: HIGH | Q4: Tush push survived 2026 rules vote; goal-line sneak intact
A5: 24 | B5: QB3 | C5: Joe Burrow | D5: CIN | E5: QB | F5: 33 | G5: 1.5 | M5: =F5*Settings!$B$4+G5*Settings!$B$5+H5*Settings!$B$6+I5*Settings!$B$7+J5*Settings!$B$8+K5*Settings!$B$9+L5*Settings!$B$10 | N5: =M5-INDEX(Settings!$G$4:$G$9,MATCH($E5,Settings!$F$4:$F$9,0)) | O5: =N5*INDEX(Settings!$H$4:$H$9,MATCH($E5,Settings!$F$4:$F$9,0)) | P5: HIGH | Q5: Volume passer; CIN 26.0 implied pts
A6: 25 | B6: QB4 | C6: Drake Maye | D6: NE | E6: QB | F6: 28 | G6: 4 | M6: =F6*Settings!$B$4+G6*Settings!$B$5+H6*Settings!$B$6+I6*Settings!$B$7+J6*Settings!$B$8+K6*Settings!$B$9+L6*Settings!$B$10 | N6: =M6-INDEX(Settings!$G$4:$G$9,MATCH($E6,Settings!$F$4:$F$9,0)) | O6: =N6*INDEX(Settings!$H$4:$H$9,MATCH($E6,Settings!$F$4:$F$9,0)) | P6: HIGH | Q6: NE 10.5 win total
A7: 33 | B7: QB5 | C7: Trevor Lawrence | D7: JAX | E7: QB | F7: 26 | G7: 4.5 | M7: =F7*Settings!$B$4+G7*Settings!$B$5+H7*Settings!$B$6+I7*Settings!$B$7+J7*Settings!$B$8+K7*Settings!$B$9+L7*Settings!$B$10 | N7: =M7-INDEX(Settings!$G$4:$G$9,MATCH($E7,Settings!$F$4:$F$9,0)) | O7: =N7*INDEX(Settings!$H$4:$H$9,MATCH($E7,Settings!$F$4:$F$9,0)) | P7: HIGH
A8: 34 | B8: QB6 | C8: Matthew Stafford | D8: LAR | E8: QB | F8: 34 | G8: 0.5 | M8: =F8*Settings!$B$4+G8*Settings!$B$5+H8*Settings!$B$6+I8*Settings!$B$7+J8*Settings!$B$8+K8*Settings!$B$9+L8*Settings!$B$10 | N8: =M8-INDEX(Settings!$G$4:$G$9,MATCH($E8,Settings!$F$4:$F$9,0)) | O8: =N8*INDEX(Settings!$H$4:$H$9,MATCH($E8,Settings!$F$4:$F$9,0)) | P8: HIGH | Q8: LAR highest implied pts 26.6 but zero rush value
A9: 37 | B9: QB7 | C9: Dak Prescott | D9: DAL | E9: QB | F9: 30.5 | G9: 2 | M9: =F9*Settings!$B$4+G9*Settings!$B$5+H9*Settings!$B$6+I9*Settings!$B$7+J9*Settings!$B$8+K9*Settings!$B$9+L9*Settings!$B$10 | N9: =M9-INDEX(Settings!$G$4:$G$9,MATCH($E9,Settings!$F$4:$F$9,0)) | O9: =N9*INDEX(Settings!$H$4:$H$9,MATCH($E9,Settings!$F$4:$F$9,0)) | P9: HIGH
A10: 44 | B10: QB8 | C10: Jaxson Dart | D10: NYG | E10: QB | F10: 22 | G10: 6 | M10: =F10*Settings!$B$4+G10*Settings!$B$5+H10*Settings!$B$6+I10*Settings!$B$7+J10*Settings!$B$8+K10*Settings!$B$9+L10*Settings!$B$10 | N10: =M10-INDEX(Settings!$G$4:$G$9,MATCH($E10,Settings!$F$4:$F$9,0)) | O10: =N10*INDEX(Settings!$H$4:$H$9,MATCH($E10,Settings!$F$4:$F$9,0)) | P10: HIGH | Q10: BIGGEST ADP ARBITRAGE. But new HC Harbaugh may curb rushing
A11: 45 | B11: QB9 | C11: Brock Purdy | D11: SF | E11: QB | F11: 27 | G11: 3.5 | M11: =F11*Settings!$B$4+G11*Settings!$B$5+H11*Settings!$B$6+I11*Settings!$B$7+J11*Settings!$B$8+K11*Settings!$B$9+L11*Settings!$B$10 | N11: =M11-INDEX(Settings!$G$4:$G$9,MATCH($E11,Settings!$F$4:$F$9,0)) | O11: =N11*INDEX(Settings!$H$4:$H$9,MATCH($E11,Settings!$F$4:$F$9,0)) | P11: HIGH
A12: 62 | B12: QB10 | C12: Lamar Jackson | D12: BAL | E12: QB | F12: 26.5 | G12: 3.5 | M12: =F12*Settings!$B$4+G12*Settings!$B$5+H12*Settings!$B$6+I12*Settings!$B$7+J12*Settings!$B$8+K12*Settings!$B$9+L12*Settings!$B$10 | N12: =M12-INDEX(Settings!$G$4:$G$9,MATCH($E12,Settings!$F$4:$F$9,0)) | O12: =N12*INDEX(Settings!$H$4:$H$9,MATCH($E12,Settings!$F$4:$F$9,0)) | P12: HIGH | Q12: BAL 11.5 win total
A13: 63 | B13: QB11 | C13: Jayden Daniels | D13: WAS | E13: QB | F13: 23.5 | G13: 5 | M13: =F13*Settings!$B$4+G13*Settings!$B$5+H13*Settings!$B$6+I13*Settings!$B$7+J13*Settings!$B$8+K13*Settings!$B$9+L13*Settings!$B$10 | N13: =M13-INDEX(Settings!$G$4:$G$9,MATCH($E13,Settings!$F$4:$F$9,0)) | O13: =N13*INDEX(Settings!$H$4:$H$9,MATCH($E13,Settings!$F$4:$F$9,0)) | P13: HIGH
A14: 64 | B14: QB12 | C14: Bo Nix | D14: DEN | E14: QB | F14: 26.5 | G14: 3.5 | M14: =F14*Settings!$B$4+G14*Settings!$B$5+H14*Settings!$B$6+I14*Settings!$B$7+J14*Settings!$B$8+K14*Settings!$B$9+L14*Settings!$B$10 | N14: =M14-INDEX(Settings!$G$4:$G$9,MATCH($E14,Settings!$F$4:$F$9,0)) | O14: =N14*INDEX(Settings!$H$4:$H$9,MATCH($E14,Settings!$F$4:$F$9,0)) | P14: HIGH
A15: 75 | B15: QB13 | C15: Caleb Williams | D15: CHI | E15: QB | F15: 27 | G15: 3 | M15: =F15*Settings!$B$4+G15*Settings!$B$5+H15*Settings!$B$6+I15*Settings!$B$7+J15*Settings!$B$8+K15*Settings!$B$9+L15*Settings!$B$10 | N15: =M15-INDEX(Settings!$G$4:$G$9,MATCH($E15,Settings!$F$4:$F$9,0)) | O15: =N15*INDEX(Settings!$H$4:$H$9,MATCH($E15,Settings!$F$4:$F$9,0)) | P15: HIGH
A16: 81 | B16: QB14 | C16: Justin Herbert | D16: LAC | E16: QB | F16: 27.5 | G16: 2.5 | M16: =F16*Settings!$B$4+G16*Settings!$B$5+H16*Settings!$B$6+I16*Settings!$B$7+J16*Settings!$B$8+K16*Settings!$B$9+L16*Settings!$B$10 | N16: =M16-INDEX(Settings!$G$4:$G$9,MATCH($E16,Settings!$F$4:$F$9,0)) | O16: =N16*INDEX(Settings!$H$4:$H$9,MATCH($E16,Settings!$F$4:$F$9,0)) | P16: HIGH
A17: 94 | B17: QB15 | C17: Patrick Mahomes | D17: KC | E17: QB | F17: 26 | G17: 3 | M17: =F17*Settings!$B$4+G17*Settings!$B$5+H17*Settings!$B$6+I17*Settings!$B$7+J17*Settings!$B$8+K17*Settings!$B$9+L17*Settings!$B$10 | N17: =M17-INDEX(Settings!$G$4:$G$9,MATCH($E17,Settings!$F$4:$F$9,0)) | O17: =N17*INDEX(Settings!$H$4:$H$9,MATCH($E17,Settings!$F$4:$F$9,0)) | P17: MEDIUM | Q17: INJURY RISK: torn ACL+LCL 2025; no preseason snaps
A18: 146 | B18: QB16 | C18: Jared Goff | D18: DET | E18: QB | F18: 30 | G18: 0.5 | M18: =F18*Settings!$B$4+G18*Settings!$B$5+H18*Settings!$B$6+I18*Settings!$B$7+J18*Settings!$B$8+K18*Settings!$B$9+L18*Settings!$B$10 | N18: =M18-INDEX(Settings!$G$4:$G$9,MATCH($E18,Settings!$F$4:$F$9,0)) | O18: =N18*INDEX(Settings!$H$4:$H$9,MATCH($E18,Settings!$F$4:$F$9,0)) | P18: MEDIUM | Q18: DET 26.1 implied pts; no rush value
A19: 147 | B19: QB17 | C19: Daniel Jones | D19: IND | E19: QB | F19: 21 | G19: 5 | M19: =F19*Settings!$B$4+G19*Settings!$B$5+H19*Settings!$B$6+I19*Settings!$B$7+J19*Settings!$B$8+K19*Settings!$B$9+L19*Settings!$B$10 | N19: =M19-INDEX(Settings!$G$4:$G$9,MATCH($E19,Settings!$F$4:$F$9,0)) | O19: =N19*INDEX(Settings!$H$4:$H$9,MATCH($E19,Settings!$F$4:$F$9,0)) | P19: MEDIUM | Q19: VALUE: Clay 6 rush TD Razzball 7.3; nobody drafts him for that
A20: 153 | B20: QB18 | C20: Tyler Shough | D20: NO | E20: QB | F20: 21.5 | G20: 4.5 | M20: =F20*Settings!$B$4+G20*Settings!$B$5+H20*Settings!$B$6+I20*Settings!$B$7+J20*Settings!$B$8+K20*Settings!$B$9+L20*Settings!$B$10 | N20: =M20-INDEX(Settings!$G$4:$G$9,MATCH($E20,Settings!$F$4:$F$9,0)) | O20: =N20*INDEX(Settings!$H$4:$H$9,MATCH($E20,Settings!$F$4:$F$9,0)) | P20: HIGH
A21: 179 | B21: QB19 | C21: Jordan Love | D21: GB | E21: QB | F21: 26.5 | G21: 1.5 | M21: =F21*Settings!$B$4+G21*Settings!$B$5+H21*Settings!$B$6+I21*Settings!$B$7+J21*Settings!$B$8+K21*Settings!$B$9+L21*Settings!$B$10 | N21: =M21-INDEX(Settings!$G$4:$G$9,MATCH($E21,Settings!$F$4:$F$9,0)) | O21: =N21*INDEX(Settings!$H$4:$H$9,MATCH($E21,Settings!$F$4:$F$9,0)) | P21: HIGH
A22: 197 | B22: QB20 | C22: Baker Mayfield | D22: TB | E22: QB | F22: 25.5 | G22: 1.5 | M22: =F22*Settings!$B$4+G22*Settings!$B$5+H22*Settings!$B$6+I22*Settings!$B$7+J22*Settings!$B$8+K22*Settings!$B$9+L22*Settings!$B$10 | N22: =M22-INDEX(Settings!$G$4:$G$9,MATCH($E22,Settings!$F$4:$F$9,0)) | O22: =N22*INDEX(Settings!$H$4:$H$9,MATCH($E22,Settings!$F$4:$F$9,0)) | P22: MEDIUM
A23: 206 | B23: QB21 | C23: Sam Darnold | D23: SEA | E23: QB | F23: 26 | G23: 1 | M23: =F23*Settings!$B$4+G23*Settings!$B$5+H23*Settings!$B$6+I23*Settings!$B$7+J23*Settings!$B$8+K23*Settings!$B$9+L23*Settings!$B$10 | N23: =M23-INDEX(Settings!$G$4:$G$9,MATCH($E23,Settings!$F$4:$F$9,0)) | O23: =N23*INDEX(Settings!$H$4:$H$9,MATCH($E23,Settings!$F$4:$F$9,0)) | P23: HIGH
A24: 211 | B24: QB22 | C24: Kyler Murray | D24: MIN | E24: QB | F24: 21.5 | G24: 3 | M24: =F24*Settings!$B$4+G24*Settings!$B$5+H24*Settings!$B$6+I24*Settings!$B$7+J24*Settings!$B$8+K24*Settings!$B$9+L24*Settings!$B$10 | N24: =M24-INDEX(Settings!$G$4:$G$9,MATCH($E24,Settings!$F$4:$F$9,0)) | O24: =N24*INDEX(Settings!$H$4:$H$9,MATCH($E24,Settings!$F$4:$F$9,0)) | P24: MEDIUM | Q24: Named Week 1 starter over McCarthy
A25: 225 | B25: QB23 | C25: Bryce Young | D25: CAR | E25: QB | F25: 21.5 | G25: 2.5 | M25: =F25*Settings!$B$4+G25*Settings!$B$5+H25*Settings!$B$6+I25*Settings!$B$7+J25*Settings!$B$8+K25*Settings!$B$9+L25*Settings!$B$10 | N25: =M25-INDEX(Settings!$G$4:$G$9,MATCH($E25,Settings!$F$4:$F$9,0)) | O25: =N25*INDEX(Settings!$H$4:$H$9,MATCH($E25,Settings!$F$4:$F$9,0)) | P25: MEDIUM
A26: 245 | B26: QB24 | C26: C.J. Stroud | D26: HOU | E26: QB | F26: 22.5 | G26: 1.5 | M26: =F26*Settings!$B$4+G26*Settings!$B$5+H26*Settings!$B$6+I26*Settings!$B$7+J26*Settings!$B$8+K26*Settings!$B$9+L26*Settings!$B$10 | N26: =M26-INDEX(Settings!$G$4:$G$9,MATCH($E26,Settings!$F$4:$F$9,0)) | O26: =N26*INDEX(Settings!$H$4:$H$9,MATCH($E26,Settings!$F$4:$F$9,0)) | P26: HIGH | Q26: Vegas is fading him
A27: 253 | B27: QB25 | C27: Aaron Rodgers | D27: PIT | E27: QB | F27: 22 | G27: 1 | M27: =F27*Settings!$B$4+G27*Settings!$B$5+H27*Settings!$B$6+I27*Settings!$B$7+J27*Settings!$B$8+K27*Settings!$B$9+L27*Settings!$B$10 | N27: =M27-INDEX(Settings!$G$4:$G$9,MATCH($E27,Settings!$F$4:$F$9,0)) | O27: =N27*INDEX(Settings!$H$4:$H$9,MATCH($E27,Settings!$F$4:$F$9,0)) | P27: MEDIUM
A28: 265 | B28: QB26 | C28: Geno Smith | D28: NYJ | E28: QB | F28: 19.5 | G28: 1.5 | M28: =F28*Settings!$B$4+G28*Settings!$B$5+H28*Settings!$B$6+I28*Settings!$B$7+J28*Settings!$B$8+K28*Settings!$B$9+L28*Settings!$B$10 | N28: =M28-INDEX(Settings!$G$4:$G$9,MATCH($E28,Settings!$F$4:$F$9,0)) | O28: =N28*INDEX(Settings!$H$4:$H$9,MATCH($E28,Settings!$F$4:$F$9,0)) | P28: MEDIUM | Q28: NYJ lowest implied total 18.4
A29: 267 | B29: QB27 | C29: Malik Willis | D29: MIA | E29: QB | F29: 14 | G29: 4 | M29: =F29*Settings!$B$4+G29*Settings!$B$5+H29*Settings!$B$6+I29*Settings!$B$7+J29*Settings!$B$8+K29*Settings!$B$9+L29*Settings!$B$10 | N29: =M29-INDEX(Settings!$G$4:$G$9,MATCH($E29,Settings!$F$4:$F$9,0)) | O29: =N29*INDEX(Settings!$H$4:$H$9,MATCH($E29,Settings!$F$4:$F$9,0)) | P29: LOW | Q29: LOTTERY TICKET: Yahoo proj 7 rush TD Razzball 2.8
A30: 271 | B30: QB28 | C30: Cam Ward | D30: TEN | E30: QB | F30: 18.5 | G30: 1.5 | M30: =F30*Settings!$B$4+G30*Settings!$B$5+H30*Settings!$B$6+I30*Settings!$B$7+J30*Settings!$B$8+K30*Settings!$B$9+L30*Settings!$B$10 | N30: =M30-INDEX(Settings!$G$4:$G$9,MATCH($E30,Settings!$F$4:$F$9,0)) | O30: =N30*INDEX(Settings!$H$4:$H$9,MATCH($E30,Settings!$F$4:$F$9,0)) | P30: MEDIUM
A31: 280 | B31: QB29 | C31: Jacoby Brissett | D31: ARI | E31: QB | F31: 18 | G31: 1 | M31: =F31*Settings!$B$4+G31*Settings!$B$5+H31*Settings!$B$6+I31*Settings!$B$7+J31*Settings!$B$8+K31*Settings!$B$9+L31*Settings!$B$10 | N31: =M31-INDEX(Settings!$G$4:$G$9,MATCH($E31,Settings!$F$4:$F$9,0)) | O31: =N31*INDEX(Settings!$H$4:$H$9,MATCH($E31,Settings!$F$4:$F$9,0)) | P31: MEDIUM | Q31: ARI 3.5 win total worst in NFL
A32: 281 | B32: QB30 | C32: Fernando Mendoza | D32: LV | E32: QB | F32: 13 | G32: 1.5 | M32: =F32*Settings!$B$4+G32*Settings!$B$5+H32*Settings!$B$6+I32*Settings!$B$7+J32*Settings!$B$8+K32*Settings!$B$9+L32*Settings!$B$10 | N32: =M32-INDEX(Settings!$G$4:$G$9,MATCH($E32,Settings!$F$4:$F$9,0)) | O32: =N32*INDEX(Settings!$H$4:$H$9,MATCH($E32,Settings!$F$4:$F$9,0)) | P32: LOW | Q32: Rookie No.1 overall; Cousins starts Week 1 but handoff expected
A33: 282 | B33: QB31 | C33: Shedeur Sanders | D33: CLE | E33: QB | F33: 11 | G33: 1.5 | M33: =F33*Settings!$B$4+G33*Settings!$B$5+H33*Settings!$B$6+I33*Settings!$B$7+J33*Settings!$B$8+K33*Settings!$B$9+L33*Settings!$B$10 | N33: =M33-INDEX(Settings!$G$4:$G$9,MATCH($E33,Settings!$F$4:$F$9,0)) | O33: =N33*INDEX(Settings!$H$4:$H$9,MATCH($E33,Settings!$F$4:$F$9,0)) | P33: LOW | Q33: Watson named starter but Clay projects Sanders more volume
A34: 283 | B34: QB32 | C34: Tua Tagovailoa | D34: ATL | E34: QB | F34: 12 | M34: =F34*Settings!$B$4+G34*Settings!$B$5+H34*Settings!$B$6+I34*Settings!$B$7+J34*Settings!$B$8+K34*Settings!$B$9+L34*Settings!$B$10 | N34: =M34-INDEX(Settings!$G$4:$G$9,MATCH($E34,Settings!$F$4:$F$9,0)) | O34: =N34*INDEX(Settings!$H$4:$H$9,MATCH($E34,Settings!$F$4:$F$9,0)) | P34: LOW | Q34: ATL QB job unsettled; no rush value either way
A35: 284 | B35: QB33 | C35: Deshaun Watson | D35: CLE | E35: QB | F35: 10 | G35: 1 | M35: =F35*Settings!$B$4+G35*Settings!$B$5+H35*Settings!$B$6+I35*Settings!$B$7+J35*Settings!$B$8+K35*Settings!$B$9+L35*Settings!$B$10 | N35: =M35-INDEX(Settings!$G$4:$G$9,MATCH($E35,Settings!$F$4:$F$9,0)) | O35: =N35*INDEX(Settings!$H$4:$H$9,MATCH($E35,Settings!$F$4:$F$9,0)) | P35: LOW | Q35: Named Week 1 starter; sources conflict badly
A36: 285 | B36: QB34 | C36: Michael Penix Jr. | D36: ATL | E36: QB | F36: 8 | G36: 1 | M36: =F36*Settings!$B$4+G36*Settings!$B$5+H36*Settings!$B$6+I36*Settings!$B$7+J36*Settings!$B$8+K36*Settings!$B$9+L36*Settings!$B$10 | N36: =M36-INDEX(Settings!$G$4:$G$9,MATCH($E36,Settings!$F$4:$F$9,0)) | O36: =N36*INDEX(Settings!$H$4:$H$9,MATCH($E36,Settings!$F$4:$F$9,0)) | P36: LOW | Q36: Recovering from torn ACL not fully cleared
A37: 286 | B37: QB35 | C37: Kirk Cousins | D37: LV | E37: QB | F37: 6 | M37: =F37*Settings!$B$4+G37*Settings!$B$5+H37*Settings!$B$6+I37*Settings!$B$7+J37*Settings!$B$8+K37*Settings!$B$9+L37*Settings!$B$10 | N37: =M37-INDEX(Settings!$G$4:$G$9,MATCH($E37,Settings!$F$4:$F$9,0)) | O37: =N37*INDEX(Settings!$H$4:$H$9,MATCH($E37,Settings!$F$4:$F$9,0)) | P37: LOW
A38: 287 | B38: QB36 | C38: J.J. McCarthy | D38: MIN | E38: QB | F38: 3 | G38: 1 | M38: =F38*Settings!$B$4+G38*Settings!$B$5+H38*Settings!$B$6+I38*Settings!$B$7+J38*Settings!$B$8+K38*Settings!$B$9+L38*Settings!$B$10 | N38: =M38-INDEX(Settings!$G$4:$G$9,MATCH($E38,Settings!$F$4:$F$9,0)) | O38: =N38*INDEX(Settings!$H$4:$H$9,MATCH($E38,Settings!$F$4:$F$9,0)) | P38: LOW | Q38: Lost job to Murray
A39: 288 | B39: QB37 | C39: Justin Fields | D39: KC | E39: QB | F39: 1 | G39: 1 | M39: =F39*Settings!$B$4+G39*Settings!$B$5+H39*Settings!$B$6+I39*Settings!$B$7+J39*Settings!$B$8+K39*Settings!$B$9+L39*Settings!$B$10 | N39: =M39-INDEX(Settings!$G$4:$G$9,MATCH($E39,Settings!$F$4:$F$9,0)) | O39: =N39*INDEX(Settings!$H$4:$H$9,MATCH($E39,Settings!$F$4:$F$9,0)) | P39: LOW | Q39: BEST HANDCUFF IN FORMAT: rushing QB behind Mahomes ACL recovery

Sheet RB
A1: RB — ranked by projected points
A2: Rank | B2: Pos | C2: Player | D2: Tm | E2: P | F2: PassTD | G2: RushTD | H2: RecTD | I2: FG | J2: PAT | K2: DefTD | L2: Saf | M2: Points | N2: VOR | O2: Adj VOR | P2: Conf | Q2: Notes
A3: 2 | B3: RB1 | C3: Jahmyr Gibbs | D3: DET | E3: RB | G3: 13.4 | H3: 3.8 | M3: =F3*Settings!$B$4+G3*Settings!$B$5+H3*Settings!$B$6+I3*Settings!$B$7+J3*Settings!$B$8+K3*Settings!$B$9+L3*Settings!$B$10 | N3: =M3-INDEX(Settings!$G$4:$G$9,MATCH($E3,Settings!$F$4:$F$9,0)) | O3: =N3*INDEX(Settings!$H$4:$H$9,MATCH($E3,Settings!$F$4:$F$9,0)) | P3: HIGH | Q3: Overall RB1
A4: 3 | B4: RB2 | C4: Jonathan Taylor | D4: IND | E4: RB | G4: 12.2 | H4: 1.3 | M4: =F4*Settings!$B$4+G4*Settings!$B$5+H4*Settings!$B$6+I4*Settings!$B$7+J4*Settings!$B$8+K4*Settings!$B$9+L4*Settings!$B$10 | N4: =M4-INDEX(Settings!$G$4:$G$9,MATCH($E4,Settings!$F$4:$F$9,0)) | O4: =N4*INDEX(Settings!$H$4:$H$9,MATCH($E4,Settings!$F$4:$F$9,0)) | P4: HIGH | Q4: True goal-line back
A5: 4 | B5: RB3 | C5: Christian McCaffrey | D5: SF | E5: RB | G5: 9 | H5: 4.4 | M5: =F5*Settings!$B$4+G5*Settings!$B$5+H5*Settings!$B$6+I5*Settings!$B$7+J5*Settings!$B$8+K5*Settings!$B$9+L5*Settings!$B$10 | N5: =M5-INDEX(Settings!$G$4:$G$9,MATCH($E5,Settings!$F$4:$F$9,0)) | O5: =N5*INDEX(Settings!$H$4:$H$9,MATCH($E5,Settings!$F$4:$F$9,0)) | P5: HIGH | Q5: Goal-line yes
A6: 5 | B6: RB4 | C6: Derrick Henry | D6: BAL | E6: RB | G6: 12.8 | H6: 0.6 | M6: =F6*Settings!$B$4+G6*Settings!$B$5+H6*Settings!$B$6+I6*Settings!$B$7+J6*Settings!$B$8+K6*Settings!$B$9+L6*Settings!$B$10 | N6: =M6-INDEX(Settings!$G$4:$G$9,MATCH($E6,Settings!$F$4:$F$9,0)) | O6: =N6*INDEX(Settings!$H$4:$H$9,MATCH($E6,Settings!$F$4:$F$9,0)) | P6: HIGH | Q6: Vegas HIGHER than consensus here
A7: 7 | B7: RB5 | C7: James Cook III | D7: BUF | E7: RB | G7: 10.8 | H7: 1.8 | M7: =F7*Settings!$B$4+G7*Settings!$B$5+H7*Settings!$B$6+I7*Settings!$B$7+J7*Settings!$B$8+K7*Settings!$B$9+L7*Settings!$B$10 | N7: =M7-INDEX(Settings!$G$4:$G$9,MATCH($E7,Settings!$F$4:$F$9,0)) | O7: =N7*INDEX(Settings!$H$4:$H$9,MATCH($E7,Settings!$F$4:$F$9,0)) | P7: HIGH | Q7: Allen vulture tax already priced into line
A8: 8 | B8: RB6 | C8: Josh Jacobs | D8: GB | E8: RB | G8: 11.3 | H8: 1.3 | M8: =F8*Settings!$B$4+G8*Settings!$B$5+H8*Settings!$B$6+I8*Settings!$B$7+J8*Settings!$B$8+K8*Settings!$B$9+L8*Settings!$B$10 | N8: =M8-INDEX(Settings!$G$4:$G$9,MATCH($E8,Settings!$F$4:$F$9,0)) | O8: =N8*INDEX(Settings!$H$4:$H$9,MATCH($E8,Settings!$F$4:$F$9,0)) | P8: HIGH | Q8: Goal-line yes
A9: 10 | B9: RB7 | C9: Bijan Robinson | D9: ATL | E9: RB | G9: 8.7 | H9: 3.3 | M9: =F9*Settings!$B$4+G9*Settings!$B$5+H9*Settings!$B$6+I9*Settings!$B$7+J9*Settings!$B$8+K9*Settings!$B$9+L9*Settings!$B$10 | N9: =M9-INDEX(Settings!$G$4:$G$9,MATCH($E9,Settings!$F$4:$F$9,0)) | O9: =N9*INDEX(Settings!$H$4:$H$9,MATCH($E9,Settings!$F$4:$F$9,0)) | P9: HIGH | Q9: CAUTION only 48 pct of inside-5 carries in 2025
A10: 11 | B10: RB8 | C10: Kyren Williams | D10: LAR | E10: RB | G10: 10.1 | H10: 1.8 | M10: =F10*Settings!$B$4+G10*Settings!$B$5+H10*Settings!$B$6+I10*Settings!$B$7+J10*Settings!$B$8+K10*Settings!$B$9+L10*Settings!$B$10 | N10: =M10-INDEX(Settings!$G$4:$G$9,MATCH($E10,Settings!$F$4:$F$9,0)) | O10: =N10*INDEX(Settings!$H$4:$H$9,MATCH($E10,Settings!$F$4:$F$9,0)) | P10: HIGH | Q10: Alternates drives with Corum
A11: 12 | B11: RB9 | C11: Javonte Williams | D11: DAL | E11: RB | G11: 10.6 | H11: 1.2 | M11: =F11*Settings!$B$4+G11*Settings!$B$5+H11*Settings!$B$6+I11*Settings!$B$7+J11*Settings!$B$8+K11*Settings!$B$9+L11*Settings!$B$10 | N11: =M11-INDEX(Settings!$G$4:$G$9,MATCH($E11,Settings!$F$4:$F$9,0)) | O11: =N11*INDEX(Settings!$H$4:$H$9,MATCH($E11,Settings!$F$4:$F$9,0)) | P11: HIGH | Q11: Goal-line yes
A12: 16 | B12: RB10 | C12: Omarion Hampton | D12: LAC | E12: RB | G12: 9.2 | H12: 1.9 | M12: =F12*Settings!$B$4+G12*Settings!$B$5+H12*Settings!$B$6+I12*Settings!$B$7+J12*Settings!$B$8+K12*Settings!$B$9+L12*Settings!$B$10 | N12: =M12-INDEX(Settings!$G$4:$G$9,MATCH($E12,Settings!$F$4:$F$9,0)) | O12: =N12*INDEX(Settings!$H$4:$H$9,MATCH($E12,Settings!$F$4:$F$9,0)) | P12: HIGH | Q12: Goal-line yes
A13: 18 | B13: RB11 | C13: Chase Brown | D13: CIN | E13: RB | G13: 7.4 | H13: 3.6 | M13: =F13*Settings!$B$4+G13*Settings!$B$5+H13*Settings!$B$6+I13*Settings!$B$7+J13*Settings!$B$8+K13*Settings!$B$9+L13*Settings!$B$10 | N13: =M13-INDEX(Settings!$G$4:$G$9,MATCH($E13,Settings!$F$4:$F$9,0)) | O13: =N13*INDEX(Settings!$H$4:$H$9,MATCH($E13,Settings!$F$4:$F$9,0)) | P13: HIGH | Q13: Vegas LOWER than consensus
A14: 19 | B14: RB12 | C14: Saquon Barkley | D14: PHI | E14: RB | G14: 8.6 | H14: 2.1 | M14: =F14*Settings!$B$4+G14*Settings!$B$5+H14*Settings!$B$6+I14*Settings!$B$7+J14*Settings!$B$8+K14*Settings!$B$9+L14*Settings!$B$10 | N14: =M14-INDEX(Settings!$G$4:$G$9,MATCH($E14,Settings!$F$4:$F$9,0)) | O14: =N14*INDEX(Settings!$H$4:$H$9,MATCH($E14,Settings!$F$4:$F$9,0)) | P14: HIGH | Q14: TRAP: Hurts vultures 8.5 rush TDs; not priced in
... A21: 60 | B21: RB19 | C21: Cam Skattebo | D21: NYG | E21: RB | G21: 7.4 | H21: 1.2 | M21: =F21*Settings!$B$4+G21*Settings!$B$5+H21*Settings!$B$6+I21*Settings!$B$7+J21*Settings!$B$8+K21*Settings!$B$9+L21*Settings!$B$10 | N21: =M21-INDEX(Settings!$G$4:$G$9,MATCH($E21,Settings!$F$4:$F$9,0)) | O21: =N21*INDEX(Settings!$H$4:$H$9,MATCH($E21,Settings!$F$4:$F$9,0)) | P21: HIGH | Q21: Goal-line yes
A22: 61 | B22: RB20 | C22: D'Andre Swift | D22: CHI | E22: RB | G22: 7.5 | H22: 1.1 | M22: =F22*Settings!$B$4+G22*Settings!$B$5+H22*Settings!$B$6+I22*Settings!$B$7+J22*Settings!$B$8+K22*Settings!$B$9+L22*Settings!$B$10 | N22: =M22-INDEX(Settings!$G$4:$G$9,MATCH($E22,Settings!$F$4:$F$9,0)) | O22: =N22*INDEX(Settings!$H$4:$H$9,MATCH($E22,Settings!$F$4:$F$9,0)) | P22: HIGH
A23: 71 | B23: RB21 | C23: Rhamondre Stevenson | D23: NE | E23: RB | G23: 6.9 | H23: 1.6 | M23: =F23*Settings!$B$4+G23*Settings!$B$5+H23*Settings!$B$6+I23*Settings!$B$7+J23*Settings!$B$8+K23*Settings!$B$9+L23*Settings!$B$10 | N23: =M23-INDEX(Settings!$G$4:$G$9,MATCH($E23,Settings!$F$4:$F$9,0)) | O23: =N23*INDEX(Settings!$H$4:$H$9,MATCH($E23,Settings!$F$4:$F$9,0)) | P23: HIGH | Q23: Goal-line yes
A24: 72 | B24: RB22 | C24: Bhayshul Tuten | D24: JAX | E24: RB | G24: 6.8 | H24: 1.7 | M24: =F24*Settings!$B$4+G24*Settings!$B$5+H24*Settings!$B$6+I24*Settings!$B$7+J24*Settings!$B$8+K24*Settings!$B$9+L24*Settings!$B$10 | N24: =M24-INDEX(Settings!$G$4:$G$9,MATCH($E24,Settings!$F$4:$F$9,0)) | O24: =N24*INDEX(Settings!$H$4:$H$9,MATCH($E24,Settings!$F$4:$F$9,0)) | P24: HIGH | Q24: But Rodriguez owns goal line
A25: 79 | B25: RB23 | C25: Bucky Irving | D25: TB | E25: RB | G25: 6.2 | H25: 1.9 | M25: =F25*Settings!$B$4+G25*Settings!$B$5+H25*Settings!$B$6+I25*Settings!$B$7+J25*Settings!$B$8+K25*Settings!$B$9+L25*Settings!$B$10 | N25: =M25-INDEX(Settings!$G$4:$G$9,MATCH($E25,Settings!$F$4:$F$9,0)) | O25: =N25*INDEX(Settings!$H$4:$H$9,MATCH($E25,Settings!$F$4:$F$9,0)) | P25: HIGH | Q25: TRAP: ZERO carries inside the 5 in 2025
A26: 83 | B26: RB24 | C26: Quinshon Judkins | D26: CLE | E26: RB | G26: 7.2 | H26: 0.8 | M26: =F26*Settings!$B$4+G26*Settings!$B$5+H26*Settings!$B$6+I26*Settings!$B$7+J26*Settings!$B$8+K26*Settings!$B$9+L26*Settings!$B$10 | N26: =M26-INDEX(Settings!$G$4:$G$9,MATCH($E26,Settings!$F$4:$F$9,0)) | O26: =N26*INDEX(Settings!$H$4:$H$9,MATCH($E26,Settings!$F$4:$F$9,0)) | P26: HIGH | Q26: Goal-line yes
A27: 84 | B27: RB25 | C27: TreVeyon Henderson | D27: NE | E27: RB | G27: 6.8 | H27: 1.2 | M27: =F27*Settings!$B$4+G27*Settings!$B$5+H27*Settings!$B$6+I27*Settings!$B$7+J27*Settings!$B$8+K27*Settings!$B$9+L27*Settings!$B$10 | N27: =M27-INDEX(Settings!$G$4:$G$9,MATCH($E27,Settings!$F$4:$F$9,0)) | O27: =N27*INDEX(Settings!$H$4:$H$9,MATCH($E27,Settings!$F$4:$F$9,0)) | P27: HIGH | Q27: Not the goal-line back
A28: 92 | B28: RB26 | C28: David Montgomery | D28: HOU | E28: RB | G28: 7 | H28: 0.8 | M28: =F28*Settings!$B$4+G28*Settings!$B$5+H28*Settings!$B$6+I28*Settings!$B$7+J28*Settings!$B$8+K28*Settings!$B$9+L28*Settings!$B$10 | N28: =M28-INDEX(Settings!$G$4:$G$9,MATCH($E28,Settings!$F$4:$F$9,0)) | O28: =N28*INDEX(Settings!$H$4:$H$9,MATCH($E28,Settings!$F$4:$F$9,0)) | P28: HIGH | Q28: Traded DET to HOU
A29: 100 | B29: RB27 | C29: J.K. Dobbins | D29: DEN | E29: RB | G29: 6.8 | H29: 0.9 | M29: =F29*Settings!$B$4+G29*Settings!$B$5+H29*Settings!$B$6+I29*Settings!$B$7+J29*Settings!$B$8+K29*Settings!$B$9+L29*Settings!$B$10 | N29: =M29-INDEX(Settings!$G$4:$G$9,MATCH($E29,Settings!$F$4:$F$9,0)) | O29: =N29*INDEX(Settings!$H$4:$H$9,MATCH($E29,Settings!$F$4:$F$9,0)) | P29: HIGH | Q29: Goal-line yes
A30: 113 | B30: RB28 | C30: Travis Etienne Jr. | D30: NO | E30: RB | G30: 5.6 | H30: 2 | M30: =F30*Settings!$B$4+G30*Settings!$B$5+H30*Settings!$B$6+I30*Settings!$B$7+J30*Settings!$B$8+K30*Settings!$B$9+L30*Settings!$B$10 | N30: =M30-INDEX(Settings!$G$4:$G$9,MATCH($E30,Settings!$F$4:$F$9,0)) | O30: =N30*INDEX(Settings!$H$4:$H$9,MATCH($E30,Settings!$F$4:$F$9,0)) | P30: HIGH | Q30: Traded JAX to NO
A31: 129 | B31: RB29 | C31: Jacory Croskey-Merritt | D31: WAS | E31: RB | G31: 7.2 | H31: 0.3 | M31: =F31*Settings!$B$4+G31*Settings!$B$5+H31*Settings!$B$6+I31*Settings!$B$7+J31*Settings!$B$8+K31*Settings!$B$9+L31*Settings!$B$10 | N31: =M31-INDEX(Settings!$G$4:$G$9,MATCH($E31,Settings!$F$4:$F$9,0)) | O31: =N31*INDEX(Settings!$H$4:$H$9,MATCH($E31,Settings!$F$4:$F$9,0)) | P31: HIGH | Q31: Goal-line yes but rookie Kaytron Allen vultures
A32: 151 | B32: RB30 | C32: Blake Corum | D32: LAR | E32: RB | G32: 6.7 | H32: 0.3 | M32: =F32*Settings!$B$4+G32*Settings!$B$5+H32*Settings!$B$6+I32*Settings!$B$7+J32*Settings!$B$8+K32*Settings!$B$9+L32*Settings!$B$10 | N32: =M32-INDEX(Settings!$G$4:$G$9,MATCH($E32,Settings!$F$4:$F$9,0)) | O32: =N32*INDEX(Settings!$H$4:$H$9,MATCH($E32,Settings!$F$4:$F$9,0)) | P32: HIGH | Q32: Alternates drives with Kyren
A33: 155 | B33: RB31 | C33: Rachaad White | D33: WAS | E33: RB | G33: 5 | H33: 1.9 | M33: =F33*Settings!$B$4+G33*Settings!$B$5+H33*Settings!$B$6+I33*Settings!$B$7+J33*Settings!$B$8+K33*Settings!$B$9+L33*Settings!$B$10 | N33: =M33-INDEX(Settings!$G$4:$G$9,MATCH($E33,Settings!$F$4:$F$9,0)) | O33: =N33*INDEX(Settings!$H$4:$H$9,MATCH($E33,Settings!$F$4:$F$9,0)) | P33: HIGH | Q33: Signed TB to WAS
A34: 166 | B34: RB32 | C34: Jaylen Warren | D34: PIT | E34: RB | G34: 4.8 | H34: 1.8 | M34: =F34*Settings!$B$4+G34*Settings!$B$5+H34*Settings!$B$6+I34*Settings!$B$7+J34*Settings!$B$8+K34*Settings!$B$9+L34*Settings!$B$10 | N34: =M34-INDEX(Settings!$G$4:$G$9,MATCH($E34,Settings!$F$4:$F$9,0)) | O34: =N34*INDEX(Settings!$H$4:$H$9,MATCH($E34,Settings!$F$4:$F$9,0)) | P34: HIGH | Q34: True 50-50 with Dowdle
A35: 188 | B35: RB33 | C35: Rico Dowdle | D35: PIT | E35: RB | G35: 5.2 | H35: 1.1 | M35: =F35*Settings!$B$4+G35*Settings!$B$5+H35*Settings!$B$6+I35*Settings!$B$7+J35*Settings!$B$8+K35*Settings!$B$9+L35*Settings!$B$10 | N35: =M35-INDEX(Settings!$G$4:$G$9,MATCH($E35,Settings!$F$4:$F$9,0)) | O35: =N35*INDEX(Settings!$H$4:$H$9,MATCH($E35,Settings!$F$4:$F$9,0)) | P35: HIGH | Q35: True 50-50 with Warren
A36: 191 | B36: RB34 | C36: Chuba Hubbard | D36: CAR | E36: RB | G36: 4.9 | H36: 1.2 | M36: =F36*Settings!$B$4+G36*Settings!$B$5+H36*Settings!$B$6+I36*Settings!$B$7+J36*Settings!$B$8+K36*Settings!$B$9+L36*Settings!$B$10 | N36: =M36-INDEX(Settings!$G$4:$G$9,MATCH($E36,Settings!$F$4:$F$9,0)) | O36: =N36*INDEX(Settings!$H$4:$H$9,MATCH($E36,Settings!$F$4:$F$9,0)) | P36: MEDIUM
A37: 192 | B37: RB35 | C37: Tony Pollard | D37: TEN | E37: RB | G37: 5.2 | H37: 0.8 | M37: =F37*Settings!$B$4+G37*Settings!$B$5+H37*Settings!$B$6+I37*Settings!$B$7+J37*Settings!$B$8+K37*Settings!$B$9+L37*Settings!$B$10 | N37: =M37-INDEX(Settings!$G$4:$G$9,MATCH($E37,Settings!$F$4:$F$9,0)) | O37: =N37*INDEX(Settings!$H$4:$H$9,MATCH($E37,Settings!$F$4:$F$9,0)) | P37: HIGH
A38: 196 | B38: RB36 | C38: Kyle Monangai | D38: CHI | E38: RB | G38: 5.2 | H38: 0.7 | M38: =F38*Settings!$B$4+G38*Settings!$B$5+H38*Settings!$B$6+I38*Settings!$B$7+J38*Settings!$B$8+K38*Settings!$B$9+L38*Settings!$B$10 | N38: =M38-INDEX(Settings!$G$4:$G$9,MATCH($E38,Settings!$F$4:$F$9,0)) | O38: =N38*INDEX(Settings!$H$4:$H$9,MATCH($E38,Settings!$F$4:$F$9,0)) | P38: MEDIUM
A39: 199 | B39: RB37 | C39: Jordan Mason | D39: MIN | E39: RB | G39: 5.7 | H39: 0.1 | M39: =F39*Settings!$B$4+G39*Settings!$B$5+H39*Settings!$B$6+I39*Settings!$B$7+J39*Settings!$B$8+K39*Settings!$B$9+L39*Settings!$B$10 | N39: =M39-INDEX(Settings!$G$4:$G$9,MATCH($E39,Settings!$F$4:$F$9,0)) | O39: =N39*INDEX(Settings!$H$4:$H$9,MATCH($E39,Settings!$F$4:$F$9,0)) | P39: HIGH | Q39: Goal-line yes; Vegas lower than consensus
A40: 200 | B40: RB38 | C40: RJ Harvey | D40: DEN | E40: RB | G40: 3 | H40: 2.8 | M40: =F40*Settings!$B$4+G40*Settings!$B$5+H40*Settings!$B$6+I40*Settings!$B$7+J40*Settings!$B$8+K40*Settings!$B$9+L40*Settings!$B$10 | N40: =M40-INDEX(Settings!$G$4:$G$9,MATCH($E40,Settings!$F$4:$F$9,0)) | O40: =N40*INDEX(Settings!$H$4:$H$9,MATCH($E40,Settings!$F$4:$F$9,0)) | P40: HIGH
A41: 201 | B41: RB39 | C41: Kenny Gainwell | D41: TB | E41: RB | G41: 3.8 | H41: 2 | M41: =F41*Settings!$B$4+G41*Settings!$B$5+H41*Settings!$B$6+I41*Settings!$B$7+J41*Settings!$B$8+K41*Settings!$B$9+L41*Settings!$B$10 | N41: =M41-INDEX(Settings!$G$4:$G$9,MATCH($E41,Settings!$F$4:$F$9,0)) | O41: =N41*INDEX(Settings!$H$4:$H$9,MATCH($E41,Settings!$F$4:$F$9,0)) | P41: HIGH
A42: 205 | B42: RB40 | C42: Zach Charbonnet | D42: SEA | E42: RB | G42: 5 | H42: 0.7 | M42: =F42*Settings!$B$4+G42*Settings!$B$5+H42*Settings!$B$6+I42*Settings!$B$7+J42*Settings!$B$8+K42*Settings!$B$9+L42*Settings!$B$10 | N42: =M42-INDEX(Settings!$G$4:$G$9,MATCH($E42,Settings!$F$4:$F$9,0)) | O42: =N42*INDEX(Settings!$H$4:$H$9,MATCH($E42,Settings!$F$4:$F$9,0)) | P42: MEDIUM | Q42: Torn ACL Feb surgery; on PUP; ESPN number too aggressive
A43: 214 | B43: RB41 | C43: Jonathon Brooks | D43: CAR | E43: RB | G43: 4.2 | H43: 1.1 | M43: =F43*Settings!$B$4+G43*Settings!$B$5+H43*Settings!$B$6+I43*Settings!$B$7+J43*Settings!$B$8+K43*Settings!$B$9+L43*Settings!$B$10 | N43: =M43-INDEX(Settings!$G$4:$G$9,MATCH($E43,Settings!$F$4:$F$9,0)) | O43: =N43*INDEX(Settings!$H$4:$H$9,MATCH($E43,Settings!$F$4:$F$9,0)) | P43: HIGH | Q43: Repeat ACL history
A44: 228 | B44: RB42 | C44: Aaron Jones Sr. | D44: MIN | E44: RB | G44: 3.1 | H44: 1.6 | M44: =F44*Settings!$B$4+G44*Settings!$B$5+H44*Settings!$B$6+I44*Settings!$B$7+J44*Settings!$B$8+K44*Settings!$B$9+L44*Settings!$B$10 | N44: =M44-INDEX(Settings!$G$4:$G$9,MATCH($E44,Settings!$F$4:$F$9,0)) | O44: =N44*INDEX(Settings!$H$4:$H$9,MATCH($E44,Settings!$F$4:$F$9,0)) | P44: HIGH
A45: 248 | B45: RB43 | C45: Isiah Pacheco | D45: DET | E45: RB | G45: 3.8 | H45: 0.4 | M45: =F45*Settings!$B$4+G45*Settings!$B$5+H45*Settings!$B$6+I45*Settings!$B$7+J45*Settings!$B$8+K45*Settings!$B$9+L45*Settings!$B$10 | N45: =M45-INDEX(Settings!$G$4:$G$9,MATCH($E45,Settings!$F$4:$F$9,0)) | O45: =N45*INDEX(Settings!$H$4:$H$9,MATCH($E45,Settings!$F$4:$F$9,0)) | P45: HIGH | Q45: Signed KC to DET
A46: 249 | B46: RB44 | C46: Brian Robinson Jr. | D46: ATL | E46: RB | G46: 3.9 | H46: 0.1 | M46: =F46*Settings!$B$4+G46*Settings!$B$5+H46*Settings!$B$6+I46*Settings!$B$7+J46*Settings!$B$8+K46*Settings!$B$9+L46*Settings!$B$10 | N46: =M46-INDEX(Settings!$G$4:$G$9,MATCH($E46,Settings!$F$4:$F$9,0)) | O46: =N46*INDEX(Settings!$H$4:$H$9,MATCH($E46,Settings!$F$4:$F$9,0)) | P46: HIGH | Q46: Vultures Bijan at goal line
A47: 250 | B47: RB45 | C47: Tyjae Spears | D47: TEN | E47: RB | G47: 2.5 | H47: 1.3 | M47: =F47*Settings!$B$4+G47*Settings!$B$5+H47*Settings!$B$6+I47*Settings!$B$7+J47*Settings!$B$8+K47*Settings!$B$9+L47*Settings!$B$10 | N47: =M47-INDEX(Settings!$G$4:$G$9,MATCH($E47,Settings!$F$4:$F$9,0)) | O47: =N47*INDEX(Settings!$H$4:$H$9,MATCH($E47,Settings!$F$4:$F$9,0)) | P47: HIGH
A48: 251 | B48: RB46 | C48: Chris Rodriguez Jr. | D48: JAX | E48: RB | G48: 3.7 | H48: 0.1 | M48: =F48*Settings!$B$4+G48*Settings!$B$5+H48*Settings!$B$6+I48*Settings!$B$7+J48*Settings!$B$8+K48*Settings!$B$9+L48*Settings!$B$10 | N48: =M48-INDEX(Settings!$G$4:$G$9,MATCH($E48,Settings!$F$4:$F$9,0)) | O48: =N48*INDEX(Settings!$H$4:$H$9,MATCH($E48,Settings!$F$4:$F$9,0)) | P48: HIGH | Q48: SLEEPER: hand-picked by Coen as goal-line back over Tuten
A49: 252 | B49: RB47 | C49: Woody Marks | D49: HOU | E49: RB | G49: 2.5 | H49: 1.1 | M49: =F49*Settings!$B$4+G49*Settings!$B$5+H49*Settings!$B$6+I49*Settings!$B$7+J49*Settings!$B$8+K49*Settings!$B$9+L49*Settings!$B$10 | N49: =M49-INDEX(Settings!$G$4:$G$9,MATCH($E49,Settings!$F$4:$F$9,0)) | O49: =N49*INDEX(Settings!$H$4:$H$9,MATCH($E49,Settings!$F$4:$F$9,0)) | P49: HIGH
A50: 254 | B50: RB48 | C50: Samaje Perine | D50: CIN | E50: RB | G50: 2.6 | H50: 0.8 | M50: =F50*Settings!$B$4+G50*Settings!$B$5+H50*Settings!$B$6+I50*Settings!$B$7+J50*Settings!$B$8+K50*Settings!$B$9+L50*Settings!$B$10 | N50: =M50-INDEX(Settings!$G$4:$G$9,MATCH($E50,Settings!$F$4:$F$9,0)) | O50: =N50*INDEX(Settings!$H$4:$H$9,MATCH($E50,Settings!$F$4:$F$9,0)) | P50: HIGH
A51: 255 | B51: RB49 | C51: Alvin Kamara | D51: NO | E51: RB | G51: 2 | H51: 1.4 | M51: =F51*Settings!$B$4+G51*Settings!$B$5+H51*Settings!$B$6+I51*Settings!$B$7+J51*Settings!$B$8+K51*Settings!$B$9+L51*Settings!$B$10 | N51: =M51-INDEX(Settings!$G$4:$G$9,MATCH($E51,Settings!$F$4:$F$9,0)) | O51: =N51*INDEX(Settings!$H$4:$H$9,MATCH($E51,Settings!$F$4:$F$9,0)) | P51: HIGH | Q51: Declining
A52: 256 | B52: RB50 | C52: Tyler Allgeier | D52: ARI | E52: RB | G52: 3.1 | H52: 0.2 | M52: =F52*Settings!$B$4+G52*Settings!$B$5+H52*Settings!$B$6+I52*Settings!$B$7+J52*Settings!$B$8+K52*Settings!$B$9+L52*Settings!$B$10 | N52: =M52-INDEX(Settings!$G$4:$G$9,MATCH($E52,Settings!$F$4:$F$9,0)) | O52: =N52*INDEX(Settings!$H$4:$H$9,MATCH($E52,Settings!$F$4:$F$9,0)) | P52: HIGH | Q52: Opened camp ahead of rookie Love
A53: 257 | B53: RB51 | C53: Tank Bigsby | D53: PHI | E53: RB | G53: 3.2 | H53: 0.1 | M53: =F53*Settings!$B$4+G53*Settings!$B$5+H53*Settings!$B$6+I53*Settings!$B$7+J53*Settings!$B$8+K53*Settings!$B$9+L53*Settings!$B$10 | N53: =M53-INDEX(Settings!$G$4:$G$9,MATCH($E53,Settings!$F$4:$F$9,0)) | O53: =N53*INDEX(Settings!$H$4:$H$9,MATCH($E53,Settings!$F$4:$F$9,0)) | P53: HIGH
A54: 258 | B54: RB52 | C54: Ty Johnson | D54: BUF | E54: RB | G54: 1.6 | H54: 1.6 | M54: =F54*Settings!$B$4+G54*Settings!$B$5+H54*Settings!$B$6+I54*Settings!$B$7+J54*Settings!$B$8+K54*Settings!$B$9+L54*Settings!$B$10 | N54: =M54-INDEX(Settings!$G$4:$G$9,MATCH($E54,Settings!$F$4:$F$9,0)) | O54: =N54*INDEX(Settings!$H$4:$H$9,MATCH($E54,Settings!$F$4:$F$9,0)) | P54: HIGH
A55: 259 | B55: RB53 | C55: MarShawn Lloyd | D55: GB | E55: RB | G55: 2.9 | H55: 0.3 | M55: =F55*Settings!$B$4+G55*Settings!$B$5+H55*Settings!$B$6+I55*Settings!$B$7+J55*Settings!$B$8+K55*Settings!$B$9+L55*Settings!$B$10 | N55: =M55-INDEX(Settings!$G$4:$G$9,MATCH($E55,Settings!$F$4:$F$9,0)) | O55: =N55*INDEX(Settings!$H$4:$H$9,MATCH($E55,Settings!$F$4:$F$9,0)) | P55: HIGH
A56: 260 | B56: RB54 | C56: Braelon Allen | D56: NYJ | E56: RB | G56: 3 | H56: 0.2 | M56: =F56*Settings!$B$4+G56*Settings!$B$5+H56*Settings!$B$6+I56*Settings!$B$7+J56*Settings!$B$8+K56*Settings!$B$9+L56*Settings!$B$10 | N56: =M56-INDEX(Settings!$G$4:$G$9,MATCH($E56,Settings!$F$4:$F$9,0)) | O56: =N56*INDEX(Settings!$H$4:$H$9,MATCH($E56,Settings!$F$4:$F$9,0)) | P56: HIGH
A57: 261 | B57: RB55 | C57: Keaton Mitchell | D57: LAC | E57: RB | G57: 2.2 | H57: 0.9 | M57: =F57*Settings!$B$4+G57*Settings!$B$5+H57*Settings!$B$6+I57*Settings!$B$7+J57*Settings!$B$8+K57*Settings!$B$9+L57*Settings!$B$10 | N57: =M57-INDEX(Settings!$G$4:$G$9,MATCH($E57,Settings!$F$4:$F$9,0)) | O57: =N57*INDEX(Settings!$H$4:$H$9,MATCH($E57,Settings!$F$4:$F$9,0)) | P57: HIGH
A58: 262 | B58: RB56 | C58: Justice Hill | D58: BAL | E58: RB | G58: 1.7 | H58: 1.4 | M58: =F58*Settings!$B$4+G58*Settings!$B$5+H58*Settings!$B$6+I58*Settings!$B$7+J58*Settings!$B$8+K58*Settings!$B$9+L58*Settings!$B$10 | N58: =M58-INDEX(Settings!$G$4:$G$9,MATCH($E58,Settings!$F$4:$F$9,0)) | O58: =N58*INDEX(Settings!$H$4:$H$9,MATCH($E58,Settings!$F$4:$F$9,0)) | P58: HIGH
A59: 263 | B59: RB57 | C59: Sean Tucker | D59: TB | E59: RB | G59: 2.7 | H59: 0.1 | M59: =F59*Settings!$B$4+G59*Settings!$B$5+H59*Settings!$B$6+I59*Settings!$B$7+J59*Settings!$B$8+K59*Settings!$B$9+L59*Settings!$B$10 | N59: =M59-INDEX(Settings!$G$4:$G$9,MATCH($E59,Settings!$F$4:$F$9,0)) | O59: =N59*INDEX(Settings!$H$4:$H$9,MATCH($E59,Settings!$F$4:$F$9,0)) | P59: LOW | Q59: BIGGEST SLEEPER: owns TB goal line; scored 8 TD in 2025 6 in final 8 games; projection is a volume artifact
A60: 264 | B60: RB58 | C60: Dylan Sampson | D60: CLE | E60: RB | G60: 1.1 | H60: 1.6 | M60: =F60*Settings!$B$4+G60*Settings!$B$5+H60*Settings!$B$6+I60*Settings!$B$7+J60*Settings!$B$8+K60*Settings!$B$9+L60*Settings!$B$10 | N60: =M60-INDEX(Settings!$G$4:$G$9,MATCH($E60,Settings!$F$4:$F$9,0)) | O60: =N60*INDEX(Settings!$H$4:$H$9,MATCH($E60,Settings!$F$4:$F$9,0)) | P60: HIGH
A61: 266 | B61: RB59 | C61: Jonah Coleman | D61: DEN | E61: RB | G61: 2 | H61: 0.4 | M61: =F61*Settings!$B$4+G61*Settings!$B$5+H61*Settings!$B$6+I61*Settings!$B$7+J61*Settings!$B$8+K61*Settings!$B$9+L61*Settings!$B$10 | N61: =M61-INDEX(Settings!$G$4:$G$9,MATCH($E61,Settings!$F$4:$F$9,0)) | O61: =N61*INDEX(Settings!$H$4:$H$9,MATCH($E61,Settings!$F$4:$F$9,0)) | P61: HIGH | Q61: Rookie GL insurance
A62: 268 | B62: RB60 | C62: Ray Davis | D62: BUF | E62: RB | G62: 1.6 | H62: 0.7 | M62: =F62*Settings!$B$4+G62*Settings!$B$5+H62*Settings!$B$6+I62*Settings!$B$7+J62*Settings!$B$8+K62*Settings!$B$9+L62*Settings!$B$10 | N62: =M62-INDEX(Settings!$G$4:$G$9,MATCH($E62,Settings!$F$4:$F$9,0)) | O62: =N62*INDEX(Settings!$H$4:$H$9,MATCH($E62,Settings!$F$4:$F$9,0)) | P62: HIGH
A63: 269 | B63: RB61 | C63: Najee Harris | D63: NYG | E63: RB | G63: 2.1 | H63: 0.2 | M63: =F63*Settings!$B$4+G63*Settings!$B$5+H63*Settings!$B$6+I63*Settings!$B$7+J63*Settings!$B$8+K63*Settings!$B$9+L63*Settings!$B$10 | N63: =M63-INDEX(Settings!$G$4:$G$9,MATCH($E63,Settings!$F$4:$F$9,0)) | O63: =N63*INDEX(Settings!$H$4:$H$9,MATCH($E63,Settings!$F$4:$F$9,0)) | P63: HIGH | Q63: Signed to NYG
A64: 270 | B64: RB62 | C64: Mike Washington Jr. | D64: LV | E64: RB | G64: 2.1 | H64: 0.1 | M64: =F64*Settings!$B$4+G64*Settings!$B$5+H64*Settings!$B$6+I64*Settings!$B$7+J64*Settings!$B$8+K64*Settings!$B$9+L64*Settings!$B$10 | N64: =M64-INDEX(Settings!$G$4:$G$9,MATCH($E64,Settings!$F$4:$F$9,0)) | O64: =N64*INDEX(Settings!$H$4:$H$9,MATCH($E64,Settings!$F$4:$F$9,0)) | P64: HIGH | Q64: Rookie backup to Jeanty
A65: 272 | B65: RB63 | C65: George Holani | D65: SEA | E65: RB | G65: 1.8 | H65: 0.1 | M65: =F65*Settings!$B$4+G65*Settings!$B$5+H65*Settings!$B$6+I65*Settings!$B$7+J65*Settings!$B$8+K65*Settings!$B$9+L65*Settings!$B$10 | N65: =M65-INDEX(Settings!$G$4:$G$9,MATCH($E65,Settings!$F$4:$F$9,0)) | O65: =N65*INDEX(Settings!$H$4:$H$9,MATCH($E65,Settings!$F$4:$F$9,0)) | P65: HIGH
A66: 273 | B66: RB64 | C66: Tyrone Tracy Jr. | D66: NYG | E66: RB | G66: 1.2 | H66: 0.7 | M66: =F66*Settings!$B$4+G66*Settings!$B$5+H66*Settings!$B$6+I66*Settings!$B$7+J66*Settings!$B$8+K66*Settings!$B$9+L66*Settings!$B$10 | N66: =M66-INDEX(Settings!$G$4:$G$9,MATCH($E66,Settings!$F$4:$F$9,0)) | O66: =N66*INDEX(Settings!$H$4:$H$9,MATCH($E66,Settings!$F$4:$F$9,0)) | P66: HIGH
A67: 274 | B67: RB65 | C67: Kaelon Black | D67: SF | E67: RB | G67: 1.6 | H67: 0.2 | M67: =F67*Settings!$B$4+G67*Settings!$B$5+H67*Settings!$B$6+I67*Settings!$B$7+J67*Settings!$B$8+K67*Settings!$B$9+L67*Settings!$B$10 | N67: =M67-INDEX(Settings!$G$4:$G$9,MATCH($E67,Settings!$F$4:$F$9,0)) | O67: =N67*INDEX(Settings!$H$4:$H$9,MATCH($E67,Settings!$F$4:$F$9,0)) | P67: HIGH | Q67: Rookie
A68: 275 | B68: RB66 | C68: Kimani Vidal | D68: LAC | E68: RB | G68: 1.6 | H68: 0.2 | M68: =F68*Settings!$B$4+G68*Settings!$B$5+H68*Settings!$B$6+I68*Settings!$B$7+J68*Settings!$B$8+K68*Settings!$B$9+L68*Settings!$B$10 | N68: =M68-INDEX(Settings!$G$4:$G$9,MATCH($E68,Settings!$F$4:$F$9,0)) | O68: =N68*INDEX(Settings!$H$4:$H$9,MATCH($E68,Settings!$F$4:$F$9,0)) | P68: HIGH
A69: 276 | B69: RB67 | C69: Jaydon Blue | D69: DAL | E69: RB | G69: 1.5 | H69: 0.2 | M69: =F69*Settings!$B$4+G69*Settings!$B$5+H69*Settings!$B$6+I69*Settings!$B$7+J69*Settings!$B$8+K69*Settings!$B$9+L69*Settings!$B$10 | N69: =M69-INDEX(Settings!$G$4:$G$9,MATCH($E69,Settings!$F$4:$F$9,0)) | O69: =N69*INDEX(Settings!$H$4:$H$9,MATCH($E69,Settings!$F$4:$F$9,0)) | P69: HIGH
A70: 277 | B70: RB68 | C70: Jaylen Wright | D70: MIA | E70: RB | G70: 1.6 | H70: 0.1 | M70: =F70*Settings!$B$4+G70*Settings!$B$5+H70*Settings!$B$6+I70*Settings!$B$7+J70*Settings!$B$8+K70*Settings!$B$9+L70*Settings!$B$10 | N70: =M70-INDEX(Settings!$G$4:$G$9,MATCH($E70,Settings!$F$4:$F$9,0)) | O70: =N70*INDEX(Settings!$H$4:$H$9,MATCH($E70,Settings!$F$4:$F$9,0)) | P70: HIGH
A71: 278 | B71: RB69 | C71: Emmett Johnson | D71: KC | E71: RB | G71: 1.3 | H71: 0.2 | M71: =F71*Settings!$B$4+G71*Settings!$B$5+H71*Settings!$B$6+I71*Settings!$B$7+J71*Settings!$B$8+K71*Settings!$B$9+L71*Settings!$B$10 | N71: =M71-INDEX(Settings!$G$4:$G$9,MATCH($E71,Settings!$F$4:$F$9,0)) | O71: =N71*INDEX(Settings!$H$4:$H$9,MATCH($E71,Settings!$F$4:$F$9,0)) | P71: HIGH | Q71: Rookie
A72: 279 | B72: RB70 | C72: Emari Demercado | D72: KC | E72: RB | G72: 1.2 | H72: 0.3 | M72: =F72*Settings!$B$4+G72*Settings!$B$5+H72*Settings!$B$6+I72*Settings!$B$7+J72*Settings!$B$8+K72*Settings!$B$9+L72*Settings!$B$10 | N72: =M72-INDEX(Settings!$G$4:$G$9,MATCH($E72,Settings!$F$4:$F$9,0)) | O72: =N72*INDEX(Settings!$H$4:$H$9,MATCH($E72,Settings!$F$4:$F$9,0)) | P72: HIGH

Sheet WR
A1: WR — ranked by projected points
A2: Rank | B2: Pos | C2: Player | D2: Tm | E2: P | F2: PassTD | G2: RushTD | H2: RecTD | I2: FG | J2: PAT | K2: DefTD | L2: Saf | M2: Points | N2: VOR | O2: Adj VOR | P2: Conf | Q2: Notes
A3: 9 | B3: WR1 | C3: Ja'Marr Chase | D3: CIN | E3: WR | G3: 0.1 | H3: 10.9 | M3: =F3*Settings!$B$4+G3*Settings!$B$5+H3*Settings!$B$6+I3*Settings!$B$7+J3*Settings!$B$8+K3*Settings!$B$9+L3*Settings!$B$10 | N3: =M3-INDEX(Settings!$G$4:$G$9,MATCH($E3,Settings!$F$4:$F$9,0)) | O3: =N3*INDEX(Settings!$H$4:$H$9,MATCH($E3,Settings!$F$4:$F$9,0)) | P3: HIGH
A4: 13 | B4: WR2 | C4: Davante Adams | D4: LAR | E4: WR | H4: 10.3 | M4: =F4*Settings!$B$4+G4*Settings!$B$5+H4*Settings!$B$6+I4*Settings!$B$7+J4*Settings!$B$8+K4*Settings!$B$9+L4*Settings!$B$10 | N4: =M4-INDEX(Settings!$G$4:$G$9,MATCH($E4,Settings!$F$4:$F$9,0)) | O4: =N4*INDEX(Settings!$H$4:$H$9,MATCH($E4,Settings!$F$4:$F$9,0)) | P4: HIGH
A5: 14 | B5: WR3 | C5: Amon-Ra St. Brown | D5: DET | E5: WR | G5: 0.1 | H5: 10.2 | M5: =F5*Settings!$B$4+G5*Settings!$B$5+H5*Settings!$B$6+I5*Settings!$B$7+J5*Settings!$B$8+K5*Settings!$B$9+L5*Settings!$B$10 | N5: =M5-INDEX(Settings!$G$4:$G$9,MATCH($E5,Settings!$F$4:$F$9,0)) | O5: =N5*INDEX(Settings!$H$4:$H$9,MATCH($E5,Settings!$F$4:$F$9,0)) | P5: HIGH
A6: 15 | B6: WR4 | C6: Puka Nacua | D6: LAR | E6: WR | G6: 0.6 | H6: 9.3 | M6: =F6*Settings!$B$4+G6*Settings!$B$5+H6*Settings!$B$6+I6*Settings!$B$7+J6*Settings!$B$8+K6*Settings!$B$9+L6*Settings!$B$10 | N6: =M6-INDEX(Settings!$G$4:$G$9,MATCH($E6,Settings!$F$4:$F$9,0)) | O6: =N6*INDEX(Settings!$H$4:$H$9,MATCH($E6,Settings!$F$4:$F$9,0)) | P6: HIGH
A7: 26 | B7: WR5 | C7: CeeDee Lamb | D7: DAL | E7: WR | G7: 0.1 | H7: 8.3 | M7: =F7*Settings!$B$4+G7*Settings!$B$5+H7*Settings!$B$6+I7*Settings!$B$7+J7*Settings!$B$8+K7*Settings!$B$9+L7*Settings!$B$10 | N7: =M7-INDEX(Settings!$G$4:$G$9,MATCH($E7,Settings!$F$4:$F$9,0)) | O7: =N7*INDEX(Settings!$H$4:$H$9,MATCH($E7,Settings!$F$4:$F$9,0)) | P7: HIGH
A8: 28 | B8: WR6 | C8: Jaxon Smith-Njigba | D8: SEA | E8: WR | G8: 0.1 | H8: 8.2 | M8: =F8*Settings!$B$4+G8*Settings!$B$5+H8*Settings!$B$6+I8*Settings!$B$7+J8*Settings!$B$8+K8*Settings!$B$9+L8*Settings!$B$10 | N8: =M8-INDEX(Settings!$G$4:$G$9,MATCH($E8,Settings!$F$4:$F$9,0)) | O8: =N8*INDEX(Settings!$H$4:$H$9,MATCH($E8,Settings!$F$4:$F$9,0)) | P8: HIGH
A9: 30 | B9: WR7 | C9: Rashee Rice | D9: KC | E9: WR | G9: 0.3 | H9: 7.9 | M9: =F9*Settings!$B$4+G9*Settings!$B$5+H9*Settings!$B$6+I9*Settings!$B$7+J9*Settings!$B$8+K9*Settings!$B$9+L9*Settings!$B$10 | N9: =M9-INDEX(Settings!$G$4:$G$9,MATCH($E9,Settings!$F$4:$F$9,0)) | O9: =N9*INDEX(Settings!$H$4:$H$9,MATCH($E9,Settings!$F$4:$F$9,0)) | P9: HIGH
A10: 31 | B10: WR8 | C10: Tee Higgins | D10: CIN | E10: WR | H10: 8.2 | M10: =F10*Settings!$B$4+G10*Settings!$B$5+H10*Settings!$B$6+I10*Settings!$B$7+J10*Settings!$B$8+K10*Settings!$B$9+L10*Settings!$B$10 | N10: =M10-INDEX(Settings!$G$4:$G$9,MATCH($E10,Settings!$F$4:$F$9,0)) | O10: =N10*INDEX(Settings!$H$4:$H$9,MATCH($E10,Settings!$F$4:$F$9,0)) | P10: HIGH
A11: 36 | B11: WR9 | C11: Rome Odunze | D11: CHI | E11: WR | H11: 7.7 | M11: =F11*Settings!$B$4+G11*Settings!$B$5+H11*Settings!$B$6+I11*Settings!$B$7+J11*Settings!$B$8+K11*Settings!$B$9+L11*Settings!$B$10 | N11: =M11-INDEX(Settings!$G$4:$G$9,MATCH($E11,Settings!$F$4:$F$9,0)) | O11: =N11*INDEX(Settings!$H$4:$H$9,MATCH($E11,Settings!$F$4:$F$9,0)) | P11: HIGH
A12: 39 | B12: WR10 | C12: George Pickens | D12: DAL | E12: WR | H12: 7.6 | M12: =F12*Settings!$B$4+G12*Settings!$B$5+H12*Settings!$B$6+I12*Settings!$B$7+J12*Settings!$B$8+K12*Settings!$B$9+L12*Settings!$B$10 | N12: =M12-INDEX(Settings!$G$4:$G$9,MATCH($E12,Settings!$F$4:$F$9,0)) | O12: =N12*INDEX(Settings!$H$4:$H$9,MATCH($E12,Settings!$F$4:$F$9,0)) | P12: HIGH
A13: 47 | B13: WR11 | C13: Malik Nabers | D13: NYG | E13: WR | G13: 0.1 | H13: 7.2 | M13: =F13*Settings!$B$4+G13*Settings!$B$5+H13*Settings!$B$6+I13*Settings!$B$7+J13*Settings!$B$8+K13*Settings!$B$9+L13*Settings!$B$10 | N13: =M13-INDEX(Settings!$G$4:$G$9,MATCH($E13,Settings!$F$4:$F$9,0)) | O13: =N13*INDEX(Settings!$H$4:$H$9,MATCH($E13,Settings!$F$4:$F$9,0)) | P13: HIGH
A14: 48 | B14: WR12 | C14: Emeka Egbuka | D14: TB | E14: WR | G14: 0.1 | H14: 7.2 | M14: =F14*Settings!$B$4+G14*Settings!$B$5+H14*Settings!$B$6+I14*Settings!$B$7+J14*Settings!$B$8+K14*Settings!$B$9+L14*Settings!$B$10 | N14: =M14-INDEX(Settings!$G$4:$G$9,MATCH($E14,Settings!$F$4:$F$9,0)) | O14: =N14*INDEX(Settings!$H$4:$H$9,MATCH($E14,Settings!$F$4:$F$9,0)) | P14: HIGH
A15: 49 | B15: WR13 | C15: Courtland Sutton | D15: DEN | E15: WR | H15: 7.3 | M15: =F15*Settings!$B$4+G15*Settings!$B$5+H15*Settings!$B$6+I15*Settings!$B$7+J15*Settings!$B$8+K15*Settings!$B$9+L15*Settings!$B$10 | N15: =M15-INDEX(Settings!$G$4:$G$9,MATCH($E15,Settings!$F$4:$F$9,0)) | O15: =N15*INDEX(Settings!$H$4:$H$9,MATCH($E15,Settings!$F$4:$F$9,0)) | P15: HIGH
A16: 50 | B16: WR14 | C16: Justin Jefferson | D16: MIN | E16: WR | G16: 0.1 | H16: 7.2 | M16: =F16*Settings!$B$4+G16*Settings!$B$5+H16*Settings!$B$6+I16*Settings!$B$7+J16*Settings!$B$8+K16*Settings!$B$9+L16*Settings!$B$10 | N16: =M16-INDEX(Settings!$G$4:$G$9,MATCH($E16,Settings!$F$4:$F$9,0)) | O16: =N16*INDEX(Settings!$H$4:$H$9,MATCH($E16,Settings!$F$4:$F$9,0)) | P16: HIGH
A17: 55 | B17: WR15 | C17: Drake London | D17: ATL | E17: WR | H17: 7.2 | M17: =F17*Settings!$B$4+G17*Settings!$B$5+H17*Settings!$B$6+I17*Settings!$B$7+J17*Settings!$B$8+K17*Settings!$B$9+L17*Settings!$B$10 | N17: =M17-INDEX(Settings!$G$4:$G$9,MATCH($E17,Settings!$F$4:$F$9,0)) | O17: =N17*INDEX(Settings!$H$4:$H$9,MATCH($E17,Settings!$F$4:$F$9,0)) | P17: HIGH
A18: 57 | B18: WR16 | C18: Christian Watson | D18: GB | E18: WR | G18: 0.1 | H18: 7 | M18: =F18*Settings!$B$4+G18*Settings!$B$5+H18*Settings!$B$6+I18*Settings!$B$7+J18*Settings!$B$8+K18*Settings!$B$9+L18*Settings!$B$10 | N18: =M18-INDEX(Settings!$G$4:$G$9,MATCH($E18,Settings!$F$4:$F$9,0)) | O18: =N18*INDEX(Settings!$H$4:$H$9,MATCH($E18,Settings!$F$4:$F$9,0)) | P18: HIGH
A19: 68 | B19: WR17 | C19: A.J. Brown | D19: NE | E19: WR | H19: 7 | M19: =F19*Settings!$B$4+G19*Settings!$B$5+H19*Settings!$B$6+I19*Settings!$B$7+J19*Settings!$B$8+K19*Settings!$B$9+L19*Settings!$B$10 | N19: =M19-INDEX(Settings!$G$4:$G$9,MATCH($E19,Settings!$F$4:$F$9,0)) | O19: =N19*INDEX(Settings!$H$4:$H$9,MATCH($E19,Settings!$F$4:$F$9,0)) | P19: HIGH
A20: 73 | B20: WR18 | C20: Nico Collins | D20: HOU | E20: WR | G20: 0.1 | H20: 6.8 | M20: =F20*Settings!$B$4+G20*Settings!$B$5+H20*Settings!$B$6+I20*Settings!$B$7+J20*Settings!$B$8+K20*Settings!$B$9+L20*Settings!$B$10 | N20: =M20-INDEX(Settings!$G$4:$G$9,MATCH($E20,Settings!$F$4:$F$9,0)) | O20: =N20*INDEX(Settings!$H$4:$H$9,MATCH($E20,Settings!$F$4:$F$9,0)) | P20: HIGH
A21: 74 | B21: WR19 | C21: Chris Olave | D21: NO | E21: WR | H21: 6.8 | M21: =F21*Settings!$B$4+G21*Settings!$B$5+H21*Settings!$B$6+I21*Settings!$B$7+J21*Settings!$B$8+K21*Settings!$B$9+L21*Settings!$B$10 | N21: =M21-INDEX(Settings!$G$4:$G$9,MATCH($E21,Settings!$F$4:$F$9,0)) | O21: =N21*INDEX(Settings!$H$4:$H$9,MATCH($E21,Settings!$F$4:$F$9,0)) | P21: HIGH
A22: 76 | B22: WR20 | C22: D.J. Moore | D22: BUF | E22: WR | G22: 0.2 | H22: 6.5 | M22: =F22*Settings!$B$4+G22*Settings!$B$5+H22*Settings!$B$6+I22*Settings!$B$7+J22*Settings!$B$8+K22*Settings!$B$9+L22*Settings!$B$10 | N22: =M22-INDEX(Settings!$G$4:$G$9,MATCH($E22,Settings!$F$4:$F$9,0)) | O22: =N22*INDEX(Settings!$H$4:$H$9,MATCH($E22,Settings!$F$4:$F$9,0)) | P22: HIGH
A23: 78 | B23: WR21 | C23: Jameson Williams | D23: DET | E23: WR | G23: 0.3 | H23: 6.3 | M23: =F23*Settings!$B$4+G23*Settings!$B$5+H23*Settings!$B$6+I23*Settings!$B$7+J23*Settings!$B$8+K23*Settings!$B$9+L23*Settings!$B$10 | N23: =M23-INDEX(Settings!$G$4:$G$9,MATCH($E23,Settings!$F$4:$F$9,0)) | O23: =N23*INDEX(Settings!$H$4:$H$9,MATCH($E23,Settings!$F$4:$F$9,0)) | P23: HIGH
A24: 86 | B24: WR22 | C24: Mike Evans | D24: SF | E24: WR | H24: 6.4 | M24: =F24*Settings!$B$4+G24*Settings!$B$5+H24*Settings!$B$6+I24*Settings!$B$7+J24*Settings!$B$8+K24*Settings!$B$9+L24*Settings!$B$10 | N24: =M24-INDEX(Settings!$G$4:$G$9,MATCH($E24,Settings!$F$4:$F$9,0)) | O24: =N24*INDEX(Settings!$H$4:$H$9,MATCH($E24,Settings!$F$4:$F$9,0)) | P24: HIGH
A25: 93 | B25: WR23 | C25: Ladd McConkey | D25: LAC | E25: WR | H25: 6.2 | M25: =F25*Settings!$B$4+G25*Settings!$B$5+H25*Settings!$B$6+I25*Settings!$B$7+J25*Settings!$B$8+K25*Settings!$B$9+L25*Settings!$B$10 | N25: =M25-INDEX(Settings!$G$4:$G$9,MATCH($E25,Settings!$F$4:$F$9,0)) | O25: =N25*INDEX(Settings!$H$4:$H$9,MATCH($E25,Settings!$F$4:$F$9,0)) | P25: HIGH
A26: 102 | B26: WR24 | C26: DK Metcalf | D26: PIT | E26: WR | H26: 6.1 | M26: =F26*Settings!$B$4+G26*Settings!$B$5+H26*Settings!$B$6+I26*Settings!$B$7+J26*Settings!$B$8+K26*Settings!$B$9+L26*Settings!$B$10 | N26: =M26-INDEX(Settings!$G$4:$G$9,MATCH($E26,Settings!$F$4:$F$9,0)) | O26: =N26*INDEX(Settings!$H$4:$H$9,MATCH($E26,Settings!$F$4:$F$9,0)) | P26: HIGH
A27: 103 | B27: WR25 | C27: Jaylen Waddle | D27: DEN | E27: WR | G27: 0.1 | H27: 6 | M27: =F27*Settings!$B$4+G27*Settings!$B$5+H27*Settings!$B$6+I27*Settings!$B$7+J27*Settings!$B$8+K27*Settings!$B$9+L27*Settings!$B$10 | N27: =M27-INDEX(Settings!$G$4:$G$9,MATCH($E27,Settings!$F$4:$F$9,0)) | O27: =N27*INDEX(Settings!$H$4:$H$9,MATCH($E27,Settings!$F$4:$F$9,0)) | P27: HIGH
A28: 114 | B28: WR26 | C28: DeVonta Smith | D28: PHI | E28: WR | H28: 6 | M28: =F28*Settings!$B$4+G28*Settings!$B$5+H28*Settings!$B$6+I28*Settings!$B$7+J28*Settings!$B$8+K28*Settings!$B$9+L28*Settings!$B$10 | N28: =M28-INDEX(Settings!$G$4:$G$9,MATCH($E28,Settings!$F$4:$F$9,0)) | O28: =N28*INDEX(Settings!$H$4:$H$9,MATCH($E28,Settings!$F$4:$F$9,0)) | P28: HIGH
A29: 115 | B29: WR27 | C29: Tetairoa McMillan | D29: CAR | E29: WR | H29: 6 | M29: =F29*Settings!$B$4+G29*Settings!$B$5+H29*Settings!$B$6+I29*Settings!$B$7+J29*Settings!$B$8+K29*Settings!$B$9+L29*Settings!$B$10 | N29: =M29-INDEX(Settings!$G$4:$G$9,MATCH($E29,Settings!$F$4:$F$9,0)) | O29: =N29*INDEX(Settings!$H$4:$H$9,MATCH($E29,Settings!$F$4:$F$9,0)) | P29: HIGH
A30: 116 | B30: WR28 | C30: Terry McLaurin | D30: WAS | E30: WR | H30: 6 | M30: =F30*Settings!$B$4+G30*Settings!$B$5+H30*Settings!$B$6+I30*Settings!$B$7+J30*Settings!$B$8+K30*Settings!$B$9+L30*Settings!$B$10 | N30: =M30-INDEX(Settings!$G$4:$G$9,MATCH($E30,Settings!$F$4:$F$9,0)) | O30: =N30*INDEX(Settings!$H$4:$H$9,MATCH($E30,Settings!$F$4:$F$9,0)) | P30: HIGH
A31: 117 | B31: WR29 | C31: Zay Flowers | D31: BAL | E31: WR | G31: 0.2 | H31: 5.8 | M31: =F31*Settings!$B$4+G31*Settings!$B$5+H31*Settings!$B$6+I31*Settings!$B$7+J31*Settings!$B$8+K31*Settings!$B$9+L31*Settings!$B$10 | N31: =M31-INDEX(Settings!$G$4:$G$9,MATCH($E31,Settings!$F$4:$F$9,0)) | O31: =N31*INDEX(Settings!$H$4:$H$9,MATCH($E31,Settings!$F$4:$F$9,0)) | P31: HIGH
A32: 128 | B32: WR30 | C32: Quentin Johnston | D32: LAC | E32: WR | G32: 0.1 | H32: 5.8 | M32: =F32*Settings!$B$4+G32*Settings!$B$5+H32*Settings!$B$6+I32*Settings!$B$7+J32*Settings!$B$8+K32*Settings!$B$9+L32*Settings!$B$10 | N32: =M32-INDEX(Settings!$G$4:$G$9,MATCH($E32,Settings!$F$4:$F$9,0)) | O32: =N32*INDEX(Settings!$H$4:$H$9,MATCH($E32,Settings!$F$4:$F$9,0)) | P32: HIGH
A33: 145 | B33: WR31 | C33: Luther Burden III | D33: CHI | E33: WR | G33: 0.2 | H33: 5.5 | M33: =F33*Settings!$B$4+G33*Settings!$B$5+H33*Settings!$B$6+I33*Settings!$B$7+J33*Settings!$B$8+K33*Settings!$B$9+L33*Settings!$B$10 | N33: =M33-INDEX(Settings!$G$4:$G$9,MATCH($E33,Settings!$F$4:$F$9,0)) | O33: =N33*INDEX(Settings!$H$4:$H$9,MATCH($E33,Settings!$F$4:$F$9,0)) | P33: HIGH
A34: 149 | B34: WR32 | C34: Marvin Harrison Jr. | D34: ARI | E34: WR | H34: 5.5 | M34: =F34*Settings!$B$4+G34*Settings!$B$5+H34*Settings!$B$6+I34*Settings!$B$7+J34*Settings!$B$8+K34*Settings!$B$9+L34*Settings!$B$10 | N34: =M34-INDEX(Settings!$G$4:$G$9,MATCH($E34,Settings!$F$4:$F$9,0)) | O34: =N34*INDEX(Settings!$H$4:$H$9,MATCH($E34,Settings!$F$4:$F$9,0)) | P34: HIGH
A35: 156 | B35: WR33 | C35: Romeo Doubs | D35: NE | E35: WR | H35: 5.2 | M35: =F35*Settings!$B$4+G35*Settings!$B$5+H35*Settings!$B$6+I35*Settings!$B$7+J35*Settings!$B$8+K35*Settings!$B$9+L35*Settings!$B$10 | N35: =M35-INDEX(Settings!$G$4:$G$9,MATCH($E35,Settings!$F$4:$F$9,0)) | O35: =N35*INDEX(Settings!$H$4:$H$9,MATCH($E35,Settings!$F$4:$F$9,0)) | P35: HIGH
A36: 157 | B36: WR34 | C36: Alec Pierce | D36: IND | E36: WR | H36: 5.2 | M36: =F36*Settings!$B$4+G36*Settings!$B$5+H36*Settings!$B$6+I36*Settings!$B$7+J36*Settings!$B$8+K36*Settings!$B$9+L36*Settings!$B$10 | N36: =M36-INDEX(Settings!$G$4:$G$9,MATCH($E36,Settings!$F$4:$F$9,0)) | O36: =N36*INDEX(Settings!$H$4:$H$9,MATCH($E36,Settings!$F$4:$F$9,0)) | P36: HIGH
A37: 158 | B37: WR35 | C37: Jakobi Meyers | D37: JAX | E37: WR | G37: 0.1 | H37: 5.1 | M37: =F37*Settings!$B$4+G37*Settings!$B$5+H37*Settings!$B$6+I37*Settings!$B$7+J37*Settings!$B$8+K37*Settings!$B$9+L37*Settings!$B$10 | N37: =M37-INDEX(Settings!$G$4:$G$9,MATCH($E37,Settings!$F$4:$F$9,0)) | O37: =N37*INDEX(Settings!$H$4:$H$9,MATCH($E37,Settings!$F$4:$F$9,0)) | P37: HIGH
A38: 159 | B38: WR36 | C38: Jordan Addison | D38: MIN | E38: WR | G38: 0.1 | H38: 5.1 | M38: =F38*Settings!$B$4+G38*Settings!$B$5+H38*Settings!$B$6+I38*Settings!$B$7+J38*Settings!$B$8+K38*Settings!$B$9+L38*Settings!$B$10 | N38: =M38-INDEX(Settings!$G$4:$G$9,MATCH($E38,Settings!$F$4:$F$9,0)) | O38: =N38*INDEX(Settings!$H$4:$H$9,MATCH($E38,Settings!$F$4:$F$9,0)) | P38: HIGH
A39: 160 | B39: WR37 | C39: Garrett Wilson | D39: NYJ | E39: WR | G39: 0.1 | H39: 5.1 | M39: =F39*Settings!$B$4+G39*Settings!$B$5+H39*Settings!$B$6+I39*Settings!$B$7+J39*Settings!$B$8+K39*Settings!$B$9+L39*Settings!$B$10 | N39: =M39-INDEX(Settings!$G$4:$G$9,MATCH($E39,Settings!$F$4:$F$9,0)) | O39: =N39*INDEX(Settings!$H$4:$H$9,MATCH($E39,Settings!$F$4:$F$9,0)) | P39: HIGH
A40: 161 | B40: WR38 | C40: Parker Washington | D40: JAX | E40: WR | G40: 0.1 | H40: 5.1 | M40: =F40*Settings!$B$4+G40*Settings!$B$5+H40*Settings!$B$6+I40*Settings!$B$7+J40*Settings!$B$8+K40*Settings!$B$9+L40*Settings!$B$10 | N40: =M40-INDEX(Settings!$G$4:$G$9,MATCH($E40,Settings!$F$4:$F$9,0)) | O40: =N40*INDEX(Settings!$H$4:$H$9,MATCH($E40,Settings!$F$4:$F$9,0)) | P40: HIGH
A41: 163 | B41: WR39 | C41: Brian Thomas Jr. | D41: JAX | E41: WR | G41: 0.1 | H41: 5 | M41: =F41*Settings!$B$4+G41*Settings!$B$5+H41*Settings!$B$6+I41*Settings!$B$7+J41*Settings!$B$8+K41*Settings!$B$9+L41*Settings!$B$10 | N41: =M41-INDEX(Settings!$G$4:$G$9,MATCH($E41,Settings!$F$4:$F$9,0)) | O41: =N41*INDEX(Settings!$H$4:$H$9,MATCH($E41,Settings!$F$4:$F$9,0)) | P41: HIGH
A42: 167 | B42: WR40 | C42: Jayden Reed | D42: GB | E42: WR | G42: 0.2 | H42: 4.7 | M42: =F42*Settings!$B$4+G42*Settings!$B$5+H42*Settings!$B$6+I42*Settings!$B$7+J42*Settings!$B$8+K42*Settings!$B$9+L42*Settings!$B$10 | N42: =M42-INDEX(Settings!$G$4:$G$9,MATCH($E42,Settings!$F$4:$F$9,0)) | O42: =N42*INDEX(Settings!$H$4:$H$9,MATCH($E42,Settings!$F$4:$F$9,0)) | P42: HIGH
A43: 168 | B43: WR41 | C43: Matthew Golden | D43: GB | E43: WR | G43: 0.1 | H43: 4.8 | M43: =F43*Settings!$B$4+G43*Settings!$B$5+H43*Settings!$B$6+I43*Settings!$B$7+J43*Settings!$B$8+K43*Settings!$B$9+L43*Settings!$B$10 | N43: =M43-INDEX(Settings!$G$4:$G$9,MATCH($E43,Settings!$F$4:$F$9,0)) | O43: =N43*INDEX(Settings!$H$4:$H$9,MATCH($E43,Settings!$F$4:$F$9,0)) | P43: HIGH
A44: 174 | B44: WR42 | C44: Deebo Samuel Sr. | D44: SF | E44: WR | G44: 1.1 | H44: 3.7 | M44: =F44*Settings!$B$4+G44*Settings!$B$5+H44*Settings!$B$6+I44*Settings!$B$7+J44*Settings!$B$8+K44*Settings!$B$9+L44*Settings!$B$10 | N44: =M44-INDEX(Settings!$G$4:$G$9,MATCH($E44,Settings!$F$4:$F$9,0)) | O44: =N44*INDEX(Settings!$H$4:$H$9,MATCH($E44,Settings!$F$4:$F$9,0)) | P44: LOW
A45: 175 | B45: WR43 | C45: Carnell Tate | D45: TEN | E45: WR | H45: 4.8 | M45: =F45*Settings!$B$4+G45*Settings!$B$5+H45*Settings!$B$6+I45*Settings!$B$7+J45*Settings!$B$8+K45*Settings!$B$9+L45*Settings!$B$10 | N45: =M45-INDEX(Settings!$G$4:$G$9,MATCH($E45,Settings!$F$4:$F$9,0)) | O45: =N45*INDEX(Settings!$H$4:$H$9,MATCH($E45,Settings!$F$4:$F$9,0)) | P45: HIGH
A46: 176 | B46: WR44 | C46: Chris Godwin | D46: TB | E46: WR | H46: 4.8 | M46: =F46*Settings!$B$4+G46*Settings!$B$5+H46*Settings!$B$6+I46*Settings!$B$7+J46*Settings!$B$8+K46*Settings!$B$9+L46*Settings!$B$10 | N46: =M46-INDEX(Settings!$G$4:$G$9,MATCH($E46,Settings!$F$4:$F$9,0)) | O46: =N46*INDEX(Settings!$H$4:$H$9,MATCH($E46,Settings!$F$4:$F$9,0)) | P46: HIGH
A47: 184 | B47: WR45 | C47: Makai Lemon | D47: PHI | E47: WR | H47: 4.7 | M47: =F47*Settings!$B$4+G47*Settings!$B$5+H47*Settings!$B$6+I47*Settings!$B$7+J47*Settings!$B$8+K47*Settings!$B$9+L47*Settings!$B$10 | N47: =M47-INDEX(Settings!$G$4:$G$9,MATCH($E47,Settings!$F$4:$F$9,0)) | O47: =N47*INDEX(Settings!$H$4:$H$9,MATCH($E47,Settings!$F$4:$F$9,0)) | P47: LOW
A48: 187 | B48: WR46 | C48: Xavier Worthy | D48: KC | E48: WR | G48: 0.3 | H48: 4.3 | M48: =F48*Settings!$B$4+G48*Settings!$B$5+H48*Settings!$B$6+I48*Settings!$B$7+J48*Settings!$B$8+K48*Settings!$B$9+L48*Settings!$B$10 | N48: =M48-INDEX(Settings!$G$4:$G$9,MATCH($E48,Settings!$F$4:$F$9,0)) | O48: =N48*INDEX(Settings!$H$4:$H$9,MATCH($E48,Settings!$F$4:$F$9,0)) | P48: HIGH
A49: 189 | B49: WR47 | C49: De'Zhaun Stribling | D49: SF | E49: WR | H49: 4.5 | M49: =F49*Settings!$B$4+G49*Settings!$B$5+H49*Settings!$B$6+I49*Settings!$B$7+J49*Settings!$B$8+K49*Settings!$B$9+L49*Settings!$B$10 | N49: =M49-INDEX(Settings!$G$4:$G$9,MATCH($E49,Settings!$F$4:$F$9,0)) | O49: =N49*INDEX(Settings!$H$4:$H$9,MATCH($E49,Settings!$F$4:$F$9,0)) | P49: LOW
A50: 190 | B50: WR48 | C50: Michael Pittman Jr. | D50: PIT | E50: WR | H50: 4.5 | M50: =F50*Settings!$B$4+G50*Settings!$B$5+H50*Settings!$B$6+I50*Settings!$B$7+J50*Settings!$B$8+K50*Settings!$B$9+L50*Settings!$B$10 | N50: =M50-INDEX(Settings!$G$4:$G$9,MATCH($E50,Settings!$F$4:$F$9,0)) | O50: =N50*INDEX(Settings!$H$4:$H$9,MATCH($E50,Settings!$F$4:$F$9,0)) | P50: HIGH
A51: 195 | B51: WR49 | C51: Stefon Diggs | D51: WAS | E51: WR | H51: 4.2 | M51: =F51*Settings!$B$4+G51*Settings!$B$5+H51*Settings!$B$6+I51*Settings!$B$7+J51*Settings!$B$8+K51*Settings!$B$9+L51*Settings!$B$10 | N51: =M51-INDEX(Settings!$G$4:$G$9,MATCH($E51,Settings!$F$4:$F$9,0)) | O51: =N51*INDEX(Settings!$H$4:$H$9,MATCH($E51,Settings!$F$4:$F$9,0)) | P51: HIGH
A52: 198 | B52: WR50 | C52: Jalen McMillan | D52: TB | E52: WR | G52: 0.2 | H52: 3.9 | M52: =F52*Settings!$B$4+G52*Settings!$B$5+H52*Settings!$B$6+I52*Settings!$B$7+J52*Settings!$B$8+K52*Settings!$B$9+L52*Settings!$B$10 | N52: =M52-INDEX(Settings!$G$4:$G$9,MATCH($E52,Settings!$F$4:$F$9,0)) | O52: =N52*INDEX(Settings!$H$4:$H$9,MATCH($E52,Settings!$F$4:$F$9,0)) | P52: LOW
A53: 202 | B53: WR51 | C53: Rashod Bateman | D53: BAL | E53: WR | H53: 4 | M53: =F53*Settings!$B$4+G53*Settings!$B$5+H53*Settings!$B$6+I53*Settings!$B$7+J53*Settings!$B$8+K53*Settings!$B$9+L53*Settings!$B$10 | N53: =M53-INDEX(Settings!$G$4:$G$9,MATCH($E53,Settings!$F$4:$F$9,0)) | O53: =N53*INDEX(Settings!$H$4:$H$9,MATCH($E53,Settings!$F$4:$F$9,0)) | P53: LOW
A54: 203 | B54: WR52 | C54: Rashid Shaheed | D54: SEA | E54: WR | G54: 0.5 | H54: 3.5 | M54: =F54*Settings!$B$4+G54*Settings!$B$5+H54*Settings!$B$6+I54*Settings!$B$7+J54*Settings!$B$8+K54*Settings!$B$9+L54*Settings!$B$10 | N54: =M54-INDEX(Settings!$G$4:$G$9,MATCH($E54,Settings!$F$4:$F$9,0)) | O54: =N54*INDEX(Settings!$H$4:$H$9,MATCH($E54,Settings!$F$4:$F$9,0)) | P54: LOW
A55: 204 | B55: WR53 | C55: Khalil Shakir | D55: BUF | E55: WR | G55: 0.1 | H55: 3.9 | M55: =F55*Settings!$B$4+G55*Settings!$B$5+H55*Settings!$B$6+I55*Settings!$B$7+J55*Settings!$B$8+K55*Settings!$B$9+L55*Settings!$B$10 | N55: =M55-INDEX(Settings!$G$4:$G$9,MATCH($E55,Settings!$F$4:$F$9,0)) | O55: =N55*INDEX(Settings!$H$4:$H$9,MATCH($E55,Settings!$F$4:$F$9,0)) | P55: HIGH
A56: 208 | B56: WR54 | C56: Michael Wilson | D56: ARI | E56: WR | H56: 3.7 | M56: =F56*Settings!$B$4+G56*Settings!$B$5+H56*Settings!$B$6+I56*Settings!$B$7+J56*Settings!$B$8+K56*Settings!$B$9+L56*Settings!$B$10 | N56: =M56-INDEX(Settings!$G$4:$G$9,MATCH($E56,Settings!$F$4:$F$9,0)) | O56: =N56*INDEX(Settings!$H$4:$H$9,MATCH($E56,Settings!$F$4:$F$9,0)) | P56: HIGH
A57: 209 | B57: WR55 | C57: Adonai Mitchell | D57: NYJ | E57: WR | G57: 0.1 | H57: 3.6 | M57: =F57*Settings!$B$4+G57*Settings!$B$5+H57*Settings!$B$6+I57*Settings!$B$7+J57*Settings!$B$8+K57*Settings!$B$9+L57*Settings!$B$10 | N57: =M57-INDEX(Settings!$G$4:$G$9,MATCH($E57,Settings!$F$4:$F$9,0)) | O57: =N57*INDEX(Settings!$H$4:$H$9,MATCH($E57,Settings!$F$4:$F$9,0)) | P57: LOW
A58: 210 | B58: WR56 | C58: Calvin Ridley | D58: TEN | E58: WR | G58: 0.2 | H58: 3.4 | M58: =F58*Settings!$B$4+G58*Settings!$B$5+H58*Settings!$B$6+I58*Settings!$B$7+J58*Settings!$B$8+K58*Settings!$B$9+L58*Settings!$B$10 | N58: =M58-INDEX(Settings!$G$4:$G$9,MATCH($E58,Settings!$F$4:$F$9,0)) | O58: =N58*INDEX(Settings!$H$4:$H$9,MATCH($E58,Settings!$F$4:$F$9,0)) | P58: LOW
A59: 212 | B59: WR57 | C59: Ja'Kobi Lane | D59: BAL | E59: WR | H59: 3.5 | M59: =F59*Settings!$B$4+G59*Settings!$B$5+H59*Settings!$B$6+I59*Settings!$B$7+J59*Settings!$B$8+K59*Settings!$B$9+L59*Settings!$B$10 | N59: =M59-INDEX(Settings!$G$4:$G$9,MATCH($E59,Settings!$F$4:$F$9,0)) | O59: =N59*INDEX(Settings!$H$4:$H$9,MATCH($E59,Settings!$F$4:$F$9,0)) | P59: LOW
A60: 213 | B60: WR58 | C60: Josh Downs | D60: IND | E60: WR | G60: 0.1 | H60: 3.4 | M60: =F60*Settings!$B$4+G60*Settings!$B$5+H60*Settings!$B$6+I60*Settings!$B$7+J60*Settings!$B$8+K60*Settings!$B$9+L60*Settings!$B$10 | N60: =M60-INDEX(Settings!$G$4:$G$9,MATCH($E60,Settings!$F$4:$F$9,0)) | O60: =N60*INDEX(Settings!$H$4:$H$9,MATCH($E60,Settings!$F$4:$F$9,0)) | P60: HIGH
A61: 215 | B61: WR59 | C61: Devaughn Vele | D61: NO | E61: WR | H61: 3.4 | M61: =F61*Settings!$B$4+G61*Settings!$B$5+H61*Settings!$B$6+I61*Settings!$B$7+J61*Settings!$B$8+K61*Settings!$B$9+L61*Settings!$B$10 | N61: =M61-INDEX(Settings!$G$4:$G$9,MATCH($E61,Settings!$F$4:$F$9,0)) | O61: =N61*INDEX(Settings!$H$4:$H$9,MATCH($E61,Settings!$F$4:$F$9,0)) | P61: LOW
A62: 216 | B62: WR60 | C62: Travis Hunter | D62: JAX | E62: WR | G62: 0.1 | H62: 3.3 | M62: =F62*Settings!$B$4+G62*Settings!$B$5+H62*Settings!$B$6+I62*Settings!$B$7+J62*Settings!$B$8+K62*Settings!$B$9+L62*Settings!$B$10 | N62: =M62-INDEX(Settings!$G$4:$G$9,MATCH($E62,Settings!$F$4:$F$9,0)) | O62: =N62*INDEX(Settings!$H$4:$H$9,MATCH($E62,Settings!$F$4:$F$9,0)) | P62: LOW
A63: 217 | B63: WR61 | C63: KC Concepcion | D63: CLE | E63: WR | G63: 0.2 | H63: 3.1 | M63: =F63*Settings!$B$4+G63*Settings!$B$5+H63*Settings!$B$6+I63*Settings!$B$7+J63*Settings!$B$8+K63*Settings!$B$9+L63*Settings!$B$10 | N63: =M63-INDEX(Settings!$G$4:$G$9,MATCH($E63,Settings!$F$4:$F$9,0)) | O63: =N63*INDEX(Settings!$H$4:$H$9,MATCH($E63,Settings!$F$4:$F$9,0)) | P63: LOW
A64: 218 | B64: WR62 | C64: Jauan Jennings | D64: MIN | E64: WR | H64: 3.3 | M64: =F64*Settings!$B$4+G64*Settings!$B$5+H64*Settings!$B$6+I64*Settings!$B$7+J64*Settings!$B$8+K64*Settings!$B$9+L64*Settings!$B$10 | N64: =M64-INDEX(Settings!$G$4:$G$9,MATCH($E64,Settings!$F$4:$F$9,0)) | O64: =N64*INDEX(Settings!$H$4:$H$9,MATCH($E64,Settings!$F$4:$F$9,0)) | P64: LOW
A65: 220 | B65: WR63 | C65: Isaac TeSlaa | D65: DET | E65: WR | H65: 3.2 | M65: =F65*Settings!$B$4+G65*Settings!$B$5+H65*Settings!$B$6+I65*Settings!$B$7+J65*Settings!$B$8+K65*Settings!$B$9+L65*Settings!$B$10 | N65: =M65-INDEX(Settings!$G$4:$G$9,MATCH($E65,Settings!$F$4:$F$9,0)) | O65: =N65*INDEX(Settings!$H$4:$H$9,MATCH($E65,Settings!$F$4:$F$9,0)) | P65: LOW
A66: 221 | B66: WR64 | C66: Jalen Nailor | D66: LV | E66: WR | G66: 0.1 | H66: 3 | M66: =F66*Settings!$B$4+G66*Settings!$B$5+H66*Settings!$B$6+I66*Settings!$B$7+J66*Settings!$B$8+K66*Settings!$B$9+L66*Settings!$B$10 | N66: =M66-INDEX(Settings!$G$4:$G$9,MATCH($E66,Settings!$F$4:$F$9,0)) | O66: =N66*INDEX(Settings!$H$4:$H$9,MATCH($E66,Settings!$F$4:$F$9,0)) | P66: LOW
A67: 222 | B67: WR65 | C67: Tyquan Thornton | D67: KC | E67: WR | H67: 3 | M67: =F67*Settings!$B$4+G67*Settings!$B$5+H67*Settings!$B$6+I67*Settings!$B$7+J67*Settings!$B$8+K67*Settings!$B$9+L67*Settings!$B$10 | N67: =M67-INDEX(Settings!$G$4:$G$9,MATCH($E67,Settings!$F$4:$F$9,0)) | O67: =N67*INDEX(Settings!$H$4:$H$9,MATCH($E67,Settings!$F$4:$F$9,0)) | P67: LOW
A68: 223 | B68: WR66 | C68: Jalen Coker | D68: CAR | E68: WR | H68: 3 | M68: =F68*Settings!$B$4+G68*Settings!$B$5+H68*Settings!$B$6+I68*Settings!$B$7+J68*Settings!$B$8+K68*Settings!$B$9+L68*Settings!$B$10 | N68: =M68-INDEX(Settings!$G$4:$G$9,MATCH($E68,Settings!$F$4:$F$9,0)) | O68: =N68*INDEX(Settings!$H$4:$H$9,MATCH($E68,Settings!$F$4:$F$9,0)) | P68: LOW
A69: 224 | B69: WR67 | C69: Denzel Boston | D69: CLE | E69: WR | H69: 3 | M69: =F69*Settings!$B$4+G69*Settings!$B$5+H69*Settings!$B$6+I69*Settings!$B$7+J69*Settings!$B$8+K69*Settings!$B$9+L69*Settings!$B$10 | N69: =M69-INDEX(Settings!$G$4:$G$9,MATCH($E69,Settings!$F$4:$F$9,0)) | O69: =N69*INDEX(Settings!$H$4:$H$9,MATCH($E69,Settings!$F$4:$F$9,0)) | P69: LOW
A70: 226 | B70: WR68 | C70: Dontayvion Wicks | D70: PHI | E70: WR | H70: 2.9 | M70: =F70*Settings!$B$4+G70*Settings!$B$5+H70*Settings!$B$6+I70*Settings!$B$7+J70*Settings!$B$8+K70*Settings!$B$9+L70*Settings!$B$10 | N70: =M70-INDEX(Settings!$G$4:$G$9,MATCH($E70,Settings!$F$4:$F$9,0)) | O70: =N70*INDEX(Settings!$H$4:$H$9,MATCH($E70,Settings!$F$4:$F$9,0)) | P70: LOW
A71: 227 | B71: WR69 | C71: Germie Bernard | D71: PIT | E71: WR | G71: 0.1 | H71: 2.8 | M71: =F71*Settings!$B$4+G71*Settings!$B$5+H71*Settings!$B$6+I71*Settings!$B$7+J71*Settings!$B$8+K71*Settings!$B$9+L71*Settings!$B$10 | N71: =M71-INDEX(Settings!$G$4:$G$9,MATCH($E71,Settings!$F$4:$F$9,0)) | O71: =N71*INDEX(Settings!$H$4:$H$9,MATCH($E71,Settings!$F$4:$F$9,0)) | P71: LOW
A72: 229 | B72: WR70 | C72: Ryan Flournoy | D72: DAL | E72: WR | G72: 0.1 | H72: 2.7 | M72: =F72*Settings!$B$4+G72*Settings!$B$5+H72*Settings!$B$6+I72*Settings!$B$7+J72*Settings!$B$8+K72*Settings!$B$9+L72*Settings!$B$10 | N72: =M72-INDEX(Settings!$G$4:$G$9,MATCH($E72,Settings!$F$4:$F$9,0)) | O72: =N72*INDEX(Settings!$H$4:$H$9,MATCH($E72,Settings!$F$4:$F$9,0)) | P72: LOW
A73: 230 | B73: WR71 | C73: Keon Coleman | D73: BUF | E73: WR | H73: 2.8 | M73: =F73*Settings!$B$4+G73*Settings!$B$5+H73*Settings!$B$6+I73*Settings!$B$7+J73*Settings!$B$8+K73*Settings!$B$9+L73*Settings!$B$10 | N73: =M73-INDEX(Settings!$G$4:$G$9,MATCH($E73,Settings!$F$4:$F$9,0)) | O73: =N73*INDEX(Settings!$H$4:$H$9,MATCH($E73,Settings!$F$4:$F$9,0)) | P73: LOW
A74: 231 | B74: WR72 | C74: Tre Tucker | D74: LV | E74: WR | G74: 0.3 | H74: 2.5 | M74: =F74*Settings!$B$4+G74*Settings!$B$5+H74*Settings!$B$6+I74*Settings!$B$7+J74*Settings!$B$8+K74*Settings!$B$9+L74*Settings!$B$10 | N74: =M74-INDEX(Settings!$G$4:$G$9,MATCH($E74,Settings!$F$4:$F$9,0)) | O74: =N74*INDEX(Settings!$H$4:$H$9,MATCH($E74,Settings!$F$4:$F$9,0)) | P74: LOW
A75: 232 | B75: WR73 | C75: Cooper Kupp | D75: SEA | E75: WR | H75: 2.8 | M75: =F75*Settings!$B$4+G75*Settings!$B$5+H75*Settings!$B$6+I75*Settings!$B$7+J75*Settings!$B$8+K75*Settings!$B$9+L75*Settings!$B$10 | N75: =M75-INDEX(Settings!$G$4:$G$9,MATCH($E75,Settings!$F$4:$F$9,0)) | O75: =N75*INDEX(Settings!$H$4:$H$9,MATCH($E75,Settings!$F$4:$F$9,0)) | P75: LOW
A76: 233 | B76: WR74 | C76: Kayshon Boutte | D76: HOU | E76: WR | H76: 2.8 | M76: =F76*Settings!$B$4+G76*Settings!$B$5+H76*Settings!$B$6+I76*Settings!$B$7+J76*Settings!$B$8+K76*Settings!$B$9+L76*Settings!$B$10 | N76: =M76-INDEX(Settings!$G$4:$G$9,MATCH($E76,Settings!$F$4:$F$9,0)) | O76: =N76*INDEX(Settings!$H$4:$H$9,MATCH($E76,Settings!$F$4:$F$9,0)) | P76: LOW
A77: 236 | B77: WR75 | C77: Jerry Jeudy | D77: CLE | E77: WR | H77: 2.7 | M77: =F77*Settings!$B$4+G77*Settings!$B$5+H77*Settings!$B$6+I77*Settings!$B$7+J77*Settings!$B$8+K77*Settings!$B$9+L77*Settings!$B$10 | N77: =M77-INDEX(Settings!$G$4:$G$9,MATCH($E77,Settings!$F$4:$F$9,0)) | O77: =N77*INDEX(Settings!$H$4:$H$9,MATCH($E77,Settings!$F$4:$F$9,0)) | P77: LOW
A78: 237 | B78: WR76 | C78: Keenan Allen | D78: IND | E78: WR | H78: 2.7 | M78: =F78*Settings!$B$4+G78*Settings!$B$5+H78*Settings!$B$6+I78*Settings!$B$7+J78*Settings!$B$8+K78*Settings!$B$9+L78*Settings!$B$10 | N78: =M78-INDEX(Settings!$G$4:$G$9,MATCH($E78,Settings!$F$4:$F$9,0)) | O78: =N78*INDEX(Settings!$H$4:$H$9,MATCH($E78,Settings!$F$4:$F$9,0)) | P78: LOW
A79: 238 | B79: WR77 | C79: Jordyn Tyson | D79: NO | E79: WR | H79: 2.7 | M79: =F79*Settings!$B$4+G79*Settings!$B$5+H79*Settings!$B$6+I79*Settings!$B$7+J79*Settings!$B$8+K79*Settings!$B$9+L79*Settings!$B$10 | N79: =M79-INDEX(Settings!$G$4:$G$9,MATCH($E79,Settings!$F$4:$F$9,0)) | O79: =N79*INDEX(Settings!$H$4:$H$9,MATCH($E79,Settings!$F$4:$F$9,0)) | P79: LOW
A80: 239 | B80: WR78 | C80: Xavier Legette | D80: CAR | E80: WR | G80: 0.1 | H80: 2.6 | M80: =F80*Settings!$B$4+G80*Settings!$B$5+H80*Settings!$B$6+I80*Settings!$B$7+J80*Settings!$B$8+K80*Settings!$B$9+L80*Settings!$B$10 | N80: =M80-INDEX(Settings!$G$4:$G$9,MATCH($E80,Settings!$F$4:$F$9,0)) | O80: =N80*INDEX(Settings!$H$4:$H$9,MATCH($E80,Settings!$F$4:$F$9,0)) | P80: LOW
A81: 240 | B81: WR79 | C81: Jaylin Noel | D81: HOU | E81: WR | G81: 0.1 | H81: 2.5 | M81: =F81*Settings!$B$4+G81*Settings!$B$5+H81*Settings!$B$6+I81*Settings!$B$7+J81*Settings!$B$8+K81*Settings!$B$9+L81*Settings!$B$10 | N81: =M81-INDEX(Settings!$G$4:$G$9,MATCH($E81,Settings!$F$4:$F$9,0)) | O81: =N81*INDEX(Settings!$H$4:$H$9,MATCH($E81,Settings!$F$4:$F$9,0)) | P81: LOW
A82: 241 | B82: WR80 | C82: Wan'Dale Robinson | D82: TEN | E82: WR | G82: 0.1 | H82: 2.5 | M82: =F82*Settings!$B$4+G82*Settings!$B$5+H82*Settings!$B$6+I82*Settings!$B$7+J82*Settings!$B$8+K82*Settings!$B$9+L82*Settings!$B$10 | N82: =M82-INDEX(Settings!$G$4:$G$9,MATCH($E82,Settings!$F$4:$F$9,0)) | O82: =N82*INDEX(Settings!$H$4:$H$9,MATCH($E82,Settings!$F$4:$F$9,0)) | P82: HIGH
A83: 242 | B83: WR81 | C83: Tank Dell | D83: HOU | E83: WR | G83: 0.2 | H83: 2.4 | M83: =F83*Settings!$B$4+G83*Settings!$B$5+H83*Settings!$B$6+I83*Settings!$B$7+J83*Settings!$B$8+K83*Settings!$B$9+L83*Settings!$B$10 | N83: =M83-INDEX(Settings!$G$4:$G$9,MATCH($E83,Settings!$F$4:$F$9,0)) | O83: =N83*INDEX(Settings!$H$4:$H$9,MATCH($E83,Settings!$F$4:$F$9,0)) | P83: LOW
A84: 243 | B84: WR82 | C84: Tre' Harris | D84: LAC | E84: WR | H84: 2.5 | M84: =F84*Settings!$B$4+G84*Settings!$B$5+H84*Settings!$B$6+I84*Settings!$B$7+J84*Settings!$B$8+K84*Settings!$B$9+L84*Settings!$B$10 | N84: =M84-INDEX(Settings!$G$4:$G$9,MATCH($E84,Settings!$F$4:$F$9,0)) | O84: =N84*INDEX(Settings!$H$4:$H$9,MATCH($E84,Settings!$F$4:$F$9,0)) | P84: LOW
A85: 244 | B85: WR83 | C85: Antonio Williams | D85: WAS | E85: WR | G85: 0.2 | H85: 2.3 | M85: =F85*Settings!$B$4+G85*Settings!$B$5+H85*Settings!$B$6+I85*Settings!$B$7+J85*Settings!$B$8+K85*Settings!$B$9+L85*Settings!$B$10 | N85: =M85-INDEX(Settings!$G$4:$G$9,MATCH($E85,Settings!$F$4:$F$9,0)) | O85: =N85*INDEX(Settings!$H$4:$H$9,MATCH($E85,Settings!$F$4:$F$9,0)) | P85: LOW
A86: 246 | B86: WR84 | C86: Omar Cooper Jr. | D86: NYJ | E86: WR | G86: 0.1 | H86: 2.2 | M86: =F86*Settings!$B$4+G86*Settings!$B$5+H86*Settings!$B$6+I86*Settings!$B$7+J86*Settings!$B$8+K86*Settings!$B$9+L86*Settings!$B$10 | N86: =M86-INDEX(Settings!$G$4:$G$9,MATCH($E86,Settings!$F$4:$F$9,0)) | O86: =N86*INDEX(Settings!$H$4:$H$9,MATCH($E86,Settings!$F$4:$F$9,0)) | P86: LOW
A87: 247 | B87: WR85 | C87: Jahan Dotson | D87: ATL | E87: WR | H87: 2.3 | M87: =F87*Settings!$B$4+G87*Settings!$B$5+H87*Settings!$B$6+I87*Settings!$B$7+J87*Settings!$B$8+K87*Settings!$B$9+L87*Settings!$B$10 | N87: =M87-INDEX(Settings!$G$4:$G$9,MATCH($E87,Settings!$F$4:$F$9,0)) | O87: =N87*INDEX(Settings!$H$4:$H$9,MATCH($E87,Settings!$F$4:$F$9,0)) | P87: LOW

Sheet TE
A1: TE — ranked by projected points
A2: Rank | B2: Pos | C2: Player | D2: Tm | E2: P | F2: PassTD | G2: RushTD | H2: RecTD | I2: FG | J2: PAT | K2: DefTD | L2: Saf | M2: Points | N2: VOR | O2: Adj VOR | P2: Conf | Q2: Notes
A3: 21 | B3: TE1 | C3: Brock Bowers | D3: LV | E3: TE | G3: 0.1 | H3: 6.8 | M3: =F3*Settings!$B$4+G3*Settings!$B$5+H3*Settings!$B$6+I3*Settings!$B$7+J3*Settings!$B$8+K3*Settings!$B$9+L3*Settings!$B$10 | N3: =M3-INDEX(Settings!$G$4:$G$9,MATCH($E3,Settings!$F$4:$F$9,0)) | O3: =N3*INDEX(Settings!$H$4:$H$9,MATCH($E3,Settings!$F$4:$F$9,0)) | P3: HIGH
A4: 22 | B4: TE2 | C4: Mark Andrews | D4: BAL | E4: TE | G4: 0.3 | H4: 6.5 | M4: =F4*Settings!$B$4+G4*Settings!$B$5+H4*Settings!$B$6+I4*Settings!$B$7+J4*Settings!$B$8+K4*Settings!$B$9+L4*Settings!$B$10 | N4: =M4-INDEX(Settings!$G$4:$G$9,MATCH($E4,Settings!$F$4:$F$9,0)) | O4: =N4*INDEX(Settings!$H$4:$H$9,MATCH($E4,Settings!$F$4:$F$9,0)) | P4: HIGH
A5: 32 | B5: TE3 | C5: Trey McBride | D5: ARI | E5: TE | H5: 6.2 | M5: =F5*Settings!$B$4+G5*Settings!$B$5+H5*Settings!$B$6+I5*Settings!$B$7+J5*Settings!$B$8+K5*Settings!$B$9+L5*Settings!$B$10 | N5: =M5-INDEX(Settings!$G$4:$G$9,MATCH($E5,Settings!$F$4:$F$9,0)) | O5: =N5*INDEX(Settings!$H$4:$H$9,MATCH($E5,Settings!$F$4:$F$9,0)) | P5: HIGH
A6: 35 | B6: TE4 | C6: Colston Loveland | D6: CHI | E6: TE | H6: 6 | M6: =F6*Settings!$B$4+G6*Settings!$B$5+H6*Settings!$B$6+I6*Settings!$B$7+J6*Settings!$B$8+K6*Settings!$B$9+L6*Settings!$B$10 | N6: =M6-INDEX(Settings!$G$4:$G$9,MATCH($E6,Settings!$F$4:$F$9,0)) | O6: =N6*INDEX(Settings!$H$4:$H$9,MATCH($E6,Settings!$F$4:$F$9,0)) | P6: HIGH
A7: 38 | B7: TE5 | C7: Dallas Goedert | D7: PHI | E7: TE | H7: 5.8 | M7: =F7*Settings!$B$4+G7*Settings!$B$5+H7*Settings!$B$6+I7*Settings!$B$7+J7*Settings!$B$8+K7*Settings!$B$9+L7*Settings!$B$10 | N7: =M7-INDEX(Settings!$G$4:$G$9,MATCH($E7,Settings!$F$4:$F$9,0)) | O7: =N7*INDEX(Settings!$H$4:$H$9,MATCH($E7,Settings!$F$4:$F$9,0)) | P7: HIGH
A8: 46 | B8: TE6 | C8: Jake Ferguson | D8: DAL | E8: TE | H8: 5.5 | M8: =F8*Settings!$B$4+G8*Settings!$B$5+H8*Settings!$B$6+I8*Settings!$B$7+J8*Settings!$B$8+K8*Settings!$B$9+L8*Settings!$B$10 | N8: =M8-INDEX(Settings!$G$4:$G$9,MATCH($E8,Settings!$F$4:$F$9,0)) | O8: =N8*INDEX(Settings!$H$4:$H$9,MATCH($E8,Settings!$F$4:$F$9,0)) | P8: HIGH
A9: 51 | B9: TE7 | C9: Tyler Warren | D9: IND | E9: TE | G9: 0.2 | H9: 5.2 | M9: =F9*Settings!$B$4+G9*Settings!$B$5+H9*Settings!$B$6+I9*Settings!$B$7+J9*Settings!$B$8+K9*Settings!$B$9+L9*Settings!$B$10 | N9: =M9-INDEX(Settings!$G$4:$G$9,MATCH($E9,Settings!$F$4:$F$9,0)) | O9: =N9*INDEX(Settings!$H$4:$H$9,MATCH($E9,Settings!$F$4:$F$9,0)) | P9: HIGH
A10: 56 | B10: TE8 | C10: George Kittle | D10: SF | E10: TE | H10: 5.3 | M10: =F10*Settings!$B$4+G10*Settings!$B$5+H10*Settings!$B$6+I10*Settings!$B$7+J10*Settings!$B$8+K10*Settings!$B$9+L10*Settings!$B$10 | N10: =M10-INDEX(Settings!$G$4:$G$9,MATCH($E10,Settings!$F$4:$F$9,0)) | O10: =N10*INDEX(Settings!$H$4:$H$9,MATCH($E10,Settings!$F$4:$F$9,0)) | P10: HIGH
A11: 65 | B11: TE9 | C11: Hunter Henry | D11: NE | E11: TE | H11: 5.2 | M11: =F11*Settings!$B$4+G11*Settings!$B$5+H11*Settings!$B$6+I11*Settings!$B$7+J11*Settings!$B$8+K11*Settings!$B$9+L11*Settings!$B$10 | N11: =M11-INDEX(Settings!$G$4:$G$9,MATCH($E11,Settings!$F$4:$F$9,0)) | O11: =N11*INDEX(Settings!$H$4:$H$9,MATCH($E11,Settings!$F$4:$F$9,0)) | P11: HIGH
A12: 66 | B12: TE10 | C12: Terrance Ferguson | D12: LAR | E12: TE | H12: 5.2 | M12: =F12*Settings!$B$4+G12*Settings!$B$5+H12*Settings!$B$6+I12*Settings!$B$7+J12*Settings!$B$8+K12*Settings!$B$9+L12*Settings!$B$10 | N12: =M12-INDEX(Settings!$G$4:$G$9,MATCH($E12,Settings!$F$4:$F$9,0)) | O12: =N12*INDEX(Settings!$H$4:$H$9,MATCH($E12,Settings!$F$4:$F$9,0)) | P12: HIGH
A13: 67 | B13: TE11 | C13: Sam LaPorta | D13: DET | E13: TE | H13: 5.2 | M13: =F13*Settings!$B$4+G13*Settings!$B$5+H13*Settings!$B$6+I13*Settings!$B$7+J13*Settings!$B$8+K13*Settings!$B$9+L13*Settings!$B$10 | N13: =M13-INDEX(Settings!$G$4:$G$9,MATCH($E13,Settings!$F$4:$F$9,0)) | O13: =N13*INDEX(Settings!$H$4:$H$9,MATCH($E13,Settings!$F$4:$F$9,0)) | P13: HIGH
A14: 77 | B14: TE12 | C14: Tucker Kraft | D14: GB | E14: TE | G14: 0.1 | H14: 4.7 | M14: =F14*Settings!$B$4+G14*Settings!$B$5+H14*Settings!$B$6+I14*Settings!$B$7+J14*Settings!$B$8+K14*Settings!$B$9+L14*Settings!$B$10 | N14: =M14-INDEX(Settings!$G$4:$G$9,MATCH($E14,Settings!$F$4:$F$9,0)) | O14: =N14*INDEX(Settings!$H$4:$H$9,MATCH($E14,Settings!$F$4:$F$9,0)) | P14: HIGH
A15: 80 | B15: TE13 | C15: Dalton Kincaid | D15: BUF | E15: TE | H15: 4.7 | M15: =F15*Settings!$B$4+G15*Settings!$B$5+H15*Settings!$B$6+I15*Settings!$B$7+J15*Settings!$B$8+K15*Settings!$B$9+L15*Settings!$B$10 | N15: =M15-INDEX(Settings!$G$4:$G$9,MATCH($E15,Settings!$F$4:$F$9,0)) | O15: =N15*INDEX(Settings!$H$4:$H$9,MATCH($E15,Settings!$F$4:$F$9,0)) | P15: HIGH
A16: 111 | B16: TE14 | C16: Travis Kelce | D16: KC | E16: TE | H16: 4.2 | M16: =F16*Settings!$B$4+G16*Settings!$B$5+H16*Settings!$B$6+I16*Settings!$B$7+J16*Settings!$B$8+K16*Settings!$B$9+L16*Settings!$B$10 | N16: =M16-INDEX(Settings!$G$4:$G$9,MATCH($E16,Settings!$F$4:$F$9,0)) | O16: =N16*INDEX(Settings!$H$4:$H$9,MATCH($E16,Settings!$F$4:$F$9,0)) | P16: HIGH
A17: 112 | B17: TE15 | C17: Harold Fannin Jr. | D17: CLE | E17: TE | G17: 0.1 | H17: 4.1 | M17: =F17*Settings!$B$4+G17*Settings!$B$5+H17*Settings!$B$6+I17*Settings!$B$7+J17*Settings!$B$8+K17*Settings!$B$9+L17*Settings!$B$10 | N17: =M17-INDEX(Settings!$G$4:$G$9,MATCH($E17,Settings!$F$4:$F$9,0)) | O17: =N17*INDEX(Settings!$H$4:$H$9,MATCH($E17,Settings!$F$4:$F$9,0)) | P17: HIGH
A18: 135 | B18: TE16 | C18: AJ Barner | D18: SEA | E18: TE | G18: 0.2 | H18: 3.8 | M18: =F18*Settings!$B$4+G18*Settings!$B$5+H18*Settings!$B$6+I18*Settings!$B$7+J18*Settings!$B$8+K18*Settings!$B$9+L18*Settings!$B$10 | N18: =M18-INDEX(Settings!$G$4:$G$9,MATCH($E18,Settings!$F$4:$F$9,0)) | O18: =N18*INDEX(Settings!$H$4:$H$9,MATCH($E18,Settings!$F$4:$F$9,0)) | P18: HIGH
A19: 136 | B19: TE17 | C19: Brenton Strange | D19: JAX | E19: TE | H19: 4 | M19: =F19*Settings!$B$4+G19*Settings!$B$5+H19*Settings!$B$6+I19*Settings!$B$7+J19*Settings!$B$8+K19*Settings!$B$9+L19*Settings!$B$10 | N19: =M19-INDEX(Settings!$G$4:$G$9,MATCH($E19,Settings!$F$4:$F$9,0)) | O19: =N19*INDEX(Settings!$H$4:$H$9,MATCH($E19,Settings!$F$4:$F$9,0)) | P19: HIGH
A20: 137 | B20: TE18 | C20: Darren Waller | D20: CAR | E20: TE | H20: 4 | M20: =F20*Settings!$B$4+G20*Settings!$B$5+H20*Settings!$B$6+I20*Settings!$B$7+J20*Settings!$B$8+K20*Settings!$B$9+L20*Settings!$B$10 | N20: =M20-INDEX(Settings!$G$4:$G$9,MATCH($E20,Settings!$F$4:$F$9,0)) | O20: =N20*INDEX(Settings!$H$4:$H$9,MATCH($E20,Settings!$F$4:$F$9,0)) | P20: HIGH
A21: 138 | B21: TE19 | C21: Isaiah Likely | D21: NYG | E21: TE | H21: 4 | M21: =F21*Settings!$B$4+G21*Settings!$B$5+H21*Settings!$B$6+I21*Settings!$B$7+J21*Settings!$B$8+K21*Settings!$B$9+L21*Settings!$B$10 | N21: =M21-INDEX(Settings!$G$4:$G$9,MATCH($E21,Settings!$F$4:$F$9,0)) | O21: =N21*INDEX(Settings!$H$4:$H$9,MATCH($E21,Settings!$F$4:$F$9,0)) | P21: HIGH
A22: 143 | B22: TE20 | C22: Mike Gesicki | D22: CIN | E22: TE | H22: 3.9 | M22: =F22*Settings!$B$4+G22*Settings!$B$5+H22*Settings!$B$6+I22*Settings!$B$7+J22*Settings!$B$8+K22*Settings!$B$9+L22*Settings!$B$10 | N22: =M22-INDEX(Settings!$G$4:$G$9,MATCH($E22,Settings!$F$4:$F$9,0)) | O22: =N22*INDEX(Settings!$H$4:$H$9,MATCH($E22,Settings!$F$4:$F$9,0)) | P22: HIGH
A23: 144 | B23: TE21 | C23: Pat Freiermuth | D23: PIT | E23: TE | H23: 3.9 | M23: =F23*Settings!$B$4+G23*Settings!$B$5+H23*Settings!$B$6+I23*Settings!$B$7+J23*Settings!$B$8+K23*Settings!$B$9+L23*Settings!$B$10 | N23: =M23-INDEX(Settings!$G$4:$G$9,MATCH($E23,Settings!$F$4:$F$9,0)) | O23: =N23*INDEX(Settings!$H$4:$H$9,MATCH($E23,Settings!$F$4:$F$9,0)) | P23: MEDIUM
A24: 150 | B24: TE22 | C24: Kyle Pitts | D24: ATL | E24: TE | H24: 3.6 | M24: =F24*Settings!$B$4+G24*Settings!$B$5+H24*Settings!$B$6+I24*Settings!$B$7+J24*Settings!$B$8+K24*Settings!$B$9+L24*Settings!$B$10 | N24: =M24-INDEX(Settings!$G$4:$G$9,MATCH($E24,Settings!$F$4:$F$9,0)) | O24: =N24*INDEX(Settings!$H$4:$H$9,MATCH($E24,Settings!$F$4:$F$9,0)) | P24: HIGH
A25: 152 | B25: TE23 | C25: David Njoku | D25: LAC | E25: TE | H25: 3.5 | M25: =F25*Settings!$B$4+G25*Settings!$B$5+H25*Settings!$B$6+I25*Settings!$B$7+J25*Settings!$B$8+K25*Settings!$B$9+L25*Settings!$B$10 | N25: =M25-INDEX(Settings!$G$4:$G$9,MATCH($E25,Settings!$F$4:$F$9,0)) | O25: =N25*INDEX(Settings!$H$4:$H$9,MATCH($E25,Settings!$F$4:$F$9,0)) | P25: HIGH
A26: 165 | B26: TE24 | C26: Gunnar Helm | D26: TEN | E26: TE | H26: 3.1 | M26: =F26*Settings!$B$4+G26*Settings!$B$5+H26*Settings!$B$6+I26*Settings!$B$7+J26*Settings!$B$8+K26*Settings!$B$9+L26*Settings!$B$10 | N26: =M26-INDEX(Settings!$G$4:$G$9,MATCH($E26,Settings!$F$4:$F$9,0)) | O26: =N26*INDEX(Settings!$H$4:$H$9,MATCH($E26,Settings!$F$4:$F$9,0)) | P26: HIGH
A27: 170 | B27: TE25 | C27: Chigoziem Okonkwo | D27: WAS | E27: TE | H27: 3 | M27: =F27*Settings!$B$4+G27*Settings!$B$5+H27*Settings!$B$6+I27*Settings!$B$7+J27*Settings!$B$8+K27*Settings!$B$9+L27*Settings!$B$10 | N27: =M27-INDEX(Settings!$G$4:$G$9,MATCH($E27,Settings!$F$4:$F$9,0)) | O27: =N27*INDEX(Settings!$H$4:$H$9,MATCH($E27,Settings!$F$4:$F$9,0)) | P27: LOW
A28: 171 | B28: TE26 | C28: Kenyon Sadiq | D28: NYJ | E28: TE | H28: 3 | M28: =F28*Settings!$B$4+G28*Settings!$B$5+H28*Settings!$B$6+I28*Settings!$B$7+J28*Settings!$B$8+K28*Settings!$B$9+L28*Settings!$B$10 | N28: =M28-INDEX(Settings!$G$4:$G$9,MATCH($E28,Settings!$F$4:$F$9,0)) | O28: =N28*INDEX(Settings!$H$4:$H$9,MATCH($E28,Settings!$F$4:$F$9,0)) | P28: HIGH
A29: 172 | B29: TE27 | C29: Dalton Schultz | D29: HOU | E29: TE | H29: 3 | M29: =F29*Settings!$B$4+G29*Settings!$B$5+H29*Settings!$B$6+I29*Settings!$B$7+J29*Settings!$B$8+K29*Settings!$B$9+L29*Settings!$B$10 | N29: =M29-INDEX(Settings!$G$4:$G$9,MATCH($E29,Settings!$F$4:$F$9,0)) | O29: =N29*INDEX(Settings!$H$4:$H$9,MATCH($E29,Settings!$F$4:$F$9,0)) | P29: HIGH
A30: 173 | B30: TE28 | C30: Colby Parkinson | D30: LAR | E30: TE | H30: 3 | M30: =F30*Settings!$B$4+G30*Settings!$B$5+H30*Settings!$B$6+I30*Settings!$B$7+J30*Settings!$B$8+K30*Settings!$B$9+L30*Settings!$B$10 | N30: =M30-INDEX(Settings!$G$4:$G$9,MATCH($E30,Settings!$F$4:$F$9,0)) | O30: =N30*INDEX(Settings!$H$4:$H$9,MATCH($E30,Settings!$F$4:$F$9,0)) | P30: HIGH
... A34: 183 | B34: TE32 | C34: Dawson Knox | D34: BUF | E34: TE | H34: 2.9 | M34: =F34*Settings!$B$4+G34*Settings!$B$5+H34*Settings!$B$6+I34*Settings!$B$7+J34*Settings!$B$8+K34*Settings!$B$9+L34*Settings!$B$10 | N34: =M34-INDEX(Settings!$G$4:$G$9,MATCH($E34,Settings!$F$4:$F$9,0)) | O34: =N34*INDEX(Settings!$H$4:$H$9,MATCH($E34,Settings!$F$4:$F$9,0)) | P34: HIGH

Sheet K
A1: K — ranked by projected points
A2: Rank | B2: Pos | C2: Player | D2: Tm | E2: P | F2: PassTD | G2: RushTD | H2: RecTD | I2: FG | J2: PAT | K2: DefTD | L2: Saf | M2: Points | N2: VOR | O2: Adj VOR | P2: Conf | Q2: Notes
A3: 17 | B3: K1 | C3: Jason Myers | D3: SEA | E3: K | I3: 39 | J3: 50 | M3: =F3*Settings!$B$4+G3*Settings!$B$5+H3*Settings!$B$6+I3*Settings!$B$7+J3*Settings!$B$8+K3*Settings!$B$9+L3*Settings!$B$10 | N3: =M3-INDEX(Settings!$G$4:$G$9,MATCH($E3,Settings!$F$4:$F$9,0)) | O3: =N3*INDEX(Settings!$H$4:$H$9,MATCH($E3,Settings!$F$4:$F$9,0)) | P3: HIGH | Q3: Led NFL 43 FGM 2025 on 48 FGA
A4: 23 | B4: K2 | C4: Ka'imi Fairbairn | D4: HOU | E4: K | I4: 39 | J4: 39 | M4: =F4*Settings!$B$4+G4*Settings!$B$5+H4*Settings!$B$6+I4*Settings!$B$7+J4*Settings!$B$8+K4*Settings!$B$9+L4*Settings!$B$10 | N4: =M4-INDEX(Settings!$G$4:$G$9,MATCH($E4,Settings!$F$4:$F$9,0)) | O4: =N4*INDEX(Settings!$H$4:$H$9,MATCH($E4,Settings!$F$4:$F$9,0)) | P4: HIGH | Q4: Best FG-lean in league; HOU led NFL 52 FGA
A5: 27 | B5: K3 | C5: Brandon Aubrey | D5: DAL | E5: K | I5: 35 | J5: 49 | M5: =F5*Settings!$B$4+G5*Settings!$B$5+H5*Settings!$B$6+I5*Settings!$B$7+J5*Settings!$B$8+K5*Settings!$B$9+L5*Settings!$B$10 | N5: =M5-INDEX(Settings!$G$4:$G$9,MATCH($E5,Settings!$F$4:$F$9,0)) | O5: =N5*INDEX(Settings!$H$4:$H$9,MATCH($E5,Settings!$F$4:$F$9,0)) | P5: HIGH
A6: 29 | B6: K4 | C6: Blake Grupe | D6: IND | E6: K | I6: 34 | J6: 51 | M6: =F6*Settings!$B$4+G6*Settings!$B$5+H6*Settings!$B$6+I6*Settings!$B$7+J6*Settings!$B$8+K6*Settings!$B$9+L6*Settings!$B$10 | N6: =M6-INDEX(Settings!$G$4:$G$9,MATCH($E6,Settings!$F$4:$F$9,0)) | O6: =N6*INDEX(Settings!$H$4:$H$9,MATCH($E6,Settings!$F$4:$F$9,0)) | P6: MEDIUM | Q6: Shrader listed as backup
A7: 42 | B7: K5 | C7: Jake Bates | D7: DET | E7: K | I7: 31 | J7: 53 | M7: =F7*Settings!$B$4+G7*Settings!$B$5+H7*Settings!$B$6+I7*Settings!$B$7+J7*Settings!$B$8+K7*Settings!$B$9+L7*Settings!$B$10 | N7: =M7-INDEX(Settings!$G$4:$G$9,MATCH($E7,Settings!$F$4:$F$9,0)) | O7: =N7*INDEX(Settings!$H$4:$H$9,MATCH($E7,Settings!$F$4:$F$9,0)) | P7: HIGH | Q7: XP-heavy; TD offense caps him
A8: 52 | B8: K6 | C8: Cameron Dicker | D8: LAC | E8: K | I8: 35 | J8: 38 | M8: =F8*Settings!$B$4+G8*Settings!$B$5+H8*Settings!$B$6+I8*Settings!$B$7+J8*Settings!$B$8+K8*Settings!$B$9+L8*Settings!$B$10 | N8: =M8-INDEX(Settings!$G$4:$G$9,MATCH($E8,Settings!$F$4:$F$9,0)) | O8: =N8*INDEX(Settings!$H$4:$H$9,MATCH($E8,Settings!$F$4:$F$9,0)) | P8: HIGH | Q8: 92.7 pct in 2025; strong FG lean
A9: 53 | B9: K7 | C9: Cairo Santos | D9: CHI | E9: K | I9: 32 | J9: 47 | M9: =F9*Settings!$B$4+G9*Settings!$B$5+H9*Settings!$B$6+I9*Settings!$B$7+J9*Settings!$B$8+K9*Settings!$B$9+L9*Settings!$B$10 | N9: =M9-INDEX(Settings!$G$4:$G$9,MATCH($E9,Settings!$F$4:$F$9,0)) | O9: =N9*INDEX(Settings!$H$4:$H$9,MATCH($E9,Settings!$F$4:$F$9,0)) | P9: HIGH | Q9: 39 FGA in 2025
A10: 58 | B10: K8 | C10: Harrison Mevis | D10: LAR | E10: K | I10: 29 | J10: 55 | M10: =F10*Settings!$B$4+G10*Settings!$B$5+H10*Settings!$B$6+I10*Settings!$B$7+J10*Settings!$B$8+K10*Settings!$B$9+L10*Settings!$B$10 | N10: =M10-INDEX(Settings!$G$4:$G$9,MATCH($E10,Settings!$F$4:$F$9,0)) | O10: =N10*INDEX(Settings!$H$4:$H$9,MATCH($E10,Settings!$F$4:$F$9,0)) | P10: MEDIUM | Q10: Most TD-heavy K; LAR led NFL RZ trips
A11: 69 | B11: K9 | C11: Will Reichard | D11: MIN | E11: K | I11: 33 | J11: 42 | M11: =F11*Settings!$B$4+G11*Settings!$B$5+H11*Settings!$B$6+I11*Settings!$B$7+J11*Settings!$B$8+K11*Settings!$B$9+L11*Settings!$B$10 | N11: =M11-INDEX(Settings!$G$4:$G$9,MATCH($E11,Settings!$F$4:$F$9,0)) | O11: =N11*INDEX(Settings!$H$4:$H$9,MATCH($E11,Settings!$F$4:$F$9,0)) | P11: HIGH | Q11: 94.3 pct in 2025
A12: 70 | B12: K10 | C12: Chase McLaughlin | D12: TB | E12: K | I12: 33 | J12: 42 | M12: =F12*Settings!$B$4+G12*Settings!$B$5+H12*Settings!$B$6+I12*Settings!$B$7+J12*Settings!$B$8+K12*Settings!$B$9+L12*Settings!$B$10 | N12: =M12-INDEX(Settings!$G$4:$G$9,MATCH($E12,Settings!$F$4:$F$9,0)) | O12: =N12*INDEX(Settings!$H$4:$H$9,MATCH($E12,Settings!$F$4:$F$9,0)) | P12: HIGH
A13: 82 | B13: K11 | C13: Tyler Loop | D13: BAL | E13: K | I13: 29 | J13: 49 | M13: =F13*Settings!$B$4+G13*Settings!$B$5+H13*Settings!$B$6+I13*Settings!$B$7+J13*Settings!$B$8+K13*Settings!$B$9+L13*Settings!$B$10 | N13: =M13-INDEX(Settings!$G$4:$G$9,MATCH($E13,Settings!$F$4:$F$9,0)) | O13: =N13*INDEX(Settings!$H$4:$H$9,MATCH($E13,Settings!$F$4:$F$9,0)) | P13: MEDIUM | Q13: Year 2; BAL 11.5 win total
A14: 87 | B14: K12 | C14: Cam Little | D14: JAX | E14: K | I14: 29 | J14: 48 | M14: =F14*Settings!$B$4+G14*Settings!$B$5+H14*Settings!$B$6+I14*Settings!$B$7+J14*Settings!$B$8+K14*Settings!$B$9+L14*Settings!$B$10 | N14: =M14-INDEX(Settings!$G$4:$G$9,MATCH($E14,Settings!$F$4:$F$9,0)) | O14: =N14*INDEX(Settings!$H$4:$H$9,MATCH($E14,Settings!$F$4:$F$9,0)) | P14: HIGH
A15: 89 | B15: K13 | C15: Harrison Butker | D15: KC | E15: K | I15: 33 | J15: 35 | M15: =F15*Settings!$B$4+G15*Settings!$B$5+H15*Settings!$B$6+I15*Settings!$B$7+J15*Settings!$B$8+K15*Settings!$B$9+L15*Settings!$B$10 | N15: =M15-INDEX(Settings!$G$4:$G$9,MATCH($E15,Settings!$F$4:$F$9,0)) | O15: =N15*INDEX(Settings!$H$4:$H$9,MATCH($E15,Settings!$F$4:$F$9,0)) | P15: HIGH | Q15: Strong FG lean
A16: 90 | B16: K14 | C16: Wil Lutz | D16: DEN | E16: K | I16: 30 | J16: 44 | M16: =F16*Settings!$B$4+G16*Settings!$B$5+H16*Settings!$B$6+I16*Settings!$B$7+J16*Settings!$B$8+K16*Settings!$B$9+L16*Settings!$B$10 | N16: =M16-INDEX(Settings!$G$4:$G$9,MATCH($E16,Settings!$F$4:$F$9,0)) | O16: =N16*INDEX(Settings!$H$4:$H$9,MATCH($E16,Settings!$F$4:$F$9,0)) | P16: HIGH
A17: 91 | B17: K15 | C17: Evan McPherson | D17: CIN | E17: K | I17: 29 | J17: 47 | M17: =F17*Settings!$B$4+G17*Settings!$B$5+H17*Settings!$B$6+I17*Settings!$B$7+J17*Settings!$B$8+K17*Settings!$B$9+L17*Settings!$B$10 | N17: =M17-INDEX(Settings!$G$4:$G$9,MATCH($E17,Settings!$F$4:$F$9,0)) | O17: =N17*INDEX(Settings!$H$4:$H$9,MATCH($E17,Settings!$F$4:$F$9,0)) | P17: HIGH | Q17: Only 28 FGA in 2025
A18: 124 | B18: K16 | C18: Nick Folk | D18: ATL | E18: K | I18: 30 | J18: 41 | M18: =F18*Settings!$B$4+G18*Settings!$B$5+H18*Settings!$B$6+I18*Settings!$B$7+J18*Settings!$B$8+K18*Settings!$B$9+L18*Settings!$B$10 | N18: =M18-INDEX(Settings!$G$4:$G$9,MATCH($E18,Settings!$F$4:$F$9,0)) | O18: =N18*INDEX(Settings!$H$4:$H$9,MATCH($E18,Settings!$F$4:$F$9,0)) | P18: MEDIUM | Q18: Age risk
A19: 133 | B19: K17 | C19: Eddy Pineiro | D19: SF | E19: K | I19: 31 | J19: 37 | M19: =F19*Settings!$B$4+G19*Settings!$B$5+H19*Settings!$B$6+I19*Settings!$B$7+J19*Settings!$B$8+K19*Settings!$B$9+L19*Settings!$B$10 | N19: =M19-INDEX(Settings!$G$4:$G$9,MATCH($E19,Settings!$F$4:$F$9,0)) | O19: =N19*INDEX(Settings!$H$4:$H$9,MATCH($E19,Settings!$F$4:$F$9,0)) | P19: MEDIUM
A20: 148 | B20: K18 | C20: Daniel Carlson | D20: NO | E20: K | I20: 30 | J20: 37 | M20: =F20*Settings!$B$4+G20*Settings!$B$5+H20*Settings!$B$6+I20*Settings!$B$7+J20*Settings!$B$8+K20*Settings!$B$9+L20*Settings!$B$10 | N20: =M20-INDEX(Settings!$G$4:$G$9,MATCH($E20,Settings!$F$4:$F$9,0)) | O20: =N20*INDEX(Settings!$H$4:$H$9,MATCH($E20,Settings!$F$4:$F$9,0)) | P20: LOW | Q20: Published projections stale (built on Smyth); NO 42 FGA at 71.4 pct = upside
A21: 154 | B21: K19 | C21: Trey Smack | D21: GB | E21: K | I21: 29 | J21: 38 | M21: =F21*Settings!$B$4+G21*Settings!$B$5+H21*Settings!$B$6+I21*Settings!$B$7+J21*Settings!$B$8+K21*Settings!$B$9+L21*Settings!$B$10 | N21: =M21-INDEX(Settings!$G$4:$G$9,MATCH($E21,Settings!$F$4:$F$9,0)) | O21: =N21*INDEX(Settings!$H$4:$H$9,MATCH($E21,Settings!$F$4:$F$9,0)) | P21: LOW | Q21: Rookie 6th rounder
A22: 162 | B22: K20 | C22: Tyler Bass | D22: BUF | E22: K | I22: 26 | J22: 46 | M22: =F22*Settings!$B$4+G22*Settings!$B$5+H22*Settings!$B$6+I22*Settings!$B$7+J22*Settings!$B$8+K22*Settings!$B$9+L22*Settings!$B$10 | N22: =M22-INDEX(Settings!$G$4:$G$9,MATCH($E22,Settings!$F$4:$F$9,0)) | O22: =N22*INDEX(Settings!$H$4:$H$9,MATCH($E22,Settings!$F$4:$F$9,0)) | P22: MEDIUM | Q22: TRAP: BUF had fewest FGA in NFL (21) in 2025
A23: 164 | B23: K21 | C23: Jason Sanders | D23: NYJ | E23: K | I23: 29 | J23: 35 | M23: =F23*Settings!$B$4+G23*Settings!$B$5+H23*Settings!$B$6+I23*Settings!$B$7+J23*Settings!$B$8+K23*Settings!$B$9+L23*Settings!$B$10 | N23: =M23-INDEX(Settings!$G$4:$G$9,MATCH($E23,Settings!$F$4:$F$9,0)) | O23: =N23*INDEX(Settings!$H$4:$H$9,MATCH($E23,Settings!$F$4:$F$9,0)) | P23: HIGH | Q23: Won job; York waived
A24: 169 | B24: K22 | C24: Joey Slye | D24: TEN | E24: K | I24: 29 | J24: 34 | M24: =F24*Settings!$B$4+G24*Settings!$B$5+H24*Settings!$B$6+I24*Settings!$B$7+J24*Settings!$B$8+K24*Settings!$B$9+L24*Settings!$B$10 | N24: =M24-INDEX(Settings!$G$4:$G$9,MATCH($E24,Settings!$F$4:$F$9,0)) | O24: =N24*INDEX(Settings!$H$4:$H$9,MATCH($E24,Settings!$F$4:$F$9,0)) | P24: MEDIUM
A25: 177 | B25: K23 | C25: Andres Borregales | D25: NE | E25: K | I25: 26 | J25: 42 | M25: =F25*Settings!$B$4+G25*Settings!$B$5+H25*Settings!$B$6+I25*Settings!$B$7+J25*Settings!$B$8+K25*Settings!$B$9+L25*Settings!$B$10 | N25: =M25-INDEX(Settings!$G$4:$G$9,MATCH($E25,Settings!$F$4:$F$9,0)) | O25: =N25*INDEX(Settings!$H$4:$H$9,MATCH($E25,Settings!$F$4:$F$9,0)) | P25: MEDIUM
A26: 178 | B26: K24 | C26: Drew Stevens | D26: WAS | E26: K | I26: 27 | J26: 39 | M26: =F26*Settings!$B$4+G26*Settings!$B$5+H26*Settings!$B$6+I26*Settings!$B$7+J26*Settings!$B$8+K26*Settings!$B$9+L26*Settings!$B$10 | N26: =M26-INDEX(Settings!$G$4:$G$9,MATCH($E26,Settings!$F$4:$F$9,0)) | O26: =N26*INDEX(Settings!$H$4:$H$9,MATCH($E26,Settings!$F$4:$F$9,0)) | P26: LOW | Q26: Rookie
A27: 185 | B27: K25 | C27: Riley Patterson | D27: MIA | E27: K | I27: 27 | J27: 38 | M27: =F27*Settings!$B$4+G27*Settings!$B$5+H27*Settings!$B$6+I27*Settings!$B$7+J27*Settings!$B$8+K27*Settings!$B$9+L27*Settings!$B$10 | N27: =M27-INDEX(Settings!$G$4:$G$9,MATCH($E27,Settings!$F$4:$F$9,0)) | O27: =N27*INDEX(Settings!$H$4:$H$9,MATCH($E27,Settings!$F$4:$F$9,0)) | P27: LOW | Q27: Zane Gonzalez on roster
A28: 186 | B28: K26 | C28: Jake Elliott | D28: PHI | E28: K | I28: 26 | J28: 41 | M28: =F28*Settings!$B$4+G28*Settings!$B$5+H28*Settings!$B$6+I28*Settings!$B$7+J28*Settings!$B$8+K28*Settings!$B$9+L28*Settings!$B$10 | N28: =M28-INDEX(Settings!$G$4:$G$9,MATCH($E28,Settings!$F$4:$F$9,0)) | O28: =N28*INDEX(Settings!$H$4:$H$9,MATCH($E28,Settings!$F$4:$F$9,0)) | P28: MEDIUM | Q28: 74.1 pct in 2025 (worst); PHI best RZ TD pct
A29: 193 | B29: K27 | C29: Chad Ryland | D29: ARI | E29: K | I29: 26 | J29: 37 | M29: =F29*Settings!$B$4+G29*Settings!$B$5+H29*Settings!$B$6+I29*Settings!$B$7+J29*Settings!$B$8+K29*Settings!$B$9+L29*Settings!$B$10 | N29: =M29-INDEX(Settings!$G$4:$G$9,MATCH($E29,Settings!$F$4:$F$9,0)) | O29: =N29*INDEX(Settings!$H$4:$H$9,MATCH($E29,Settings!$F$4:$F$9,0)) | P29: MEDIUM | Q29: ARI 4.5 win total
A30: 194 | B30: K28 | C30: Giants Kicker | D30: NYG | E30: K | I30: 27 | J30: 34 | M30: =F30*Settings!$B$4+G30*Settings!$B$5+H30*Settings!$B$6+I30*Settings!$B$7+J30*Settings!$B$8+K30*Settings!$B$9+L30*Settings!$B$10 | N30: =M30-INDEX(Settings!$G$4:$G$9,MATCH($E30,Settings!$F$4:$F$9,0)) | O30: =N30*INDEX(Settings!$H$4:$H$9,MATCH($E30,Settings!$F$4:$F$9,0)) | P30: LOW | Q30: Open battle Sauls vs Zvada; avoid
A31: 207 | B31: K29 | C31: Chris Boswell | D31: PIT | E31: K | I31: 25 | J31: 36 | M31: =F31*Settings!$B$4+G31*Settings!$B$5+H31*Settings!$B$6+I31*Settings!$B$7+J31*Settings!$B$8+K31*Settings!$B$9+L31*Settings!$B$10 | N31: =M31-INDEX(Settings!$G$4:$G$9,MATCH($E31,Settings!$F$4:$F$9,0)) | O31: =N31*INDEX(Settings!$H$4:$H$9,MATCH($E31,Settings!$F$4:$F$9,0)) | P31: MEDIUM
A32: 219 | B32: K30 | C32: Ryan Fitzgerald | D32: CAR | E32: K | I32: 24 | J32: 34 | M32: =F32*Settings!$B$4+G32*Settings!$B$5+H32*Settings!$B$6+I32*Settings!$B$7+J32*Settings!$B$8+K32*Settings!$B$9+L32*Settings!$B$10 | N32: =M32-INDEX(Settings!$G$4:$G$9,MATCH($E32,Settings!$F$4:$F$9,0)) | O32: =N32*INDEX(Settings!$H$4:$H$9,MATCH($E32,Settings!$F$4:$F$9,0)) | P32: LOW
A33: 234 | B33: K31 | C33: Matt Gay | D33: LV | E33: K | I33: 23 | J33: 32 | M33: =F33*Settings!$B$4+G33*Settings!$B$5+H33*Settings!$B$6+I33*Settings!$B$7+J33*Settings!$B$8+K33*Settings!$B$9+L33*Settings!$B$10 | N33: =M33-INDEX(Settings!$G$4:$G$9,MATCH($E33,Settings!$F$4:$F$9,0)) | O33: =N33*INDEX(Settings!$H$4:$H$9,MATCH($E33,Settings!$F$4:$F$9,0)) | P33: MEDIUM | Q33: LV 5.5 win total
A34: 235 | B34: K32 | C34: Andre Szmyt | D34: CLE | E34: K | I34: 23 | J34: 32 | M34: =F34*Settings!$B$4+G34*Settings!$B$5+H34*Settings!$B$6+I34*Settings!$B$7+J34*Settings!$B$8+K34*Settings!$B$9+L34*Settings!$B$10 | N34: =M34-INDEX(Settings!$G$4:$G$9,MATCH($E34,Settings!$F$4:$F$9,0)) | O34: =N34*INDEX(Settings!$H$4:$H$9,MATCH($E34,Settings!$F$4:$F$9,0)) | P34: LOW | Q34: CLE 7.8 win total

Sheet DEF
A1: DEF — ranked by projected points
A2: Rank | B2: Pos | C2: Player | D2: Tm | E2: P | F2: PassTD | G2: RushTD | H2: RecTD | I2: FG | J2: PAT | K2: DefTD | L2: Saf | M2: Points | N2: VOR | O2: Adj VOR | P2: Conf | Q2: Notes
A3: 85 | B3: DST1 | C3: Seahawks D/ST | D3: SEA | E3: DST | K3: 3.47 | L3: 0.5 | M3: =F3*Settings!$B$4+G3*Settings!$B$5+H3*Settings!$B$6+I3*Settings!$B$7+J3*Settings!$B$8+K3*Settings!$B$9+L3*Settings!$B$10 | N3: =M3-INDEX(Settings!$G$4:$G$9,MATCH($E3,Settings!$F$4:$F$9,0)) | O3: =N3*INDEX(Settings!$H$4:$H$9,MATCH($E3,Settings!$F$4:$F$9,0)) | P3: MEDIUM | Q3: Only team with 3+ def TD all 3 yrs; Tory Horton PR
A4: 88 | B4: DST2 | C4: Cowboys D/ST | D4: DAL | E4: DST | K4: 3.14 | L4: 0.45 | M4: =F4*Settings!$B$4+G4*Settings!$B$5+H4*Settings!$B$6+I4*Settings!$B$7+J4*Settings!$B$8+K4*Settings!$B$9+L4*Settings!$B$10 | N4: =M4-INDEX(Settings!$G$4:$G$9,MATCH($E4,Settings!$F$4:$F$9,0)) | O4: =N4*INDEX(Settings!$H$4:$H$9,MATCH($E4,Settings!$F$4:$F$9,0)) | P4: MEDIUM | Q4: KaVontae Turpin led NFL KR yds 2025
A5: 95 | B5: DST3 | C5: Texans D/ST | D5: HOU | E5: DST | K5: 2.79 | L5: 0.65 | M5: =F5*Settings!$B$4+G5*Settings!$B$5+H5*Settings!$B$6+I5*Settings!$B$7+J5*Settings!$B$8+K5*Settings!$B$9+L5*Settings!$B$10 | N5: =M5-INDEX(Settings!$G$4:$G$9,MATCH($E5,Settings!$F$4:$F$9,0)) | O5: =N5*INDEX(Settings!$H$4:$H$9,MATCH($E5,Settings!$F$4:$F$9,0)) | P5: MEDIUM | Q5: 3 FR TD in 2025; elite pass rush; weak returns
A6: 96 | B6: DST4 | C6: Browns D/ST | D6: CLE | E6: DST | K6: 2.79 | L6: 0.6 | M6: =F6*Settings!$B$4+G6*Settings!$B$5+H6*Settings!$B$6+I6*Settings!$B$7+J6*Settings!$B$8+K6*Settings!$B$9+L6*Settings!$B$10 | N6: =M6-INDEX(Settings!$G$4:$G$9,MATCH($E6,Settings!$F$4:$F$9,0)) | O6: =N6*INDEX(Settings!$H$4:$H$9,MATCH($E6,Settings!$F$4:$F$9,0)) | P6: MEDIUM | Q6: 3 INT TD on only 11 INTs; bad offense = more snaps
A7: 97 | B7: DST5 | C7: Broncos D/ST | D7: DEN | E7: DST | K7: 2.77 | L7: 0.65 | M7: =F7*Settings!$B$4+G7*Settings!$B$5+H7*Settings!$B$6+I7*Settings!$B$7+J7*Settings!$B$8+K7*Settings!$B$9+L7*Settings!$B$10 | N7: =M7-INDEX(Settings!$G$4:$G$9,MATCH($E7,Settings!$F$4:$F$9,0)) | O7: =N7*INDEX(Settings!$H$4:$H$9,MATCH($E7,Settings!$F$4:$F$9,0)) | P7: MEDIUM | Q7: Marvin Mims led PR yds 2025
A8: 98 | B8: DST6 | C8: Vikings D/ST | D8: MIN | E8: DST | K8: 2.77 | L8: 0.6 | M8: =F8*Settings!$B$4+G8*Settings!$B$5+H8*Settings!$B$6+I8*Settings!$B$7+J8*Settings!$B$8+K8*Settings!$B$9+L8*Settings!$B$10 | N8: =M8-INDEX(Settings!$G$4:$G$9,MATCH($E8,Settings!$F$4:$F$9,0)) | O8: =N8*INDEX(Settings!$H$4:$H$9,MATCH($E8,Settings!$F$4:$F$9,0)) | P8: MEDIUM | Q8: Led NFL forced fumbles 2025
A9: 99 | B9: DST7 | C9: Bills D/ST | D9: BUF | E9: DST | K9: 2.77 | L9: 0.5 | M9: =F9*Settings!$B$4+G9*Settings!$B$5+H9*Settings!$B$6+I9*Settings!$B$7+J9*Settings!$B$8+K9*Settings!$B$9+L9*Settings!$B$10 | N9: =M9-INDEX(Settings!$G$4:$G$9,MATCH($E9,Settings!$F$4:$F$9,0)) | O9: =N9*INDEX(Settings!$H$4:$H$9,MATCH($E9,Settings!$F$4:$F$9,0)) | P9: MEDIUM | Q9: Consistent 2-3 def TD/yr
A10: 101 | B10: DST8 | C10: Jaguars D/ST | D10: JAX | E10: DST | K10: 2.63 | L10: 0.55 | M10: =F10*Settings!$B$4+G10*Settings!$B$5+H10*Settings!$B$6+I10*Settings!$B$7+J10*Settings!$B$8+K10*Settings!$B$9+L10*Settings!$B$10 | N10: =M10-INDEX(Settings!$G$4:$G$9,MATCH($E10,Settings!$F$4:$F$9,0)) | O10: =N10*INDEX(Settings!$H$4:$H$9,MATCH($E10,Settings!$F$4:$F$9,0)) | P10: MEDIUM | Q10: Parker Washington 3 PR TD in 2 yrs
A11: 104 | B11: DST9 | C11: Falcons D/ST | D11: ATL | E11: DST | K11: 2.6 | L11: 0.5 | M11: =F11*Settings!$B$4+G11*Settings!$B$5+H11*Settings!$B$6+I11*Settings!$B$7+J11*Settings!$B$8+K11*Settings!$B$9+L11*Settings!$B$10 | N11: =M11-INDEX(Settings!$G$4:$G$9,MATCH($E11,Settings!$F$4:$F$9,0)) | O11: =N11*INDEX(Settings!$H$4:$H$9,MATCH($E11,Settings!$F$4:$F$9,0)) | P11: MEDIUM | Q11: 4 def TD in 2024; Branch return upside
A12: 105 | B12: DST10 | C12: Steelers D/ST | D12: PIT | E12: DST | K12: 2.45 | L12: 0.6 | M12: =F12*Settings!$B$4+G12*Settings!$B$5+H12*Settings!$B$6+I12*Settings!$B$7+J12*Settings!$B$8+K12*Settings!$B$9+L12*Settings!$B$10 | N12: =M12-INDEX(Settings!$G$4:$G$9,MATCH($E12,Settings!$F$4:$F$9,0)) | O12: =N12*INDEX(Settings!$H$4:$H$9,MATCH($E12,Settings!$F$4:$F$9,0)) | P12: MEDIUM | Q12: 3 def TD 2025
A13: 106 | B13: DST11 | C13: Patriots D/ST | D13: NE | E13: DST | K13: 2.47 | L13: 0.5 | M13: =F13*Settings!$B$4+G13*Settings!$B$5+H13*Settings!$B$6+I13*Settings!$B$7+J13*Settings!$B$8+K13*Settings!$B$9+L13*Settings!$B$10 | N13: =M13-INDEX(Settings!$G$4:$G$9,MATCH($E13,Settings!$F$4:$F$9,0)) | O13: =N13*INDEX(Settings!$H$4:$H$9,MATCH($E13,Settings!$F$4:$F$9,0)) | P13: MEDIUM | Q13: Marcus Jones 2 PR TD 2025; best PR unit
A14: 107 | B14: DST12 | C14: Raiders D/ST | D14: LV | E14: DST | K14: 2.45 | L14: 0.55 | M14: =F14*Settings!$B$4+G14*Settings!$B$5+H14*Settings!$B$6+I14*Settings!$B$7+J14*Settings!$B$8+K14*Settings!$B$9+L14*Settings!$B$10 | N14: =M14-INDEX(Settings!$G$4:$G$9,MATCH($E14,Settings!$F$4:$F$9,0)) | O14: =N14*INDEX(Settings!$H$4:$H$9,MATCH($E14,Settings!$F$4:$F$9,0)) | P14: LOW | Q14: 5 def TD in 2023 then 1 then 0
A15: 108 | B15: DST13 | C15: Colts D/ST | D15: IND | E15: DST | K15: 2.45 | L15: 0.5 | M15: =F15*Settings!$B$4+G15*Settings!$B$5+H15*Settings!$B$6+I15*Settings!$B$7+J15*Settings!$B$8+K15*Settings!$B$9+L15*Settings!$B$10 | N15: =M15-INDEX(Settings!$G$4:$G$9,MATCH($E15,Settings!$F$4:$F$9,0)) | O15: =N15*INDEX(Settings!$H$4:$H$9,MATCH($E15,Settings!$F$4:$F$9,0)) | P15: MEDIUM
A16: 109 | B16: DST14 | C16: Ravens D/ST | D16: BAL | E16: DST | K16: 2.43 | L16: 0.55 | M16: =F16*Settings!$B$4+G16*Settings!$B$5+H16*Settings!$B$6+I16*Settings!$B$7+J16*Settings!$B$8+K16*Settings!$B$9+L16*Settings!$B$10 | N16: =M16-INDEX(Settings!$G$4:$G$9,MATCH($E16,Settings!$F$4:$F$9,0)) | O16: =N16*INDEX(Settings!$H$4:$H$9,MATCH($E16,Settings!$F$4:$F$9,0)) | P16: MEDIUM | Q16: Steady 1-2/yr
A17: 110 | B17: DST15 | C17: Bears D/ST | D17: CHI | E17: DST | K17: 2.43 | L17: 0.5 | M17: =F17*Settings!$B$4+G17*Settings!$B$5+H17*Settings!$B$6+I17*Settings!$B$7+J17*Settings!$B$8+K17*Settings!$B$9+L17*Settings!$B$10 | N17: =M17-INDEX(Settings!$G$4:$G$9,MATCH($E17,Settings!$F$4:$F$9,0)) | O17: =N17*INDEX(Settings!$H$4:$H$9,MATCH($E17,Settings!$F$4:$F$9,0)) | P17: MEDIUM | Q17: Led NFL 23 INTs 2025
A18: 118 | B18: DST16 | C18: Giants D/ST | D18: NYG | E18: DST | K18: 2.27 | L18: 0.6 | M18: =F18*Settings!$B$4+G18*Settings!$B$5+H18*Settings!$B$6+I18*Settings!$B$7+J18*Settings!$B$8+K18*Settings!$B$9+L18*Settings!$B$10 | N18: =M18-INDEX(Settings!$G$4:$G$9,MATCH($E18,Settings!$F$4:$F$9,0)) | O18: =N18*INDEX(Settings!$H$4:$H$9,MATCH($E18,Settings!$F$4:$F$9,0)) | P18: LOW | Q18: Elite pass rush drives safeties
A19: 119 | B19: DST17 | C19: Jets D/ST | D19: NYJ | E19: DST | K19: 2.3 | L19: 0.45 | M19: =F19*Settings!$B$4+G19*Settings!$B$5+H19*Settings!$B$6+I19*Settings!$B$7+J19*Settings!$B$8+K19*Settings!$B$9+L19*Settings!$B$10 | N19: =M19-INDEX(Settings!$G$4:$G$9,MATCH($E19,Settings!$F$4:$F$9,0)) | O19: =N19*INDEX(Settings!$H$4:$H$9,MATCH($E19,Settings!$F$4:$F$9,0)) | P19: LOW | Q19: Best return duo; defense contributes nothing
A20: 120 | B20: DST18 | C20: Titans D/ST | D20: TEN | E20: DST | K20: 2.3 | L20: 0.4 | M20: =F20*Settings!$B$4+G20*Settings!$B$5+H20*Settings!$B$6+I20*Settings!$B$7+J20*Settings!$B$8+K20*Settings!$B$9+L20*Settings!$B$10 | N20: =M20-INDEX(Settings!$G$4:$G$9,MATCH($E20,Settings!$F$4:$F$9,0)) | O20: =N20*INDEX(Settings!$H$4:$H$9,MATCH($E20,Settings!$F$4:$F$9,0)) | P20: LOW | Q20: Chimere Dike 2 PR TD 2025; pure return play
A21: 121 | B21: DST19 | C21: New Orleans D/ST | D21: NO | E21: DST | K21: 2.28 | L21: 0.45 | M21: =F21*Settings!$B$4+G21*Settings!$B$5+H21*Settings!$B$6+I21*Settings!$B$7+J21*Settings!$B$8+K21*Settings!$B$9+L21*Settings!$B$10 | N21: =M21-INDEX(Settings!$G$4:$G$9,MATCH($E21,Settings!$F$4:$F$9,0)) | O21: =N21*INDEX(Settings!$H$4:$H$9,MATCH($E21,Settings!$F$4:$F$9,0)) | P21: LOW | Q21: 3 def TD 2025
A22: 122 | B22: DST20 | C22: Bengals D/ST | D22: CIN | E22: DST | K22: 2.27 | L22: 0.45 | M22: =F22*Settings!$B$4+G22*Settings!$B$5+H22*Settings!$B$6+I22*Settings!$B$7+J22*Settings!$B$8+K22*Settings!$B$9+L22*Settings!$B$10 | N22: =M22-INDEX(Settings!$G$4:$G$9,MATCH($E22,Settings!$F$4:$F$9,0)) | O22: =N22*INDEX(Settings!$H$4:$H$9,MATCH($E22,Settings!$F$4:$F$9,0)) | P22: MEDIUM | Q22: Charlie Jones KR TD in both 2024 and 2025
A23: 123 | B23: DST21 | C23: Dolphins D/ST | D23: MIA | E23: DST | K23: 2.27 | L23: 0.4 | M23: =F23*Settings!$B$4+G23*Settings!$B$5+H23*Settings!$B$6+I23*Settings!$B$7+J23*Settings!$B$8+K23*Settings!$B$9+L23*Settings!$B$10 | N23: =M23-INDEX(Settings!$G$4:$G$9,MATCH($E23,Settings!$F$4:$F$9,0)) | O23: =N23*INDEX(Settings!$H$4:$H$9,MATCH($E23,Settings!$F$4:$F$9,0)) | P23: LOW | Q23: 0 def TD in 2024 AND 2025
A24: 125 | B24: DST22 | C24: Panthers D/ST | D24: CAR | E24: DST | K24: 2.12 | L24: 0.45 | M24: =F24*Settings!$B$4+G24*Settings!$B$5+H24*Settings!$B$6+I24*Settings!$B$7+J24*Settings!$B$8+K24*Settings!$B$9+L24*Settings!$B$10 | N24: =M24-INDEX(Settings!$G$4:$G$9,MATCH($E24,Settings!$F$4:$F$9,0)) | O24: =N24*INDEX(Settings!$H$4:$H$9,MATCH($E24,Settings!$F$4:$F$9,0)) | P24: LOW
A25: 126 | B25: DST23 | C25: Buccaneers D/ST | D25: TB | E25: DST | K25: 2.12 | L25: 0.45 | M25: =F25*Settings!$B$4+G25*Settings!$B$5+H25*Settings!$B$6+I25*Settings!$B$7+J25*Settings!$B$8+K25*Settings!$B$9+L25*Settings!$B$10 | N25: =M25-INDEX(Settings!$G$4:$G$9,MATCH($E25,Settings!$F$4:$F$9,0)) | O25: =N25*INDEX(Settings!$H$4:$H$9,MATCH($E25,Settings!$F$4:$F$9,0)) | P25: MEDIUM
A26: 127 | B26: DST24 | C26: Chiefs D/ST | D26: KC | E26: DST | K26: 2.1 | L26: 0.5 | M26: =F26*Settings!$B$4+G26*Settings!$B$5+H26*Settings!$B$6+I26*Settings!$B$7+J26*Settings!$B$8+K26*Settings!$B$9+L26*Settings!$B$10 | N26: =M26-INDEX(Settings!$G$4:$G$9,MATCH($E26,Settings!$F$4:$F$9,0)) | O26: =N26*INDEX(Settings!$H$4:$H$9,MATCH($E26,Settings!$F$4:$F$9,0)) | P26: MEDIUM | Q26: 0 def TD in 2025; low variance
A27: 130 | B27: DST25 | C27: Eagles D/ST | D27: PHI | E27: DST | K27: 2.03 | L27: 0.6 | M27: =F27*Settings!$B$4+G27*Settings!$B$5+H27*Settings!$B$6+I27*Settings!$B$7+J27*Settings!$B$8+K27*Settings!$B$9+L27*Settings!$B$10 | N27: =M27-INDEX(Settings!$G$4:$G$9,MATCH($E27,Settings!$F$4:$F$9,0)) | O27: =N27*INDEX(Settings!$H$4:$H$9,MATCH($E27,Settings!$F$4:$F$9,0)) | P27: MEDIUM | Q27: TRAP: great real defense but no return game
A28: 131 | B28: DST26 | C28: 49ers D/ST | D28: SF | E28: DST | K28: 1.95 | L28: 0.55 | M28: =F28*Settings!$B$4+G28*Settings!$B$5+H28*Settings!$B$6+I28*Settings!$B$7+J28*Settings!$B$8+K28*Settings!$B$9+L28*Settings!$B$10 | N28: =M28-INDEX(Settings!$G$4:$G$9,MATCH($E28,Settings!$F$4:$F$9,0)) | O28: =N28*INDEX(Settings!$H$4:$H$9,MATCH($E28,Settings!$F$4:$F$9,0)) | P28: MEDIUM | Q28: Exactly 1 def TD each of last 3 yrs
A29: 132 | B29: DST27 | C29: Cardinals D/ST | D29: ARI | E29: DST | K29: 1.95 | L29: 0.5 | M29: =F29*Settings!$B$4+G29*Settings!$B$5+H29*Settings!$B$6+I29*Settings!$B$7+J29*Settings!$B$8+K29*Settings!$B$9+L29*Settings!$B$10 | N29: =M29-INDEX(Settings!$G$4:$G$9,MATCH($E29,Settings!$F$4:$F$9,0)) | O29: =N29*INDEX(Settings!$H$4:$H$9,MATCH($E29,Settings!$F$4:$F$9,0)) | P29: LOW
A30: 134 | B30: DST28 | C30: Rams D/ST | D30: LAR | E30: DST | K30: 1.87 | L30: 0.5 | M30: =F30*Settings!$B$4+G30*Settings!$B$5+H30*Settings!$B$6+I30*Settings!$B$7+J30*Settings!$B$8+K30*Settings!$B$9+L30*Settings!$B$10 | N30: =M30-INDEX(Settings!$G$4:$G$9,MATCH($E30,Settings!$F$4:$F$9,0)) | O30: =N30*INDEX(Settings!$H$4:$H$9,MATCH($E30,Settings!$F$4:$F$9,0)) | P30: MEDIUM | Q30: Weak returners
A31: 139 | B31: DST29 | C31: Lions D/ST | D31: DET | E31: DST | K31: 1.78 | L31: 0.45 | M31: =F31*Settings!$B$4+G31*Settings!$B$5+H31*Settings!$B$6+I31*Settings!$B$7+J31*Settings!$B$8+K31*Settings!$B$9+L31*Settings!$B$10 | N31: =M31-INDEX(Settings!$G$4:$G$9,MATCH($E31,Settings!$F$4:$F$9,0)) | O31: =N31*INDEX(Settings!$H$4:$H$9,MATCH($E31,Settings!$F$4:$F$9,0)) | P31: MEDIUM | Q31: Only 2 def TD in 3 seasons
A32: 140 | B32: DST30 | C32: Commanders D/ST | D32: WAS | E32: DST | K32: 1.77 | L32: 0.4 | M32: =F32*Settings!$B$4+G32*Settings!$B$5+H32*Settings!$B$6+I32*Settings!$B$7+J32*Settings!$B$8+K32*Settings!$B$9+L32*Settings!$B$10 | N32: =M32-INDEX(Settings!$G$4:$G$9,MATCH($E32,Settings!$F$4:$F$9,0)) | O32: =N32*INDEX(Settings!$H$4:$H$9,MATCH($E32,Settings!$F$4:$F$9,0)) | P32: LOW | Q32: 1 def TD in 3 years
A33: 141 | B33: DST31 | C33: Packers D/ST | D33: GB | E33: DST | K33: 1.7 | L33: 0.55 | M33: =F33*Settings!$B$4+G33*Settings!$B$5+H33*Settings!$B$6+I33*Settings!$B$7+J33*Settings!$B$8+K33*Settings!$B$9+L33*Settings!$B$10 | N33: =M33-INDEX(Settings!$G$4:$G$9,MATCH($E33,Settings!$F$4:$F$9,0)) | O33: =N33*INDEX(Settings!$H$4:$H$9,MATCH($E33,Settings!$F$4:$F$9,0)) | P33: MEDIUM | Q33: 0 def TD 2025; poor returner
A34: 142 | B34: DST32 | C34: Chargers D/ST | D34: LAC | E34: DST | K34: 1.62 | L34: 0.5 | M34: =F34*Settings!$B$4+G34*Settings!$B$5+H34*Settings!$B$6+I34*Settings!$B$7+J34*Settings!$B$8+K34*Settings!$B$9+L34*Settings!$B$10 | N34: =M34-INDEX(Settings!$G$4:$G$9,MATCH($E34,Settings!$F$4:$F$9,0)) | O34: =N34*INDEX(Settings!$H$4:$H$9,MATCH($E34,Settings!$F$4:$F$9,0)) | P34: MEDIUM | Q34: 1 def TD in 3 seasons; 19 INTs to 0 INT TD

Sheet Strategy
A1: How this format differs from normal fantasy
A2: # | B2: Principle | C2: Why
A3: 1 | B3: Rushing QBs are the single biggest edge | C3: A rushing TD (6) is worth double a passing TD (3). Josh Allen projects for 153 points — 30 clear of QB2 and a bigger gap than QB2-to-QB12. He is a legitimate 1.01 in this format. After him, prioritize rushing floor over passing volume every time.
A4: 2 | B4: Draft your kicker around round 2 | C4: Counterintuitive but real. Kickers have the highest raw VOR of any position after Allen, because FG x 3 produces huge absolute totals. BUT kicker projections are the least reliable of any position, so the risk-adjusted board slots K1 near pick 17 rather than pick 4. That is still four to six rounds earlier than anyone else in your league will move.
A5: 3 | B5: Target offenses that stall, not offenses that score | C5: For kickers only. A drive ending in a FG pays 3; a drive ending in a TD pays the kicker 1. Houston (52 FGA) is the ideal kicker offense. Buffalo (21 FGA) is the worst.
A6: 4 | B6: Chase the goal-line role, not the workload | C6: Yardage is worth nothing. A short-yardage specialist who scores 10 times beats a 1,400-yard back who scores 5. Identify who gets the ball inside the 5 in every backfield — that is the whole RB position.
A7: 5 | B7: Stream D/ST, do not draft one early | C7: The D1-to-D32 spread is only 11 points, versus 66 for kickers. With no sacks or points-allowed scoring, defenses only score on return/defensive TDs — a stat that barely correlates year to year. Take one in the last round. If your roster allows, a second kicker is worth more than a second defense.
A8: 6 | B8: Punt returners matter more than pass rushers | C8: Punt return TDs jumped from 6 to 15 league-wide in 2025 while kick return TDs fell. When you do pick a defense, buy the return game (SEA, DAL, NE, NYJ, TEN) over the conventional 'elite defense' (PHI).
A9: 7 | B9: Fade elite possession receivers | C9: Target volume is worth nothing without the end zone. Prioritize contested-catch and red-zone bodies. Note Davante Adams (LAR) projects for ~10 receiving TDs as the Rams' goal-line target — WR2 overall here despite a modest standard-league ADP.

Sheet Sleepers
A1: Players the projections systematically underrate
A2: Player | B2: Tm | C2: Pos | D2: Why he is undervalued in a TD-only league
A3: Sean Tucker | B3: TB | C3: RB | D3: Owns the Tampa goal line. Bucky Irving had ZERO carries inside the 5 in 2025; Tucker took nearly all of them and scored 8 TDs, 6 in his final 8 games. TB re-signed him specifically for that role. His ~2.8 projected TDs is a model artifact of low carry volume. Biggest value in the format.
A4: Jaxson Dart | B4: NYG | C4: QB | D4: Grades QB8 on ~6 rushing TDs (9 as a rookie, 2nd-highest designed-rush share among QBs). Rushing TDs are worth 2x passing TDs here. Caveat: new HC John Harbaugh spent a decade teaching Lamar Jackson to slide — highest-variance pick on the board.
A5: Daniel Jones | B5: IND | C5: QB | D5: Clay projects 6 rushing TDs, Razzball 7.3. Grades QB17 in this format. Nobody drafts him for that.
A6: Ka'imi Fairbairn | B6: HOU | C6: K | D6: Purest FG-lean in the league (~50% of value from FGs, not PATs). Houston led the NFL with 52 FG attempts in 2025 because the offense stalls in the red zone — exactly what you want when a FG is worth 3x a PAT.
A7: Daniel Carlson | B7: NO | C7: K | D7: Signed Aug 24, 2026 — every published projection was built on Charlie Smyth and is stale. New Orleans took 42 FG attempts in 2025 (T-3rd) at a league-worst 71.4%. An accurate kicker on that volume is unpriced.
A8: Chris Rodriguez Jr. | B8: JAX | C8: RB | D8: Hand-picked by Liam Coen as the goal-line back over Bhayshul Tuten. Pure TD specialist, free in drafts.
A9: Justin Fields | B9: KC | C9: QB | D9: Best handcuff in the format: a rushing QB sitting behind Mahomes, who is coming off ACL+LCL surgery and has not played a preseason snap.
A10: Malik Willis | B10: MIA | C10: QB | D10: Pure lottery ticket. Yahoo projects 7 rushing TDs (would be 4th among QBs), Razzball 2.8. If Miami uses him on designed goal-line runs he is a top-15 QB from an undrafted price.

Sheet Traps
A1: Players who cost more than they are worth here
A2: Player | B2: Tm | C2: Pos | D2: Why to fade
A3: Bucky Irving | B3: TB | C3: RB | D3: Zero carries inside the 5-yard line in 2025. Costs a real pick and does not get the goal line. Sean Tucker does.
A4: Saquon Barkley | B4: PHI | C4: RB | D4: Jalen Hurts vultures ~8.5 rushing TDs on the tush push, which survived the 2026 rules vote. Barkley's ADP does not price this in. (James Cook has the same Josh Allen problem, but his 10.5 Vegas line already accounts for it.)
A5: Bijan Robinson | B5: ATL | C5: RB | D5: Took only 48% of Atlanta's inside-5 carries in 2025, and the team signed Brian Robinson Jr. A committee back at a bell-cow price.
A6: Tyler Bass | B6: BUF | C6: K | D6: Buffalo attempted a league-low 21 field goals in 2025 — they score touchdowns instead. Second-worst FG lean in the league. Fine in standard formats, bad here.
A7: Eagles D/ST | B7: PHI | C7: DST | D7: Will be top-5 in every conventional D/ST ranking, which is built on sacks and points allowed — both worth ZERO in this league. No return threat and only 5 defensive TDs in three years. Ranks 25th here.
A8: Matthew Stafford | B8: LAR | C8: QB | D8: 34 passing TDs but 0.5 rushing. Elite in standard leagues, mid-pack here because passing TDs are only worth 3.
A9: Jared Goff | B9: DET | C9: QB | D9: Same problem: 30 passing TDs, no rushing floor.
A10: Kyren Williams / Blake Corum | B10: LAR | C10: RB | D10: Literally alternate drives, and reporting says Davante Adams is the Rams' actual goal-line target — note Adams projects for ~10 receiving TDs.

Sheet Sources
A1: Where every number came from, and what is missing
A2: Category | B2: Detail
A3: Vegas — RB rushing TD O/U | B3: Nine real season-long lines: Henry 12.5, Taylor 11.5, Cook 10.5, Kyren Williams 9.5, Javonte Williams 9.5, Montgomery 7.5, Chase Brown 5.5, Achane 5.5, Mason 4.5. Books are LOWER than consensus on Chase Brown and Mason, HIGHER on Henry.
A4: Vegas — RB receiving TD O/U | B4: Three lines only: Gibbs O4.5, McCaffrey O4.5, Bijan O3.5.
A5: Vegas — QB passing TD O/U | B5: Four lines only: Allen O24.5, Prescott O27.5, Herbert O22.5, Stroud U22.5.
A6: Vegas — QB rushing TD | B6: NONE EXIST at any book. Confirmed. Since rushing TDs carry most of the weight for mobile QBs, this is the single largest uncertainty on the board.
A7: Vegas — WR/TE and kickers | B7: No usable season-long TD props found. Kicker futures are not posted by major books at all; only weekly in-season FG totals.
A8: Kalshi prediction markets | B8: Season rushing-TD ladders were pulled but DELIBERATELY EXCLUDED — zero volume, 20-40 cent spreads, and non-monotonic pricing (Henry's 12+ traded above his 10+). Used only as a sanity check on ordering. Raw data in data/raw/rb_sources/.
A9: QB projections | B9: ESPN/Mike Clay 2026 Projection Guide (updated 8/26/26, all 32 team pages parsed), Razzball, Yahoo, FFToday, Footballguys, CBS, FantasyPros.
A10: RB projections | B10: FFToday full 2026 table (94 RBs, rush/rec TD split) + ESPN projections API (102 RBs) as independent second source, plus Ourlads depth charts for goal-line roles.
A11: WR/TE projections | B11: FFToday 2026 tables + ESPN projections API, merged with name/team normalization. 81 of 117 players confirmed by both sources; the rest are single-source and flagged LOW confidence.
A12: Kicker projections | B12: CBS Sports 2026 season projections (FGM/XPM split for all 32 starters), cross-checked against FantasyPros top 10 and Draft Sharks. Supplemented with 2025 team FG attempts from NFL.com as the red-zone-stalling proxy.
A13: D/ST projections | B13: MODEL ESTIMATE, not sourced. Built from NFL.com three-year defensive TD history (2023-25) regressed 50% to the league mean of 1.6, plus a returner-quality adjustment and a flat blocked-kick term. Model totals 74 TDs vs. ~72 actual in 2025.
... A15: Reliability caveat | B15: Confidence flags mean 2+ sources agree within ~2 TDs. For deep backups that is a weak signal — two models agreeing a backup scores ~1 TD is not real information. Treat HIGH as meaningful only in the top ~45 at RB and top ~30 at WR.

Sheet Settings
A1: League Settings — edit the blue cells and every tab re-ranks
A3: SCORING | F3: Pos | G3: Replacement | H3: Reliability
A4: Passing TD | B4: 3 | F4: QB | G4: 95 | H4: 0.65
A5: Rushing TD | B5: 6 | F5: RB | G5: 45.6 | H5: 0.6
A6: Receiving TD | B6: 6 | F6: WR | G6: 36 | H6: 0.55
A7: Field Goal (any distance) | B7: 3 | F7: TE | G7: 25.1 | H7: 0.55
A8: Extra Point | B8: 1 | F8: K | G8: 131.67 | H8: 0.35
A9: Def/ST TD | B9: 6 | F9: DST | G9: 15.18 | H9: 0.2
A10: Safety | B10: 2
A12: Teams in league | B12: 12 | F12: Replacement level = mean points of the players just past the last startable slot
F13: at each position (12 teams x starters). Computed by rank.py; recomputed if you
F14: change the player pool. Starters: 1QB, 2RB, 2WR, 1TE, 1K, 1D/ST.
F16: Reliability = how much of a projected edge actually shows up in reality. These are
F17: JUDGMENT ESTIMATES, not fitted from data. Kicker FG totals and defensive/return TDs
F18: have very little year-over-year predictive power, so most of their apparent spread
F19: is noise; raw VOR badly overrates both. Set every value to 1.00 to see raw VOR.
F21: Blue cells are inputs. Black cells are formulas. Edit projections directly on any
F22: tab and Points/VOR/Adj VOR recalculate.
